{
  "type": "Feature",
  "properties": {
    "gn:admin1_code":"03",
    "gn:asciiname":"Senir",
    "gn:country_code":"IL",
    "gn:dem":307,
    "gn:feature_class":"P",
    "gn:feature_code":"STLMT",
    "gn:name":"Senir",
    "gn:population":0,
    "gn:timezone":"Asia/Damascus",
    "iso:country":"IL",
    "name:ces_x_preferred":[
        "Snir"
    ],
    "name:heb_x_preferred":[
        "\u05e9\u05e0\u05d9\u05e8"
    ],
    "name:nno_x_preferred":[
        "Snir"
    ],
    "name:pol_x_preferred":[
        "Senir"
    ],
    "wof:name":"Senir",
    "wof:placetype":"locality"
},
  "geometry": {"coordinates":[35.6773,33.24073],"type":"Point"}
}