{
  "type": "Feature",
  "properties": {
    "iso:country":"IL",
    "name:ara_x_preferred":[
        "\u0643\u0648\u0643\u0628 \u0623\u0628\u0648 \u0627\u0644\u0647\u064a\u062c\u0627\u0621"
    ],
    "name:ceb_x_preferred":[
        "Kaukab Ab\u016b el H\u012bj\u0101"
    ],
    "name:ces_x_preferred":[
        "Kaukab Abu al-Hid\u017ea"
    ],
    "name:eng_x_preferred":[
        "Kaukab Abu al-Hija"
    ],
    "name:eng_x_variant":[
        "Kawkab Abu-Al-Hij"
    ],
    "name:heb_x_preferred":[
        "\u05db\u05d0\u05d5\u05db\u05d1 \u05d0\u05d1\u05d5 \u05d0\u05dc-\u05d4\u05d9\u05d2'\u05d0"
    ],
    "name:heb_x_variant":[
        "\u05db\u05d5\u05db\u05d1 \u05d0\u05e0\u05d5 \u05d0\u05dc \u05d4\u05d9\u05d2\u2019\u05d0",
        "Kaukab Ab\u016b el H\u012bj\u0101",
        "Kawkab Ab\u016b el H\u012bj\u0101",
        "\u0643\u0648\u0643\u0628 \u0623\u0628\u0648 \u0627\u0644\u0647\u064a\u062c\u0627\u0621"
    ],
    "name:nld_x_preferred":[
        "Kaukab Abu al-Hija"
    ],
    "name:nno_x_preferred":[
        "Kaukab Abu al-Hija"
    ],
    "name:pol_x_preferred":[
        "Kaukab Abu al-Hid\u017ca"
    ],
    "name:rus_x_preferred":[
        "\u041a\u0430\u0443\u043a\u0430\u0431-\u0430\u0431\u0443-\u0430\u043b\u044c-\u0425\u0438\u0434\u0436\u0430"
    ],
    "name:rus_x_variant":[
        "Kawkab Abu-Al-Hij"
    ],
    "name:sco_x_preferred":[
        "Kaukab Abu al-Hija"
    ],
    "name:swe_x_preferred":[
        "Kaukab Ab\u016b el H\u012bj\u0101"
    ],
    "name:unk_x_variant":[
        "Kawkab"
    ],
    "qs:gn_country":"IL",
    "qs:gn_fcode":"PPL",
    "qs:gn_pop":2800,
    "qs:name":"Kaukab Abu el Hija",
    "qs:name_adm0":"Israel",
    "qs:name_adm1":"Northern",
    "qs:photos":0,
    "qs:photos_1k":0,
    "qs:photos_9k":1,
    "qs:photos_9r":1,
    "qs:photos_all":3,
    "qs:photos_sr":0,
    "qs:placetype":"Town",
    "qs:pop_sr":"4",
    "qs:woe_adm0":23424852,
    "wd:wordcount":1584,
    "wof:name":"Kaukab Abu el Hija",
    "wof:placetype":"locality",
    "wof:population":2800
},
  "geometry": {"coordinates":[35.24848,32.83155],"type":"Point"}
}