{
  "type": "Feature",
  "properties": {
    "gn:admin1_code":"02",
    "gn:asciiname":"Kefar Bilu",
    "gn:country_code":"IL",
    "gn:dem":76,
    "gn:feature_class":"P",
    "gn:feature_code":"PPL",
    "gn:name":"Kefar Bilu",
    "gn:population":0,
    "gn:timezone":"Asia/Jerusalem",
    "iso:country":"IL",
    "name:heb_x_preferred":[
        "\u05db\u05e4\u05e8 \u05d1\u05d9\u05dc\u05d5"
    ],
    "wof:name":"Kefar Bilu",
    "wof:placetype":"locality"
},
  "geometry": {"coordinates":[34.82108,31.87702],"type":"Point"}
}