{
  "type": "Feature",
  "properties": {
    "iso:country":"IL",
    "name:ces_x_preferred":[
        "Sanhedrija"
    ],
    "name:eng_x_preferred":[
        "Sanhedria"
    ],
    "name:fra_x_preferred":[
        "Sanh\u00e9driah"
    ],
    "name:heb_x_preferred":[
        "\u05e1\u05e0\u05d4\u05d3\u05e8\u05d9\u05d4"
    ],
    "name:ind_x_preferred":[
        "Sanhedria"
    ],
    "name:und_x_variant":[
        "Sanhedriyya"
    ],
    "qs:gn_country":"IL",
    "qs:gn_fcode":"PPLX",
    "qs:gn_pop":0,
    "qs:name":"Sanhedria",
    "qs:name_adm0":"Palestine",
    "qs:name_adm1":"West Bank",
    "qs:photos":1,
    "qs:photos_1k":1,
    "qs:photos_9k":1,
    "qs:photos_9r":1,
    "qs:photos_all":1,
    "qs:photos_sr":1,
    "qs:placetype":"Suburb",
    "qs:pop_sr":"0",
    "qs:woe_adm0":28289408,
    "wd:wordcount":320,
    "wof:name":"Sanhedria",
    "wof:placetype":"neighbourhood"
},
  "geometry": {"coordinates":[35.21841,31.79711],"type":"Point"}
}