{
  "type": "Feature",
  "properties": {
    "iso:country":"IL",
    "name:ces_x_preferred":[
        "Menucha"
    ],
    "name:eng_x_preferred":[
        "Menuha"
    ],
    "name:heb_x_preferred":[
        "\u05de\u05e0\u05d5\u05d7\u05d4"
    ],
    "name:heb_x_variant":[
        "Menu\u1e96a"
    ],
    "name:kat_x_preferred":[
        "\u10db\u10d4\u10dc\u10d8\u10ee\u10d0"
    ],
    "name:nno_x_preferred":[
        "Menuha"
    ],
    "name:pol_x_preferred":[
        "Menuha"
    ],
    "name:und_x_variant":[
        "Gat 3A"
    ],
    "qs:gn_country":"IL",
    "qs:gn_fcode":"PPL",
    "qs:gn_pop":0,
    "qs:name":"Menuha",
    "qs:name_adm0":"Israel",
    "qs:name_adm1":"Southern",
    "qs:photos":7,
    "qs:photos_1k":1,
    "qs:photos_9k":1,
    "qs:photos_9r":1,
    "qs:photos_all":7,
    "qs:photos_sr":1,
    "qs:placetype":"Town",
    "qs:pop_sr":"0",
    "qs:woe_adm0":23424852,
    "wd:wordcount":214,
    "wof:name":"Menuha",
    "wof:placetype":"locality"
},
  "geometry": {"coordinates":[34.77693,31.6569],"type":"Point"}
}