{
  "type": "Feature",
  "properties": {
    "iso:country":"IL",
    "name:ara_x_preferred":[
        "\u0643\u0641\u0627\u0631 \u0633\u0627\u0628\u0627"
    ],
    "name:ces_x_preferred":[
        "Kfar Saba"
    ],
    "name:dan_x_preferred":[
        "Kfar Saba"
    ],
    "name:deu_x_preferred":[
        "Kfar Saba"
    ],
    "name:eng_x_historical":[
        "Kafr Saba",
        "Kef\u00e1r Saba",
        "Kefar Sava"
    ],
    "name:eng_x_preferred":[
        "Kafr Saba"
    ],
    "name:eng_x_variant":[
        "Kef\u00e1r Saba",
        "Kefar Sava",
        "Kfar Saba",
        "Kfar Sava"
    ],
    "name:epo_x_preferred":[
        "Kfar Saba"
    ],
    "name:est_x_preferred":[
        "Kfar Sava"
    ],
    "name:fas_x_preferred":[
        "\u06a9\u0641\u0627\u0631 \u0633\u0627\u0628\u0627"
    ],
    "name:fin_x_preferred":[
        "Kfar Saba"
    ],
    "name:fra_x_preferred":[
        "Kfar Saba"
    ],
    "name:heb_x_preferred":[
        "\u05db\u05e4\u05e8 \u05e1\u05d1\u05d0"
    ],
    "name:ind_x_preferred":[
        "Kefar Sava"
    ],
    "name:ita_x_preferred":[
        "Kfar Saba"
    ],
    "name:lit_x_preferred":[
        "Kfar Saba"
    ],
    "name:msa_x_preferred":[
        "Kefar Sava"
    ],
    "name:nld_x_preferred":[
        "Kefar Sava"
    ],
    "name:nno_x_preferred":[
        "Kfar Saba"
    ],
    "name:nor_x_preferred":[
        "Kfar Saba"
    ],
    "name:pol_x_preferred":[
        "Kefar Sawa"
    ],
    "name:por_x_preferred":[
        "Kfar Saba"
    ],
    "name:rus_x_preferred":[
        "\u041a\u0444\u0430\u0440-\u0421\u0430\u0432\u0430"
    ],
    "name:rus_x_variant":[
        "\u041a\u0435\u0444\u0430\u0440-\u0421\u0430\u0432\u0430"
    ],
    "name:sco_x_preferred":[
        "Kfar Saba"
    ],
    "name:spa_x_preferred":[
        "Kfar Saba"
    ],
    "name:srp_x_preferred":[
        "\u041a\u0444\u0430\u0440 \u0421\u0430\u0432\u0430"
    ],
    "name:swe_x_preferred":[
        "Kfar Saba"
    ],
    "name:tgl_x_preferred":[
        "Kfar Saba"
    ],
    "name:tur_x_preferred":[
        "Kfar Saba"
    ],
    "name:ukr_x_preferred":[
        "\u041a\u0444\u0430\u0440-\u0421\u0430\u0432\u0430"
    ],
    "name:urd_x_preferred":[
        "\u06a9\u0641\u0631 \u0633\u0628\u0627"
    ],
    "name:vie_x_preferred":[
        "Kfar Saba"
    ],
    "name:war_x_preferred":[
        "Kfar Saba"
    ],
    "name:yid_x_preferred":[
        "\u05db\u05e4\u05e8 \u05e1\u05d1\u05d0"
    ],
    "name:zho_x_preferred":[
        "\u5361\u6cd5\u85a9\u5df4"
    ],
    "qs:gn_country":"IL",
    "qs:gn_fcode":"PPL",
    "qs:gn_pop":80773,
    "qs:name":"Kfar Sava",
    "qs:name_adm0":"Israel",
    "qs:name_adm1":"Central",
    "qs:photos":3980,
    "qs:photos_1k":806,
    "qs:photos_9k":25,
    "qs:photos_9r":14,
    "qs:photos_all":5677,
    "qs:photos_sr":22,
    "qs:placetype":"Town",
    "qs:pop_sr":"8",
    "qs:woe_adm0":23424852,
    "wd:wordcount":2254,
    "wof:name":"Kfar Sava",
    "wof:placetype":"locality",
    "wof:population":80773
},
  "geometry": {"coordinates":[34.90694,32.175],"type":"Point"}
}