{
  "type": "Feature",
  "properties": {
    "gn:admin1_code":"03",
    "gn:asciiname":"Lahavot HaBashan",
    "gn:country_code":"IL",
    "gn:dem":90,
    "gn:feature_class":"P",
    "gn:feature_code":"PPL",
    "gn:name":"Lahavot HaBashan",
    "gn:population":0,
    "gn:timezone":"Asia/Jerusalem",
    "iso:country":"IL",
    "name:heb_x_preferred":[
        "\u05dc\u05d4\u05d1\u05d5\u05ea \u05d4\u05d1\u05e9\u05df"
    ],
    "name:und_x_variant":[
        "Ma\u2018ale Habashan",
        "Ma\u2018aleh Habashan",
        "Lahovot Habashan",
        "Lahavot HaBashan"
    ],
    "wof:name":"Lahavot HaBashan",
    "wof:placetype":"locality"
},
  "geometry": {"coordinates":[35.64678,33.14165999999999],"type":"Point"}
}