{
  "type": "Feature",
  "properties": {
    "gn:admin1_code":"02",
    "gn:asciiname":"Ganne Yohanan",
    "gn:country_code":"IL",
    "gn:dem":66,
    "gn:feature_class":"P",
    "gn:feature_code":"PPL",
    "gn:name":"Gann\u00e9 Yo\u1e96anan",
    "gn:population":0,
    "gn:timezone":"Asia/Jerusalem",
    "iso:country":"IL",
    "name:ces_x_preferred":[
        "Ganej Jochanan"
    ],
    "name:heb_x_preferred":[
        "\u05d2\u05e0\u05d9 \u05d9\u05d5\u05d7\u05e0\u05df"
    ],
    "name:nno_x_preferred":[
        "Ganei Yohanan"
    ],
    "name:pol_x_preferred":[
        "Ganne Jochanan"
    ],
    "name:und_x_variant":[
        "Ganne-Yona",
        "Ganne Yo\u1e96anan",
        "Gann\u00e9 Yo\u1e96anan"
    ],
    "wof:name":"Ganne Yohanan",
    "wof:placetype":"locality"
},
  "geometry": {"coordinates":[34.83643,31.85446],"type":"Point"}
}