{
  "type": "Feature",
  "properties": {
    "iso:country":"IL",
    "name:cat_x_preferred":[
        "Merom"
    ],
    "name:ces_x_preferred":[
        "Meron"
    ],
    "name:deu_x_preferred":[
        "Meron"
    ],
    "name:eng_x_preferred":[
        "Meron"
    ],
    "name:fas_x_preferred":[
        "\u0645\u0631\u0648\u0646"
    ],
    "name:fra_x_preferred":[
        "Meron"
    ],
    "name:heb_x_preferred":[
        "\u05de\u05d9\u05e8\u05d5\u05df"
    ],
    "name:jpn_x_preferred":[
        "\u30e1\u30ed\u30f3"
    ],
    "name:nld_x_preferred":[
        "Meron"
    ],
    "name:nno_x_preferred":[
        "Meron i Israel"
    ],
    "name:pol_x_preferred":[
        "Meron"
    ],
    "name:spa_x_preferred":[
        "Mer\u00f3n"
    ],
    "name:und_x_variant":[
        "Meiron"
    ],
    "name:yid_x_preferred":[
        "\u05de\u05d9\u05e8\u05d5\u05df"
    ],
    "qs:gn_country":"IL",
    "qs:gn_fcode":"PPL",
    "qs:gn_pop":0,
    "qs:name":"Meron",
    "qs:name_adm0":"Israel",
    "qs:name_adm1":"Northern",
    "qs:photos":340,
    "qs:photos_1k":69,
    "qs:photos_9k":2,
    "qs:photos_9r":5,
    "qs:photos_all":340,
    "qs:photos_sr":5,
    "qs:placetype":"Town",
    "qs:pop_sr":"0",
    "qs:woe_adm0":23424852,
    "wd:wordcount":2038,
    "wof:name":"Meron",
    "wof:placetype":"locality"
},
  "geometry": {"coordinates":[35.44087,32.9878],"type":"Point"}
}