{
  "type": "Feature",
  "properties": {
    "gn:admin1_code":"06",
    "gn:asciiname":"Bet Me'ir",
    "gn:country_code":"IL",
    "gn:dem":583,
    "gn:feature_class":"P",
    "gn:feature_code":"PPL",
    "gn:name":"Bet Me\u2019ir",
    "gn:population":0,
    "gn:timezone":"Asia/Jerusalem",
    "iso:country":"IL",
    "name:heb_x_preferred":[
        "\u05d1\u05d9\u05ea \u05de\u05d0\u05d9\u05e8"
    ],
    "name:und_x_variant":[
        "Beit Meir",
        "Beit Mahsir",
        "Beyt-Meyir",
        "Bayt Mahsir",
        "Bet Me\u2019ir"
    ],
    "wof:name":"Bet Me'ir",
    "wof:placetype":"locality"
},
  "geometry": {"coordinates":[35.03689,31.79393],"type":"Point"}
}