{
  "type": "Feature",
  "properties": {
    "gn:admin1_code":"06",
    "gn:asciiname":"Kefar Zahorim",
    "gn:country_code":"IL",
    "gn:dem":301,
    "gn:feature_class":"P",
    "gn:feature_code":"PPL",
    "gn:name":"Kefar \u1e94ahorim",
    "gn:population":0,
    "gn:timezone":"Asia/Jerusalem",
    "iso:country":"IL",
    "name:heb_x_preferred":[
        "Kefar \u1e94ahorim"
    ],
    "name:heb_x_variant":[
        "\u05db\u05e4\u05e8 \u05e6\u05d4\u05e8\u05d9\u05dd"
    ],
    "wof:name":"Kefar Zahorim",
    "wof:placetype":"locality"
},
  "geometry": {"coordinates":[34.92404000000001,31.62052000000001],"type":"Point"}
}