{
  "type": "Feature",
  "properties": {
    "gn:admin1_code":"03",
    "gn:asciiname":"Eshbal",
    "gn:country_code":"IL",
    "gn:dem":269,
    "gn:feature_class":"P",
    "gn:feature_code":"PPL",
    "gn:name":"Eshbal",
    "gn:population":0,
    "gn:timezone":"Asia/Jerusalem",
    "iso:country":"IL",
    "name:ces_x_preferred":[
        "E\u0161bal"
    ],
    "name:heb_x_preferred":[
        "Na\u1e96al Eshbar"
    ],
    "name:heb_x_variant":[
        "\u05e0\u05d7\u2019\u2019\u05dc \u05d0\u05e9\u05d1\u05dc",
        "\u05d0\u05e9\u05d1\u05dc"
    ],
    "name:nno_x_preferred":[
        "Eshbal"
    ],
    "name:pol_x_preferred":[
        "Eszbal"
    ],
    "wof:name":"Eshbal",
    "wof:placetype":"locality"
},
  "geometry": {"coordinates":[35.30553,32.87655],"type":"Point"}
}