{
  "type": "Feature",
  "properties": {
    "gn:admin1_code":"02",
    "gn:asciiname":"Tel Yizhaq",
    "gn:country_code":"IL",
    "gn:dem":43,
    "gn:feature_class":"P",
    "gn:feature_code":"PPL",
    "gn:name":"Tel Yi\u1e95\u1e96aq",
    "gn:population":0,
    "gn:timezone":"Asia/Jerusalem",
    "iso:country":"IL",
    "name:heb_x_preferred":[
        "Tel Yi\u1e95\u1e96aq"
    ],
    "name:heb_x_variant":[
        "\u05ea\u05dc \u05d9\u05e6\u05d7\u05e7",
        "Tel Yits\u1e96ak"
    ],
    "name:und_x_variant":[
        "Tel Yits-haq",
        "Tel Yi\u1e95\u1e96aq"
    ],
    "wof:name":"Tel Yizhaq",
    "wof:placetype":"locality"
},
  "geometry": {"coordinates":[34.87034,32.25327],"type":"Point"}
}