{
  "type": "Feature",
  "properties": {
    "iso:country":"IL",
    "name:ara_x_preferred":[
        "\u0628\u064a\u062a\u0633\u0631\u0648\u0646"
    ],
    "name:ces_x_preferred":[
        "Bicaron"
    ],
    "name:eng_x_preferred":[
        "Bitzaron"
    ],
    "name:heb_x_preferred":[
        "\u05d1\u05d9\u05e6\u05e8\u05d5\u05df"
    ],
    "name:nld_x_preferred":[
        "Bitzaron"
    ],
    "name:nno_x_preferred":[
        "Bitzaron"
    ],
    "name:pol_x_preferred":[
        "Biccaron"
    ],
    "name:pol_x_variant":[
        "Bicaron"
    ],
    "qs:gn_pop":0,
    "qs:name":"Bitsaron",
    "qs:name_adm0":"Israel",
    "qs:name_adm1":"Tel Aviv",
    "qs:photos":146,
    "qs:photos_1k":30,
    "qs:photos_9k":1,
    "qs:photos_9r":3,
    "qs:photos_all":146,
    "qs:photos_sr":3,
    "qs:placetype":"Suburb",
    "qs:pop_sr":"0",
    "qs:woe_adm0":23424852,
    "wd:wordcount":427,
    "wof:name":"Bitsaron",
    "wof:placetype":"neighbourhood"
},
  "geometry": {"coordinates":[34.794558,32.073234],"type":"Point"}
}