{
  "type": "Feature",
  "properties": {
    "gn:admin1_code":"02",
    "gn:asciiname":"Porat",
    "gn:country_code":"IL",
    "gn:dem":62,
    "gn:feature_class":"P",
    "gn:feature_code":"PPL",
    "gn:name":"Porat",
    "gn:population":0,
    "gn:timezone":"Asia/Jerusalem",
    "iso:country":"IL",
    "name:ces_x_preferred":[
        "Porat"
    ],
    "name:heb_x_preferred":[
        "\u05e4\u05d5\u05e8\u05ea"
    ],
    "name:nno_x_preferred":[
        "Porat"
    ],
    "name:pol_x_preferred":[
        "Porat"
    ],
    "wof:name":"Porat",
    "wof:placetype":"locality"
},
  "geometry": {"coordinates":[34.94874,32.27626],"type":"Point"}
}