{
  "type": "Feature",
  "properties": {
    "iso:country":"IL",
    "name:ara_x_preferred":[
        "\u0623\u0645\u0627\u062a\u0633\u064a\u0627"
    ],
    "name:ces_x_preferred":[
        "Amacja"
    ],
    "name:eng_x_preferred":[
        "Amatzia"
    ],
    "name:heb_x_preferred":[
        "\u05d0\u05de\u05e6\u05d9\u05d4"
    ],
    "name:heb_x_variant":[
        "Ama\u1e95ya"
    ],
    "name:nno_x_preferred":[
        "Amatzia i Israel"
    ],
    "name:nob_x_preferred":[
        "Amatzia i Israel"
    ],
    "name:nor_x_preferred":[
        "Amatzia i Israel"
    ],
    "name:pol_x_preferred":[
        "Amacja"
    ],
    "name:unk_x_variant":[
        "Amatsya"
    ],
    "qs:gn_country":"IL",
    "qs:gn_fcode":"PPL",
    "qs:gn_pop":0,
    "qs:name":"Amazya",
    "qs:name_adm0":"Israel",
    "qs:name_adm1":"Southern",
    "qs:photos":155,
    "qs:photos_1k":31,
    "qs:photos_9k":1,
    "qs:photos_9r":4,
    "qs:photos_all":155,
    "qs:photos_sr":4,
    "qs:placetype":"Town",
    "qs:pop_sr":"0",
    "qs:woe_adm0":23424852,
    "wd:wordcount":197,
    "wof:name":"Amazya",
    "wof:placetype":"locality"
},
  "geometry": {"coordinates":[34.91404,31.53248],"type":"Point"}
}