{
  "type": "Feature",
  "properties": {
    "gn:admin1_code":"06",
    "gn:asciiname":"Nahal Teqoa'",
    "gn:country_code":"IL",
    "gn:dem":624,
    "gn:feature_class":"P",
    "gn:feature_code":"STLMT",
    "gn:name":"Na\u1e96al Teqoa\u2018",
    "gn:population":0,
    "gn:timezone":"Asia/Hebron",
    "iso:country":"IL",
    "name:und_x_variant":[
        "Nahal Tekea",
        "Na\u1e96al Teqoa\u2018"
    ],
    "wof:name":"Nahal Teqoa'",
    "wof:placetype":"locality"
},
  "geometry": {"coordinates":[35.23333,31.65],"type":"Point"}
}