{
  "type": "Feature",
  "properties": {
    "iso:country":"IL",
    "name:ces_x_preferred":[
        "Bejt Jeho\u0161ua"
    ],
    "name:eng_x_preferred":[
        "Beit Yehoshua"
    ],
    "name:fra_x_preferred":[
        "Be\u00eft-Y\u00e9hoshoua"
    ],
    "name:heb_x_preferred":[
        "\u05d1\u05d9\u05ea \u05d9\u05d4\u05d5\u05e9\u05e2"
    ],
    "name:heb_x_variant":[
        "Bet Yehoshua\u2018"
    ],
    "name:nno_x_preferred":[
        "Beit Yehoshua"
    ],
    "name:pol_x_preferred":[
        "Beit Jehoszua"
    ],
    "name:swe_x_preferred":[
        "Bet Yehoshua\u2018"
    ],
    "name:unk_x_variant":[
        "Beit Yehoshua\u2018"
    ],
    "qs:gn_country":"IL",
    "qs:gn_fcode":"PPL",
    "qs:gn_pop":0,
    "qs:name":"Bet Yehoshua",
    "qs:name_adm0":"Israel",
    "qs:name_adm1":"Central",
    "qs:photos":79,
    "qs:photos_1k":16,
    "qs:photos_9k":1,
    "qs:photos_9r":3,
    "qs:photos_all":79,
    "qs:photos_sr":3,
    "qs:placetype":"Town",
    "qs:pop_sr":"0",
    "qs:woe_adm0":23424852,
    "wd:wordcount":161,
    "wof:name":"Bet Yehoshua",
    "wof:placetype":"locality"
},
  "geometry": {"coordinates":[34.86414,32.25942],"type":"Point"}
}