{
  "type": "Feature",
  "properties": {
    "gn:admin1_code":"01",
    "gn:asciiname":"Nevatim",
    "gn:country_code":"IL",
    "gn:dem":324,
    "gn:feature_class":"P",
    "gn:feature_code":"PPL",
    "gn:name":"Nevatim",
    "gn:population":0,
    "gn:timezone":"Asia/Jerusalem",
    "iso:country":"IL",
    "name:heb_x_preferred":[
        "\u05e0\u05d1\u05d8\u05d9\u05dd"
    ],
    "wof:name":"Nevatim",
    "wof:placetype":"locality"
},
  "geometry": {"coordinates":[34.88098,31.22417],"type":"Point"}
}