{
  "type": "Feature",
  "properties": {
    "iso:country":"IL",
    "name:ara_x_preferred":[
        "\u0623\u0628\u0648 \u063a\u0648\u0634"
    ],
    "name:bul_x_preferred":[
        "\u0410\u0431\u0443 \u0413\u043e\u0448"
    ],
    "name:cat_x_preferred":[
        "Abu Gosh"
    ],
    "name:ceb_x_preferred":[
        "Ab\u016b Ghaush"
    ],
    "name:ces_x_preferred":[
        "Abu Go\u0161"
    ],
    "name:che_x_preferred":[
        "\u0410\u0431\u0443-\u0413\u043e\u0448"
    ],
    "name:deu_x_preferred":[
        "Abu Gosch"
    ],
    "name:ell_x_preferred":[
        "\u0391\u03bc\u03c0\u03bf\u03cd \u0393\u03ba\u03bf\u03c2"
    ],
    "name:eng_x_preferred":[
        "Abu Ghosh"
    ],
    "name:fas_x_preferred":[
        "\u0627\u0628\u0648 \u063a\u0648\u0634"
    ],
    "name:fas_x_variant":[
        "\u0627\u0628\u0648 \u0642\u0627\u0634"
    ],
    "name:fin_x_preferred":[
        "Abu Ghosh"
    ],
    "name:fra_x_preferred":[
        "Abou Gosh"
    ],
    "name:glg_x_preferred":[
        "Abu Ghosh"
    ],
    "name:heb_x_preferred":[
        "\u05d0\u05d1\u05d5 \u05d2\u05d5\u05e9"
    ],
    "name:heb_x_variant":[
        "\u05d0\u05d1\u05d5 \u05e2\u2019\u05d5\u05e9"
    ],
    "name:jpn_x_preferred":[
        "\u30a2\u30d6\u30fb\u30b4\u30fc\u30b7\u30e5"
    ],
    "name:lad_x_preferred":[
        "Abu Gosh"
    ],
    "name:nld_x_preferred":[
        "Abu Ghosh"
    ],
    "name:nno_x_preferred":[
        "Abu Ghosh"
    ],
    "name:nor_x_preferred":[
        "Abu Ghosh"
    ],
    "name:pol_x_preferred":[
        "Abu Ghusz"
    ],
    "name:pol_x_variant":[
        "Abu Gosz"
    ],
    "name:por_x_preferred":[
        "Abu Ghosh"
    ],
    "name:rus_x_preferred":[
        "\u0410\u0431\u0443-\u0413\u043e\u0448"
    ],
    "name:sco_x_preferred":[
        "Abu Ghosh"
    ],
    "name:swe_x_preferred":[
        "Ab\u016b Ghaush"
    ],
    "name:ukr_x_preferred":[
        "\u0410\u0431\u0443-\u0490\u043e\u0448"
    ],
    "name:unk_x_variant":[
        "Kuryet el Enab"
    ],
    "name:urd_x_preferred":[
        "\u0627\u0628\u0648 \u063a\u0648\u0634"
    ],
    "qs:gn_country":"IL",
    "qs:gn_fcode":"PPL",
    "qs:gn_pop":5707,
    "qs:name":"Abu Ghaush",
    "qs:name_adm0":"Israel",
    "qs:name_adm1":"Jerusalem",
    "qs:photos":22,
    "qs:photos_1k":4,
    "qs:photos_9k":1,
    "qs:photos_9r":1,
    "qs:photos_all":22,
    "qs:photos_sr":1,
    "qs:placetype":"Town",
    "qs:pop_sr":"5",
    "qs:woe_adm0":23424852,
    "wd:wordcount":2556,
    "wof:name":"Abu Ghaush",
    "wof:placetype":"locality",
    "wof:population":5707
},
  "geometry": {"coordinates":[35.1093,31.80592],"type":"Point"}
}