{
  "type": "Feature",
  "properties": {
    "iso:country":"IL",
    "name:ces_x_preferred":[
        "Bnej Cijon"
    ],
    "name:cze_x_preferred":[
        "Bnej Cijon"
    ],
    "name:dut_x_preferred":[
        "Bnei Zion"
    ],
    "name:eng_x_preferred":[
        "Bnei Zion"
    ],
    "name:heb_x_preferred":[
        "\u05d1\u05e0\u05d9 \u05e6\u05d9\u05d5\u05df"
    ],
    "name:heb_x_variant":[
        "Ben\u00e9 \u1e94iyyon",
        "Ben\u00e9 Tsiyyon"
    ],
    "name:nno_x_preferred":[
        "Bnei Zion"
    ],
    "name:pol_x_preferred":[
        "Bnei Syjon"
    ],
    "name:spa_x_preferred":[
        "Bnei Zion"
    ],
    "name:unk_x_variant":[
        "Benei Tsiyon"
    ],
    "qs:gn_country":"IL",
    "qs:gn_fcode":"PPL",
    "qs:gn_pop":0,
    "qs:name":"Bene Ziyyon",
    "qs:name_adm0":"Israel",
    "qs:name_adm1":"Central",
    "qs:photos":672,
    "qs:photos_1k":136,
    "qs:photos_9k":3,
    "qs:photos_9r":5,
    "qs:photos_all":672,
    "qs:photos_sr":8,
    "qs:placetype":"Town",
    "qs:pop_sr":"0",
    "qs:woe_adm0":23424852,
    "wd:wordcount":164,
    "wof:name":"Bene Ziyyon",
    "wof:placetype":"locality"
},
  "geometry": {"coordinates":[34.86965,32.22121],"type":"Point"}
}