{
  "type": "Feature",
  "properties": {
    "gn:admin1_code":"01",
    "gn:asciiname":"Maslul",
    "gn:country_code":"IL",
    "gn:dem":113,
    "gn:feature_class":"P",
    "gn:feature_code":"PPL",
    "gn:name":"Maslul",
    "gn:population":0,
    "gn:timezone":"Asia/Jerusalem",
    "iso:country":"IL",
    "name:heb_x_preferred":[
        "\u05de\u05e1\u05dc\u05d5\u05dc"
    ],
    "wof:name":"Maslul",
    "wof:placetype":"locality"
},
  "geometry": {"coordinates":[34.59056,31.32485],"type":"Point"}
}