{
  "type": "Feature",
  "properties": {
    "gn:admin1_code":"03",
    "gn:asciiname":"Tal El",
    "gn:country_code":"IL",
    "gn:dem":149,
    "gn:feature_class":"P",
    "gn:feature_code":"PPL",
    "gn:name":"Tal El",
    "gn:population":0,
    "gn:timezone":"Asia/Jerusalem",
    "iso:country":"IL",
    "name:ces_x_preferred":[
        "Tal El"
    ],
    "name:heb_x_preferred":[
        "\u05d8\u05dc \u05d0\u05dc"
    ],
    "name:heb_x_variant":[
        "\u05d8\u05dc-\u05d0\u05dc"
    ],
    "name:pol_x_preferred":[
        "Tal-El"
    ],
    "wof:name":"Tal El",
    "wof:placetype":"locality"
},
  "geometry": {"coordinates":[35.18128,32.92825],"type":"Point"}
}