{
  "type": "Feature",
  "properties": {
    "iso:country":"IL",
    "name:ara_x_preferred":[
        "\u0635\u0641\u0648\u0631\u064a\u0629"
    ],
    "name:aze_x_preferred":[
        "Sepforis"
    ],
    "name:bul_x_preferred":[
        "\u0421\u0435\u043f\u0444\u043e\u0440\u0438\u0441"
    ],
    "name:cat_x_preferred":[
        "Seforis"
    ],
    "name:ceb_x_preferred":[
        "\u1e94ippori"
    ],
    "name:ces_x_preferred":[
        "Cipori"
    ],
    "name:dan_x_preferred":[
        "Sepphoris"
    ],
    "name:deu_x_preferred":[
        "Sepphoris"
    ],
    "name:ell_x_preferred":[
        "\u03a3\u03b5\u03c0\u03c6\u03c9\u03c1\u03af\u03b4\u03b1"
    ],
    "name:eng_x_preferred":[
        "Tzippori"
    ],
    "name:eng_x_variant":[
        "Sepphoris"
    ],
    "name:eus_x_preferred":[
        "Seforis"
    ],
    "name:fas_x_preferred":[
        "\u0633\u0641\u0648\u0631\u06cc\u0633"
    ],
    "name:fin_x_preferred":[
        "Sepforis"
    ],
    "name:fra_x_preferred":[
        "Sepphoris"
    ],
    "name:glg_x_preferred":[
        "S\u00e9foris"
    ],
    "name:heb_x_preferred":[
        "\u05e6\u05e4\u05d5\u05e8\u05d9"
    ],
    "name:heb_x_variant":[
        "\u05e6\u05d9\u05e4\u05d5\u05e8\u05d9"
    ],
    "name:ind_x_preferred":[
        "Sepforis"
    ],
    "name:ita_x_preferred":[
        "Zippori"
    ],
    "name:jpn_x_preferred":[
        "\u30bb\u30d5\u30a9\u30ea\u30b9"
    ],
    "name:min_x_preferred":[
        "Sepforis"
    ],
    "name:nld_x_preferred":[
        "Tzippori"
    ],
    "name:nno_x_preferred":[
        "Sepphoris"
    ],
    "name:nob_x_preferred":[
        "Sepforis"
    ],
    "name:oci_x_preferred":[
        "Seforis"
    ],
    "name:pol_x_preferred":[
        "Seforis"
    ],
    "name:por_x_preferred":[
        "S\u00e9foris"
    ],
    "name:ron_x_preferred":[
        "Sepphoris"
    ],
    "name:rus_x_preferred":[
        "\u0426\u0438\u043f\u043f\u043e\u0440\u0438"
    ],
    "name:rus_x_variant":[
        "\u0421\u0435\u043f\u0444\u043e\u0440\u0438\u0441"
    ],
    "name:spa_x_preferred":[
        "S\u00e9foris"
    ],
    "name:swe_x_preferred":[
        "\u1e94ippori"
    ],
    "name:ukr_x_preferred":[
        "\u0421\u0435\u043f\u0444\u043e\u0440\u0456\u0441"
    ],
    "name:und_x_variant":[
        "Saffuri"
    ],
    "name:urd_x_preferred":[
        "\u0635\u0641\u0648\u0631\u06cc\u06c1"
    ],
    "name:yid_x_preferred":[
        "\u05e6\u05d9\u05e4\u05d5\u05e8\u05d9"
    ],
    "name:zho_x_preferred":[
        "\u585e\u4f5b\u745e\u65af"
    ],
    "qs:gn_country":"IL",
    "qs:gn_fcode":"PPL",
    "qs:gn_pop":616,
    "qs:name":"Zippori",
    "qs:name_adm0":"Israel",
    "qs:name_adm1":"Northern",
    "qs:photos":411,
    "qs:photos_1k":83,
    "qs:photos_9k":2,
    "qs:photos_9r":5,
    "qs:photos_all":411,
    "qs:photos_sr":6,
    "qs:placetype":"Town",
    "qs:pop_sr":"2",
    "qs:woe_adm0":23424852,
    "wof:name":"Zippori",
    "wof:placetype":"locality",
    "wof:population":616
},
  "geometry": {"coordinates":[35.28003,32.74535],"type":"Point"}
}