{
  "type": "Feature",
  "properties": {
    "iso:country":"IL",
    "name:heb_x_preferred":[
        "\u05e6\u05e4\u05d5\u05e8\u05d9"
    ],
    "name:rus_x_preferred":[
        "\u0426\u0438\u043f\u043f\u043e\u0440\u0438"
    ],
    "name:unk_x_variant":[
        "Saffuri"
    ],
    "qs:gn_country":"IL",
    "qs:gn_fcode":"PPL",
    "qs:gn_pop":616,
    "qs:name":"Zippori",
    "qs:name_adm0":"Israel",
    "qs:name_adm1":"Northern",
    "qs:photos":411,
    "qs:photos_1k":83,
    "qs:photos_9k":2,
    "qs:photos_9r":5,
    "qs:photos_all":411,
    "qs:photos_sr":6,
    "qs:placetype":"Town",
    "qs:pop_sr":"2",
    "qs:woe_adm0":23424852,
    "wof:name":"Zippori",
    "wof:placetype":"locality",
    "wof:population":616
},
  "geometry": {"coordinates":[35.28003,32.74535],"type":"Point"}
}