{
  "type": "Feature",
  "properties": {
    "gn:admin1_code":"02",
    "gn:asciiname":"Gezer",
    "gn:country_code":"IL",
    "gn:dem":127,
    "gn:feature_class":"P",
    "gn:feature_code":"PPL",
    "gn:name":"Gezer",
    "gn:population":0,
    "gn:timezone":"Asia/Jerusalem",
    "iso:country":"IL",
    "name:heb_x_preferred":[
        "\u05d2\u05d6\u05e8"
    ],
    "wof:name":"Gezer",
    "wof:placetype":"locality"
},
  "geometry": {"coordinates":[34.92046,31.87658],"type":"Point"}
}