{
  "type": "Feature",
  "properties": {
    "iso:country":"IL",
    "name:heb_x_preferred":[
        "\u05e7\u05e8\u05d9\u05ea \u05d0\u05e8\u05d9\u05d4"
    ],
    "name:unk_x_variant":[
        "Kiriat Arieh"
    ],
    "qs:gn_country":"IL",
    "qs:gn_fcode":"PPLX",
    "qs:gn_pop":0,
    "qs:name":"Kiryat Arie",
    "qs:name_adm0":"Palestine",
    "qs:name_adm1":"West Bank",
    "qs:photos":1,
    "qs:photos_1k":1,
    "qs:photos_9k":1,
    "qs:photos_9r":1,
    "qs:photos_all":1,
    "qs:photos_sr":1,
    "qs:placetype":"Suburb",
    "qs:pop_sr":"0",
    "qs:woe_adm0":28289408,
    "wof:name":"Kiryat Arie",
    "wof:placetype":"neighbourhood"
},
  "geometry": {"coordinates":[34.85948,32.09405],"type":"Point"}
}