{
  "type": "Feature",
  "properties": {
    "gn:admin1_code":"01",
    "gn:asciiname":"Nehora",
    "gn:country_code":"IL",
    "gn:dem":109,
    "gn:feature_class":"P",
    "gn:feature_code":"PPL",
    "gn:name":"Nehora",
    "gn:population":0,
    "gn:timezone":"Asia/Jerusalem",
    "iso:country":"IL",
    "name:heb_x_preferred":[
        "\u05e0\u05d4\u05d5\u05e8\u05d4"
    ],
    "wof:name":"Nehora",
    "wof:placetype":"locality"
},
  "geometry": {"coordinates":[34.70424000000001,31.62276],"type":"Point"}
}