{
  "type": "Feature",
  "properties": {
    "gn:admin1_code":"01",
    "gn:asciiname":"Giv`at Rahel",
    "gn:country_code":"IL",
    "gn:dem":236,
    "gn:feature_class":"P",
    "gn:feature_code":"PPL",
    "gn:name":"Giv\u2018at Ra\u1e96el",
    "gn:population":0,
    "gn:timezone":"Africa/Cairo",
    "iso:country":"IL",
    "wof:name":"Giv`at Rahel",
    "wof:placetype":"locality"
},
  "geometry": {"coordinates":[34.43917,30.89],"type":"Point"}
}