{
  "type": "Feature",
  "properties": {
    "gn:admin1_code":"03",
    "gn:asciiname":"Ahihud",
    "gn:country_code":"IL",
    "gn:dem":26,
    "gn:feature_class":"P",
    "gn:feature_code":"PPL",
    "gn:name":"A\u1e96ihud",
    "gn:population":0,
    "gn:timezone":"Asia/Jerusalem",
    "iso:country":"IL",
    "name:ara_x_preferred":[
        "\u0623\u062d\u064a\u0647\u0648\u062f"
    ],
    "name:ces_x_preferred":[
        "Achihud"
    ],
    "name:fas_x_preferred":[
        "\u0627\u062d\u06cc\u0647\u0648\u062f"
    ],
    "name:heb_x_preferred":[
        "\u05d0\u05d7\u05d9\u05d4\u05d5\u05d3"
    ],
    "name:nno_x_preferred":[
        "Ahihud"
    ],
    "name:pol_x_preferred":[
        "Achihud"
    ],
    "name:und_x_variant":[
        "A\u1e96ihud"
    ],
    "wof:name":"Ahihud",
    "wof:placetype":"locality"
},
  "geometry": {"coordinates":[35.17137,32.90835999999999],"type":"Point"}
}