{
  "type": "Feature",
  "properties": {
    "gn:admin1_code":"06",
    "gn:asciiname":"Tirosh",
    "gn:country_code":"IL",
    "gn:dem":158,
    "gn:feature_class":"P",
    "gn:feature_code":"PPL",
    "gn:name":"Tirosh",
    "gn:population":0,
    "gn:timezone":"Asia/Jerusalem",
    "iso:country":"IL",
    "name:heb_x_preferred":[
        "\u05ea\u05d9\u05e8\u05d5\u05e9"
    ],
    "name:und_x_variant":[
        "Mughallis B",
        "Tirosh"
    ],
    "wof:name":"Tirosh",
    "wof:placetype":"locality"
},
  "geometry": {"coordinates":[34.88634,31.74995],"type":"Point"}
}