{
  "type": "Feature",
  "properties": {
    "gn:admin1_code":"03",
    "gn:asciiname":"Deganya Bet",
    "gn:country_code":"IL",
    "gn:dem":-197,
    "gn:feature_class":"P",
    "gn:feature_code":"PPL",
    "gn:name":"Deganya Bet",
    "gn:population":0,
    "gn:timezone":"Asia/Jerusalem",
    "iso:country":"IL",
    "name:ces_x_preferred":[
        "Deganja Bet"
    ],
    "name:heb_x_preferred":[
        "\u05d3\u05d2\u05e0\u05d9\u05d4 \u05d1\u05d9\u05ea"
    ],
    "name:heb_x_variant":[
        "\u05d3\u05d2\u05e0\u05d9\u05d4 \u05d1",
        "\u05d3\u05d2\u05e0\u05d9\u05d4 \u05d1'"
    ],
    "name:ita_x_preferred":[
        "Degania Bet"
    ],
    "name:jpn_x_preferred":[
        "\u30c7\u30ac\u30cb\u30a2"
    ],
    "name:nno_x_preferred":[
        "Degania Bet"
    ],
    "name:pol_x_preferred":[
        "Deganja Bet"
    ],
    "name:por_x_preferred":[
        "Degania Bet"
    ],
    "name:und_x_variant":[
        "Deganyah Bet",
        "Deganiya Bet",
        "Deganiya",
        "Deganiyah",
        "Deganya Bet",
        "Deganya B"
    ],
    "name:yid_x_preferred":[
        "\u05d3\u05d2\u05e0\u05d9\u05d4 \u05d1'"
    ],
    "wof:name":"Deganya Bet",
    "wof:placetype":"locality"
},
  "geometry": {"coordinates":[35.57595999999999,32.69987],"type":"Point"}
}