{
  "type": "Feature",
  "properties": {
    "gn:admin1_code":"06",
    "gn:asciiname":"Kokhav HaShahar",
    "gn:country_code":"IL",
    "gn:dem":533,
    "gn:feature_class":"P",
    "gn:feature_code":"STLMT",
    "gn:name":"Kokhav HaSha\u1e96ar",
    "gn:population":0,
    "gn:timezone":"Asia/Jerusalem",
    "iso:country":"IL",
    "name:und_x_variant":[
        "Nahal Kochav Hashahar",
        "Kokhav HaSha\u1e96ar"
    ],
    "wof:name":"Kokhav HaShahar",
    "wof:placetype":"locality"
},
  "geometry": {"coordinates":[35.35,31.96667],"type":"Point"}
}