{
  "type": "Feature",
  "properties": {
    "iso:country":"IL",
    "name:ces_x_preferred":[
        "Gid'ona"
    ],
    "name:eng_x_preferred":[
        "Gidona"
    ],
    "name:heb_x_preferred":[
        "\u05d2\u05d3\u05e2\u05d5\u05e0\u05d4"
    ],
    "name:nno_x_preferred":[
        "Gidona"
    ],
    "name:pol_x_preferred":[
        "Gidona"
    ],
    "name:und_x_variant":[
        "Zera\u2018im"
    ],
    "qs:gn_country":"IL",
    "qs:gn_fcode":"PPL",
    "qs:gn_pop":0,
    "qs:name":"Gidona",
    "qs:name_adm0":"Israel",
    "qs:name_adm1":"Northern",
    "qs:photos":117,
    "qs:photos_1k":24,
    "qs:photos_9k":1,
    "qs:photos_9r":3,
    "qs:photos_all":117,
    "qs:photos_sr":3,
    "qs:placetype":"Town",
    "qs:pop_sr":"0",
    "qs:woe_adm0":23424852,
    "wd:wordcount":96,
    "wof:name":"Gidona",
    "wof:placetype":"locality"
},
  "geometry": {"coordinates":[35.35833,32.54722],"type":"Point"}
}