{
  "type": "Feature",
  "properties": {
    "gn:admin1_code":"03",
    "gn:asciiname":"Hodayot",
    "gn:country_code":"IL",
    "gn:dem":287,
    "gn:feature_class":"P",
    "gn:feature_code":"PPL",
    "gn:name":"Hodayot",
    "gn:population":0,
    "gn:timezone":"Asia/Jerusalem",
    "iso:country":"IL",
    "name:ceb_x_preferred":[
        "Hodayot"
    ],
    "name:ces_x_preferred":[
        "Hodajot"
    ],
    "name:heb_x_preferred":[
        "\u05d4\u05d5\u05d3\u05d9\u05d5\u05ea"
    ],
    "name:pol_x_preferred":[
        "Hodajot"
    ],
    "name:swe_x_preferred":[
        "Hodayot"
    ],
    "wof:name":"Hodayot",
    "wof:placetype":"locality"
},
  "geometry": {"coordinates":[35.43486,32.78857],"type":"Point"}
}