{
  "type": "Feature",
  "properties": {
    "gn:admin1_code":"03",
    "gn:asciiname":"Menora",
    "gn:country_code":"IL",
    "gn:dem":-188,
    "gn:feature_class":"P",
    "gn:feature_code":"PPL",
    "gn:name":"Menora",
    "gn:population":0,
    "gn:timezone":"Asia/Jerusalem",
    "iso:country":"IL",
    "name:deu_x_preferred":[
        "Menora"
    ],
    "name:heb_x_preferred":[
        "\u05de\u05e0\u05d5\u05e8\u05d4"
    ],
    "name:und_x_variant":[
        "Al Man\u0101ra",
        "El Manara",
        "Menara",
        "Manara"
    ],
    "wof:name":"Menora",
    "wof:placetype":"locality"
},
  "geometry": {"coordinates":[35.55305999999999,32.76385],"type":"Point"}
}