{
  "type": "Feature",
  "properties": {
    "iso:country":"IL",
    "name:ces_x_preferred":[
        "Nataf"
    ],
    "name:eng_x_preferred":[
        "Nataf"
    ],
    "name:fra_x_preferred":[
        "Nataf"
    ],
    "name:heb_x_preferred":[
        "\u05e0\u05d8\u05e3"
    ],
    "name:nno_x_preferred":[
        "Nataf"
    ],
    "name:pol_x_preferred":[
        "Nataf"
    ],
    "qs:gn_pop":0,
    "qs:name":"Nataf",
    "qs:name_adm0":"Israel",
    "qs:name_adm1":"Jerusalem",
    "qs:photos":47,
    "qs:photos_1k":10,
    "qs:photos_9k":1,
    "qs:photos_9r":2,
    "qs:photos_all":47,
    "qs:photos_sr":2,
    "qs:placetype":"Town",
    "qs:pop_sr":"0",
    "qs:woe_adm0":23424852,
    "wd:wordcount":306,
    "wof:name":"Nataf",
    "wof:placetype":"locality"
},
  "geometry": {"coordinates":[35.061492,31.837024],"type":"Point"}
}