{
  "type": "Feature",
  "properties": {
    "gn:admin1_code":"02",
    "gn:asciiname":"Kafr Bara",
    "gn:country_code":"IL",
    "gn:dem":98,
    "gn:feature_class":"P",
    "gn:feature_code":"PPL",
    "gn:name":"Kafr Bar\u0101",
    "gn:population":0,
    "gn:timezone":"Asia/Jerusalem",
    "iso:country":"IL",
    "name:ara_x_preferred":[
        "\u0643\u0641\u0631 \u0628\u0631\u0627"
    ],
    "name:ces_x_preferred":[
        "Kafr Bara"
    ],
    "name:fas_x_preferred":[
        "\u06a9\u0641\u0631 \u0628\u0631\u0627"
    ],
    "name:heb_x_preferred":[
        "\u05db\u05e4\u05e8 \u05d1\u05e8\u05d0"
    ],
    "name:heb_x_variant":[
        "Kafr Bar\u0101"
    ],
    "name:nno_x_preferred":[
        "Kafr Bara"
    ],
    "name:pol_x_preferred":[
        "Kafr Bara"
    ],
    "name:rus_x_preferred":[
        "\u041a\u0430\u0444\u0440-\u0411\u0430\u0440\u0430"
    ],
    "name:sco_x_preferred":[
        "Kafr Bara"
    ],
    "name:und_x_variant":[
        "Kafr Barah",
        "Kafr B\u0101r\u0101",
        "Kefar Bara"
    ],
    "name:urd_x_preferred":[
        "\u06a9\u0641\u0631 \u0628\u0631\u0627"
    ],
    "wof:name":"Kafr Bara",
    "wof:placetype":"locality"
},
  "geometry": {"coordinates":[34.97079,32.13136],"type":"Point"}
}