{
  "type": "Feature",
  "properties": {
    "gn:admin1_code":"03",
    "gn:asciiname":"Giv`at Hazaq",
    "gn:country_code":"IL",
    "gn:dem":308,
    "gn:feature_class":"P",
    "gn:feature_code":"PPL",
    "gn:name":"Giv\u2018at H\u0331azaq",
    "gn:population":0,
    "gn:timezone":"Asia/Jerusalem",
    "iso:country":"IL",
    "name:heb_x_preferred":[
        "Giv\u2018at H\u0331azaq"
    ],
    "name:heb_x_variant":[
        "\u05d2\u05d1\u05e2\u05ea \u05d7\u05d6\u05e7"
    ],
    "wof:name":"Giv`at Hazaq",
    "wof:placetype":"locality"
},
  "geometry": {"coordinates":[35.5515,33.04461],"type":"Point"}
}