{
  "type": "Feature",
  "properties": {
    "iso:country":"IL",
    "name:eng_x_preferred":[
        "Barnea"
    ],
    "name:heb_x_preferred":[
        "Barnea\u2018"
    ],
    "name:heb_x_variant":[
        "\u05d1\u05e8\u05e0\u05e2"
    ],
    "qs:gn_fcode":"PPLX",
    "qs:gn_local":0,
    "qs:gn_namadm1":"01",
    "qs:gn_name":"Barnea\u2018",
    "qs:local_max":628,
    "qs:local_sum":628,
    "qs:localhoods":1,
    "qs:name":"Barnea",
    "qs:name_adm0":"Israel",
    "qs:name_adm1":"Southern",
    "qs:name_local":"Ashkelon",
    "qs:photo_max":108,
    "qs:photo_sum":628,
    "qs:placetype":"Suburb",
    "qs:quad_count":41,
    "qs:woe_adm0":23424852,
    "qs:woe_adm1":2345791,
    "qs:woe_adm2":0,
    "qs:woe_lau":0,
    "qs:woe_local":1968154,
    "qs:woe_ver":"7.10.0",
    "wof:lang":[
        "eng"
    ],
    "wof:name":"Barnea",
    "wof:placetype":"neighbourhood"
},
  "geometry": {"coordinates":[34.557112,31.675271],"type":"Point"}
}