{
  "type": "Feature",
  "properties": {
    "iso:country":"IL",
    "qs:gn_pop":0,
    "qs:name":"Shikunei Khisakhon",
    "qs:name_adm0":"Israel",
    "qs:name_adm1":"Tel Aviv",
    "qs:photos":51,
    "qs:photos_1k":10,
    "qs:photos_9k":1,
    "qs:photos_9r":2,
    "qs:photos_all":51,
    "qs:photos_sr":2,
    "qs:placetype":"Suburb",
    "qs:pop_sr":"0",
    "qs:woe_adm0":23424852,
    "wof:name":"Shikunei Khisakhon",
    "wof:placetype":"neighbourhood"
},
  "geometry": {"coordinates":[34.755077,32.040312],"type":"Point"}
}