{
  "type": "Feature",
  "properties": {
    "gn:admin1_code":"02",
    "gn:asciiname":"Nahalat Yehuda",
    "gn:country_code":"IL",
    "gn:dem":42,
    "gn:feature_class":"P",
    "gn:feature_code":"PPL",
    "gn:name":"Na\u1e96alat Yehuda",
    "gn:population":0,
    "gn:timezone":"Asia/Jerusalem",
    "iso:country":"IL",
    "name:heb_x_preferred":[
        "\u05e0\u05d7\u05dc\u05ea \u05d9\u05d4\u05d5\u05d3\u05d4"
    ],
    "name:und_x_variant":[
        "Nahalath Yeh\u016bd\u0101",
        "Nahalat Yehudah",
        "Na\u1e96alat Yehuda"
    ],
    "wof:name":"Nahalat Yehuda",
    "wof:placetype":"neighbourhood"
},
  "geometry": {"coordinates":[34.80788,31.98057],"type":"Point"}
}