{
  "type": "Feature",
  "properties": {
    "gn:admin1_code":"02",
    "gn:asciiname":"Kefar Malal",
    "gn:country_code":"IL",
    "gn:dem":64,
    "gn:feature_class":"P",
    "gn:feature_code":"PPL",
    "gn:name":"Kefar Malal",
    "gn:population":0,
    "gn:timezone":"Asia/Jerusalem",
    "iso:country":"IL",
    "name:heb_x_preferred":[
        "\u05db\u05e4\u05e8 \u05de\u05dc\u2019\u2019\u05dc"
    ],
    "name:und_x_variant":[
        "\u2018Ein H\u0101y",
        "Kfar Malal",
        "\u2018Ein Hai",
        "Kefar Malal",
        "Kefar Mallal"
    ],
    "wof:name":"Kefar Malal",
    "wof:placetype":"locality"
},
  "geometry": {"coordinates":[34.89828,32.16656],"type":"Point"}
}