{
  "type": "Feature",
  "properties": {
    "gn:admin1_code":"02",
    "gn:asciiname":"Kefar Malal",
    "gn:country_code":"IL",
    "gn:dem":64,
    "gn:feature_class":"P",
    "gn:feature_code":"PPL",
    "gn:name":"Kefar Malal",
    "gn:population":0,
    "gn:timezone":"Asia/Jerusalem",
    "iso:country":"IL",
    "name:ara_x_preferred":[
        "\u0643\u0641\u0627\u0631 \u0645\u0644\u0627\u0644"
    ],
    "name:ceb_x_preferred":[
        "Kefar Malal"
    ],
    "name:ces_x_preferred":[
        "Kfar Malal"
    ],
    "name:dan_x_preferred":[
        "Kfar Malal"
    ],
    "name:deu_x_preferred":[
        "Kfar Malal"
    ],
    "name:fra_x_preferred":[
        "Kfar Malal"
    ],
    "name:heb_x_preferred":[
        "\u05db\u05e4\u05e8 \u05de\u05dc\u2019\u2019\u05dc"
    ],
    "name:heb_x_variant":[
        "\u05db\u05e4\u05e8 \u05de\u05dc\"\u05dc"
    ],
    "name:ind_x_preferred":[
        "Kfar Malal"
    ],
    "name:ita_x_preferred":[
        "Kfar Malal"
    ],
    "name:nld_x_preferred":[
        "Kfar Malal"
    ],
    "name:nno_x_preferred":[
        "Kfar Malal"
    ],
    "name:pol_x_preferred":[
        "Kefar Malal"
    ],
    "name:ron_x_preferred":[
        "Kfar Malal"
    ],
    "name:spa_x_preferred":[
        "Kfar Malal"
    ],
    "name:swe_x_preferred":[
        "Kefar Malal"
    ],
    "name:ukr_x_preferred":[
        "\u041a\u0444\u0430\u0440-\u041c\u0430\u043b\u0430\u043b\u044c"
    ],
    "name:und_x_variant":[
        "\u2018Ein H\u0101y",
        "Kfar Malal",
        "\u2018Ein Hai",
        "Kefar Malal",
        "Kefar Mallal"
    ],
    "name:urd_x_preferred":[
        "\u06a9\u0641\u0631 \u0645\u0644\u0627\u0644"
    ],
    "name:vie_x_preferred":[
        "Kfar Malal"
    ],
    "wof:name":"Kefar Malal",
    "wof:placetype":"locality"
},
  "geometry": {"coordinates":[34.89828,32.16656],"type":"Point"}
}