{
  "type": "Feature",
  "properties": {
    "gn:admin1_code":"01",
    "gn:asciiname":"Emunim",
    "gn:country_code":"IL",
    "gn:dem":32,
    "gn:feature_class":"P",
    "gn:feature_code":"PPL",
    "gn:name":"Emunim",
    "gn:population":0,
    "gn:timezone":"Asia/Jerusalem",
    "iso:country":"IL",
    "name:ara_x_preferred":[
        "\u0625\u0645\u0648\u0646\u064a\u0645"
    ],
    "name:ces_x_preferred":[
        "Emunim"
    ],
    "name:fas_x_preferred":[
        "\u0625\u0645\u0648\u0646\u06cc\u0645"
    ],
    "name:heb_x_preferred":[
        "\u05d0\u05de\u05d5\u05e0\u05d9\u05dd"
    ],
    "name:nld_x_preferred":[
        "Emoenim"
    ],
    "name:nno_x_preferred":[
        "Emunim"
    ],
    "name:pol_x_preferred":[
        "Emunim"
    ],
    "name:und_x_variant":[
        "Ashdod Gimmel C",
        "Ashdod Gimel",
        "Ashdod C",
        "Ashdod"
    ],
    "name:urd_x_preferred":[
        "\u0627\u0645\u0648\u0646\u06cc\u0645"
    ],
    "wof:name":"Emunim",
    "wof:placetype":"locality"
},
  "geometry": {"coordinates":[34.6754,31.74391],"type":"Point"}
}