{
  "type": "Feature",
  "properties": {
    "gn:admin1_code":"02",
    "gn:asciiname":"Sha`ar Efrayim",
    "gn:country_code":"IL",
    "gn:dem":47,
    "gn:feature_class":"P",
    "gn:feature_code":"PPL",
    "gn:name":"Sha\u2018ar Efrayim",
    "gn:population":0,
    "gn:timezone":"Asia/Jerusalem",
    "iso:country":"IL",
    "name:ces_x_preferred":[
        "\u0160a'ar Efrajim"
    ],
    "name:heb_x_preferred":[
        "Sha\u2018ar Efrayim"
    ],
    "name:heb_x_variant":[
        "\u05e9\u05e2\u05e8 \u05d0\u05e4\u05e8\u05d9\u05dd",
        "Sha\u2019ar Efrayim"
    ],
    "name:nno_x_preferred":[
        "Sha'ar Efraim"
    ],
    "name:pol_x_preferred":[
        "Sza\u2019ar Efrajim"
    ],
    "name:und_x_variant":[
        "Birburin D",
        "Sha\u2019ar Ephraim"
    ],
    "wof:name":"Sha`ar Efrayim",
    "wof:placetype":"locality"
},
  "geometry": {"coordinates":[34.9984,32.29067],"type":"Point"}
}