{
  "type": "Feature",
  "properties": {
    "gn:admin1_code":"01",
    "gn:asciiname":"Hura",
    "gn:country_code":"IL",
    "gn:dem":425,
    "gn:feature_class":"P",
    "gn:feature_code":"PPL",
    "gn:name":"H\u0331ura",
    "gn:population":0,
    "gn:timezone":"Asia/Jerusalem",
    "iso:country":"IL",
    "name:heb_x_preferred":[
        "H\u0331ura"
    ],
    "name:heb_x_variant":[
        "\u05d7\u05d5\u05e8\u05d4"
    ],
    "name:und_x_variant":[
        "H\u0331\u016bra"
    ],
    "wof:name":"Hura",
    "wof:placetype":"locality"
},
  "geometry": {"coordinates":[34.93606,31.30084],"type":"Point"}
}