{
  "type": "Feature",
  "properties": {
    "gn:admin1_code":"02",
    "gn:asciiname":"Bet Hanan",
    "gn:country_code":"IL",
    "gn:dem":43,
    "gn:feature_class":"P",
    "gn:feature_code":"PPL",
    "gn:name":"Bet H\u0331anan",
    "gn:population":0,
    "gn:timezone":"Asia/Jerusalem",
    "iso:country":"IL",
    "name:heb_x_preferred":[
        "\u05d1\u05d9\u05ea \u05d7\u05e0\u05df"
    ],
    "name:und_x_variant":[
        "Beit \u1e24anan",
        "Bet H\u0331anan"
    ],
    "wof:name":"Bet Hanan",
    "wof:placetype":"locality"
},
  "geometry": {"coordinates":[34.77304,31.93432],"type":"Point"}
}