{
  "type": "Feature",
  "properties": {
    "iso:country":"IL",
    "name:ara_x_preferred":[
        "\u062c\u0641\u0639\u0627\u062a \u0634\u0645\u0648\u0626\u064a\u0644"
    ],
    "name:ces_x_preferred":[
        "Giv'at \u0160mu'el"
    ],
    "name:deu_x_preferred":[
        "Givat Schmuel"
    ],
    "name:eng_x_preferred":[
        "Giv\u2018at Shmuel"
    ],
    "name:eng_x_variant":[
        "Giv\u2018at Shemu\u2019el",
        "Giv\u2018at Shemuel",
        "Giv\u2018at Shmu\u2019el",
        "Givat Shmu\u2019el",
        "Giv'at Shmuel"
    ],
    "name:fra_x_preferred":[
        "Giv'at Shmuel"
    ],
    "name:heb_x_preferred":[
        "\u05d2\u05d1\u05e2\u05ea \u05e9\u05de\u05d5\u05d0\u05dc"
    ],
    "name:heb_x_variant":[
        "\u05d2\u05d9\u05d1\u05e2\u05ea \u05e9\u05de\u05d5\u05d0\u05dc"
    ],
    "name:hun_x_preferred":[
        "Giv'at Shmuel"
    ],
    "name:hye_x_preferred":[
        "\u0533\u056b\u057e\u0561\u0569 \u0547\u0574\u0578\u0582\u0565\u056c"
    ],
    "name:ind_x_preferred":[
        "Giv'at Shmuel"
    ],
    "name:nld_x_preferred":[
        "Giv'at Shmuel"
    ],
    "name:nno_x_preferred":[
        "Giv'at Shmuel"
    ],
    "name:pol_x_preferred":[
        "Giv'at Shemuel"
    ],
    "name:por_x_preferred":[
        "Giv'at Shmuel"
    ],
    "name:rus_x_preferred":[
        "\u0413\u0438\u0432\u0430\u0442-\u0428\u043c\u0443\u044d\u043b\u044c"
    ],
    "name:sco_x_preferred":[
        "Giv'at Shmuel"
    ],
    "name:urd_x_preferred":[
        "\u062c\u0641\u0639\u0627\u062a \u0634\u0645\u0648\u0626\u06cc\u0644"
    ],
    "name:vie_x_preferred":[
        "Giv'at Shmuel"
    ],
    "name:war_x_preferred":[
        "Giv'at Shmuel"
    ],
    "name:yid_x_preferred":[
        "\u05d2\u05d1\u05e2\u05ea \u05e9\u05de\u05d5\u05d0\u05dc"
    ],
    "name:zho_x_preferred":[
        "\u5409\u592b\u963f\u7279\u4ec0\u7a46\u57c3\u723e"
    ],
    "qs:gn_country":"IL",
    "qs:gn_fcode":"PPL",
    "qs:gn_pop":18500,
    "qs:name":"Givat Shemu'el",
    "qs:name_adm0":"Israel",
    "qs:name_adm1":"Central",
    "qs:photos":131,
    "qs:photos_1k":27,
    "qs:photos_9k":1,
    "qs:photos_9r":3,
    "qs:photos_all":131,
    "qs:photos_sr":3,
    "qs:placetype":"Town",
    "qs:pop_sr":"6",
    "qs:woe_adm0":23424852,
    "wd:wordcount":603,
    "wof:name":"Givat Shemu'el",
    "wof:placetype":"neighbourhood",
    "wof:population":18500
},
  "geometry": {"coordinates":[34.84667,32.07528],"type":"Point"}
}