{
  "type": "Feature",
  "properties": {
    "iso:country":"IL",
    "name:heb_x_preferred":[
        "\u05d1\u05d9\u05ea \u05e6\u05d1\u05d9"
    ],
    "name:unk_x_variant":[
        "Beit-Tsevi"
    ],
    "qs:gn_country":"IL",
    "qs:gn_fcode":"PPL",
    "qs:gn_pop":0,
    "qs:name":"Bet Zevi",
    "qs:name_adm0":"Israel",
    "qs:name_adm1":"Haifa",
    "qs:photos":27,
    "qs:photos_1k":5,
    "qs:photos_9k":1,
    "qs:photos_9r":2,
    "qs:photos_all":27,
    "qs:photos_sr":2,
    "qs:placetype":"Town",
    "qs:pop_sr":"0",
    "qs:woe_adm0":23424852,
    "wof:name":"Bet Zevi",
    "wof:placetype":"locality"
},
  "geometry": {"coordinates":[34.96986,32.72045],"type":"Point"}
}