{
  "type": "Feature",
  "properties": {
    "gn:admin1_code":"03",
    "gn:asciiname":"Yif`at",
    "gn:country_code":"IL",
    "gn:dem":140,
    "gn:feature_class":"P",
    "gn:feature_code":"PPL",
    "gn:name":"Yif\u2018at",
    "gn:population":0,
    "gn:timezone":"Asia/Jerusalem",
    "iso:country":"IL",
    "name:ces_x_preferred":[
        "Jif'at"
    ],
    "name:deu_x_preferred":[
        "Jif\u02bfat"
    ],
    "name:heb_x_preferred":[
        "Yif\u2018at"
    ],
    "name:heb_x_variant":[
        "\u05d9\u05e4\u05e2\u05ea"
    ],
    "name:nno_x_preferred":[
        "Yifat"
    ],
    "name:pol_x_preferred":[
        "Jifat"
    ],
    "wof:name":"Yif`at",
    "wof:placetype":"locality"
},
  "geometry": {"coordinates":[35.22333,32.6775],"type":"Point"}
}