{
  "type": "Feature",
  "properties": {
    "iso:country":"IL",
    "name:bul_x_preferred":[
        "\u0413\u0435\u0432\u0430\u0442"
    ],
    "name:ceb_x_preferred":[
        "Gevat"
    ],
    "name:ces_x_preferred":[
        "Gvat"
    ],
    "name:eng_x_preferred":[
        "Gvat"
    ],
    "name:fra_x_preferred":[
        "Gvat"
    ],
    "name:heb_x_preferred":[
        "\u05d2\u05d1\u05ea"
    ],
    "name:nld_x_preferred":[
        "Gvat"
    ],
    "name:nno_x_preferred":[
        "Gevat"
    ],
    "name:nob_x_preferred":[
        "Gevat"
    ],
    "name:nor_x_preferred":[
        "Gevat"
    ],
    "name:pol_x_preferred":[
        "Gewat"
    ],
    "name:pol_x_variant":[
        "Gevat"
    ],
    "name:rus_x_preferred":[
        "\u0413\u0432\u0430\u0442"
    ],
    "name:swe_x_preferred":[
        "Gevat"
    ],
    "name:und_x_variant":[
        "Jabata"
    ],
    "qs:gn_country":"IL",
    "qs:gn_fcode":"PPL",
    "qs:gn_pop":0,
    "qs:name":"Gevat",
    "qs:name_adm0":"Israel",
    "qs:name_adm1":"Northern",
    "qs:photos":0,
    "qs:photos_1k":0,
    "qs:photos_9k":1,
    "qs:photos_9r":1,
    "qs:photos_all":16,
    "qs:photos_sr":0,
    "qs:placetype":"Town",
    "qs:pop_sr":"0",
    "qs:woe_adm0":23424852,
    "wd:wordcount":868,
    "wof:name":"Gevat",
    "wof:placetype":"locality"
},
  "geometry": {"coordinates":[35.21247,32.67547],"type":"Point"}
}