{
  "type": "Feature",
  "properties": {
    "iso:country":"IL",
    "name:ces_x_preferred":[
        "Mevo Bejtar"
    ],
    "name:cze_x_preferred":[
        "Mevo Bejtar"
    ],
    "name:eng_x_preferred":[
        "Mevoot Beitar"
    ],
    "name:eng_x_variant":[
        "Mevo Beiter",
        "Mevoot Betar",
        "Mevoot Beiter",
        "Mevo Betar",
        "Mevo Beitar"
    ],
    "name:heb_x_preferred":[
        "\u05de\u05d1\u05d5\u05d0 \u05d1\u05d9\u05ea\u05e8"
    ],
    "name:heb_x_variant":[
        "\u05de\u05d1\u05d5\u05d0 \u05e0\u05d9\u05ea\u05e8"
    ],
    "name:nno_x_preferred":[
        "Mevo Beitar"
    ],
    "name:pol_x_preferred":[
        "Mewo Betar"
    ],
    "name:swe_x_preferred":[
        "Mevo Betar"
    ],
    "name:unk_x_variant":[
        "Mevo Beter"
    ],
    "qs:gn_country":"IL",
    "qs:gn_fcode":"PPL",
    "qs:gn_pop":27267,
    "qs:name":"Mevo Betar",
    "qs:name_adm0":"Israel",
    "qs:name_adm1":"Jerusalem",
    "qs:photos":0,
    "qs:photos_1k":0,
    "qs:photos_9k":0,
    "qs:photos_9r":0,
    "qs:photos_all":0,
    "qs:photos_sr":0,
    "qs:placetype":"Town",
    "qs:pop_sr":"7",
    "qs:woe_adm0":23424852,
    "wd:wordcount":147,
    "wof:name":"Mevo Betar",
    "wof:placetype":"locality",
    "wof:population":27267
},
  "geometry": {"coordinates":[35.10669,31.72177],"type":"Point"}
}