{
  "type": "Feature",
  "properties": {
    "iso:country":"IL",
    "name:ces_x_preferred":[
        "Kerem Maharal"
    ],
    "name:cze_x_preferred":[
        "Kerem Maharal"
    ],
    "name:eng_x_preferred":[
        "Kerem Maharal"
    ],
    "name:heb_x_preferred":[
        "\u05db\u05e8\u05dd \u05de\u05d4\u05e8\"\u05dc"
    ],
    "name:heb_x_variant":[
        "\u05e7\u05e8\u05dd \u05de\u05d4\u05e8\u2019\u2019\u05dc"
    ],
    "name:nno_x_preferred":[
        "Kerem Maharal"
    ],
    "name:pol_x_preferred":[
        "Kerem Maharal"
    ],
    "name:unk_x_variant":[
        "Ijzim"
    ],
    "qs:gn_country":"IL",
    "qs:gn_fcode":"PPL",
    "qs:gn_pop":0,
    "qs:name":"Kerem Maharal",
    "qs:name_adm0":"Israel",
    "qs:name_adm1":"Haifa",
    "qs:photos":279,
    "qs:photos_1k":57,
    "qs:photos_9k":1,
    "qs:photos_9r":4,
    "qs:photos_all":279,
    "qs:photos_sr":5,
    "qs:placetype":"Town",
    "qs:pop_sr":"0",
    "qs:woe_adm0":23424852,
    "wd:wordcount":169,
    "wof:name":"Kerem Maharal",
    "wof:placetype":"locality"
},
  "geometry": {"coordinates":[34.99034,32.64577],"type":"Point"}
}