{
  "type": "Feature",
  "properties": {
    "gn:admin1_code":"02",
    "gn:asciiname":"Pedaya",
    "gn:country_code":"IL",
    "gn:dem":104,
    "gn:feature_class":"P",
    "gn:feature_code":"PPL",
    "gn:name":"Pedaya",
    "gn:population":0,
    "gn:timezone":"Asia/Jerusalem",
    "iso:country":"IL",
    "name:ces_x_preferred":[
        "Pedaja"
    ],
    "name:heb_x_preferred":[
        "\u05e4\u05d3\u05d9\u05d4"
    ],
    "name:nno_x_preferred":[
        "Pedaya"
    ],
    "name:pol_x_preferred":[
        "Pedaja"
    ],
    "wof:name":"Pedaya",
    "wof:placetype":"locality"
},
  "geometry": {"coordinates":[34.88391,31.85853],"type":"Point"}
}