{
  "type": "Feature",
  "properties": {
    "iso:country":"IL",
    "name:ces_x_preferred":[
        "Midrach Oz"
    ],
    "name:eng_x_preferred":[
        "Midrakh Oz"
    ],
    "name:heb_x_preferred":[
        "\u05de\u05d3\u05e8\u05da \u05e2\u05d5\u05d6"
    ],
    "name:heb_x_variant":[
        "Midrakh \u2018Oz"
    ],
    "name:nno_x_preferred":[
        "Midrakh Oz"
    ],
    "name:pol_x_preferred":[
        "Midrach Oz"
    ],
    "name:unk_x_variant":[
        "\u2018Ein al Mansi"
    ],
    "qs:gn_country":"IL",
    "qs:gn_fcode":"PPL",
    "qs:gn_pop":0,
    "qs:name":"Midrakh Oz",
    "qs:name_adm0":"Israel",
    "qs:name_adm1":"Northern",
    "qs:photos":21,
    "qs:photos_1k":4,
    "qs:photos_9k":1,
    "qs:photos_9r":1,
    "qs:photos_all":21,
    "qs:photos_sr":1,
    "qs:placetype":"Town",
    "qs:pop_sr":"0",
    "qs:woe_adm0":23424852,
    "wd:wordcount":83,
    "wof:name":"Midrakh Oz",
    "wof:placetype":"locality"
},
  "geometry": {"coordinates":[35.15912,32.59517],"type":"Point"}
}