{
  "type": "Feature",
  "properties": {
    "iso:country":"IL",
    "name:ara_x_preferred":[
        "\u063a\u064a\u0641\u0648\u0646 \u0647\u0627\u0647\u0627\u062f\u0627\u0634\u0627"
    ],
    "name:ceb_x_preferred":[
        "Giv'on HaHadasha"
    ],
    "name:ces_x_preferred":[
        "Giv'on ha-Chada\u0161a"
    ],
    "name:deu_x_preferred":[
        "Giw'on haChadascha"
    ],
    "name:eng_x_preferred":[
        "Giv'on HaHadasha"
    ],
    "name:fra_x_preferred":[
        "Giv'on HaHadasha"
    ],
    "name:heb_x_colloquial":[
        "\u05d2\u05d1\u05e2\u05d5\u05df \u05d4\u05d7\u05d3\u05e9\u05d4"
    ],
    "name:heb_x_historical":[
        "\u05d2\u05d1\u05e2\u05d5\u05df \u05d4\u05d7\u05d3\u05e9\u05d4"
    ],
    "name:heb_x_preferred":[
        "\u05d2\u05d1\u05e2\u05d5\u05df \u05d4\u05d7\u05d3\u05e9\u05d4"
    ],
    "name:ita_x_preferred":[
        "Giv'on HaHadasha"
    ],
    "name:nld_x_preferred":[
        "Giv'on HaHadasha"
    ],
    "name:nno_x_preferred":[
        "Giv'on HaHadasha"
    ],
    "name:pol_x_preferred":[
        "Giwon ha-Chadasza"
    ],
    "name:pol_x_variant":[
        "Zetan",
        "Giv'on HaHadasza"
    ],
    "name:swe_x_preferred":[
        "Giv'on HaHadasha"
    ],
    "qs:gn_country":"IL",
    "qs:gn_fcode":"PPL",
    "qs:gn_pop":1097,
    "qs:name":"Givon Hahadasha",
    "qs:name_adm0":"Palestine",
    "qs:name_adm1":"West Bank",
    "qs:photos":0,
    "qs:photos_1k":0,
    "qs:photos_9k":0,
    "qs:photos_9r":0,
    "qs:photos_all":0,
    "qs:photos_sr":0,
    "qs:placetype":"Suburb",
    "qs:pop_sr":"3",
    "qs:woe_adm0":28289408,
    "wd:wordcount":211,
    "wof:name":"Givon Hahadasha",
    "wof:placetype":"neighbourhood",
    "wof:population":1097
},
  "geometry": {"coordinates":[35.16106,31.84927],"type":"Point"}
}