{
  "type": "Feature",
  "properties": {
    "iso:country":"IL",
    "name:ara_x_preferred":[
        "\u0645\u062c\u062f\u0627\u0644 \u0647\u0639\u064a\u0645\u0642"
    ],
    "name:arz_x_preferred":[
        "\u0645\u062c\u062f\u0627\u0644 \u0647\u0639\u064a\u0645\u0642"
    ],
    "name:ast_x_preferred":[
        "Migdal HaEmek"
    ],
    "name:cat_x_preferred":[
        "Migdal HaEmek"
    ],
    "name:ceb_x_preferred":[
        "Migdal Ha\u2018Emeq"
    ],
    "name:ces_x_preferred":[
        "Migdal ha-Emek"
    ],
    "name:deu_x_preferred":[
        "Migdal haEmek"
    ],
    "name:eng_x_preferred":[
        "Magidal"
    ],
    "name:eng_x_variant":[
        "Migdal Haemeqck",
        "Migdal Hameq",
        "Migdal Ha\u2018Emeq",
        "Migdal Ha\u2018Emek",
        "Migdal HaEmek",
        "Migdal HaEmeq"
    ],
    "name:fas_x_preferred":[
        "\u0645\u06cc\u06af\u062f\u0627\u0644 \u0647\u0627\u0626\u0645\u06a9"
    ],
    "name:fin_x_preferred":[
        "Migdal HaEmek"
    ],
    "name:fra_x_preferred":[
        "Migdal HaEmek"
    ],
    "name:heb_x_preferred":[
        "\u05de\u05d2\u05d3\u05dc \u05d4\u05e2\u05de\u05e7"
    ],
    "name:ind_x_preferred":[
        "Migdal HaEmek"
    ],
    "name:ita_x_preferred":[
        "Migdal HaEmek"
    ],
    "name:kat_x_preferred":[
        "\u10db\u10d8\u10d2\u10d3\u10d0\u10da-\u10f0\u10d0\u10d4\u10db\u10d4\u10d9\u10d8"
    ],
    "name:nld_x_preferred":[
        "Migdal HaEmek"
    ],
    "name:nno_x_preferred":[
        "Migdal HaEmek"
    ],
    "name:pol_x_preferred":[
        "Migdal ha-Emek"
    ],
    "name:pol_x_variant":[
        "Migdal HaEmek"
    ],
    "name:por_x_preferred":[
        "Migdal HaEmeq"
    ],
    "name:rus_x_preferred":[
        "\u041c\u0438\u0433\u0434\u0430\u043b\u044c-\u0445\u0430-\u042d\u043c\u0435\u043a"
    ],
    "name:rus_x_variant":[
        "\u041c\u0438\u0433\u0434\u0430\u043b\u044c \u0425\u0430\u042d\u043c\u0435\u043a"
    ],
    "name:sco_x_preferred":[
        "Migdal HaEmek"
    ],
    "name:spa_x_preferred":[
        "Migdal HaEmek"
    ],
    "name:srp_x_preferred":[
        "\u041c\u0438\u0433\u0434\u0430\u043b \u0425\u0430\u0435\u043c\u0435\u043a"
    ],
    "name:swa_x_preferred":[
        "Migdal HaEmek"
    ],
    "name:swe_x_preferred":[
        "Migdal Ha\u2018Emeq"
    ],
    "name:tgl_x_preferred":[
        "Migdal HaEmek"
    ],
    "name:urd_x_preferred":[
        "\u0645\u062c\u062f\u0627\u0644 \u06c1\u0639\u06cc\u0645\u0642"
    ],
    "name:vie_x_preferred":[
        "Migdal HaEmek"
    ],
    "name:yid_x_preferred":[
        "\u05de\u05d2\u05d3\u05dc \u05d4\u05e2\u05de\u05e7"
    ],
    "name:zho_x_preferred":[
        "\u7c73\u683c\u9054\u52d2\u57c3\u6885\u514b"
    ],
    "qs:gn_country":"IL",
    "qs:gn_fcode":"PPL",
    "qs:gn_pop":24800,
    "qs:name":"Migdal HaEmeq",
    "qs:name_adm0":"Israel",
    "qs:name_adm1":"Northern",
    "qs:photos":109,
    "qs:photos_1k":22,
    "qs:photos_9k":1,
    "qs:photos_9r":3,
    "qs:photos_all":109,
    "qs:photos_sr":3,
    "qs:placetype":"Town",
    "qs:pop_sr":"7",
    "qs:woe_adm0":23424852,
    "wd:wordcount":502,
    "wof:name":"Migdal HaEmeq",
    "wof:placetype":"locality",
    "wof:population":24800
},
  "geometry": {"coordinates":[35.23986,32.67597],"type":"Point"}
}