{
  "type": "Feature",
  "properties": {
    "gn:admin1_code":"01",
    "gn:asciiname":"Netiv Ha`Asara",
    "gn:country_code":"IL",
    "gn:dem":70,
    "gn:feature_class":"P",
    "gn:feature_code":"PPL",
    "gn:name":"Netiv Ha\u2018Asara",
    "gn:population":0,
    "gn:timezone":"Asia/Jerusalem",
    "iso:country":"IL",
    "name:heb_x_preferred":[
        "Netiv Ha\u2018Asara"
    ],
    "name:heb_x_variant":[
        "\u05e0\u05ea\u05d9\u05d1 \u05d4\u05e2\u05e9\u05e8\u05d4"
    ],
    "name:und_x_variant":[
        "Netiv HaAsara"
    ],
    "wof:name":"Netiv Ha`Asara",
    "wof:placetype":"locality"
},
  "geometry": {"coordinates":[34.53955,31.57201],"type":"Point"}
}