{
  "type": "Feature",
  "properties": {
    "gn:admin1_code":"01",
    "gn:asciiname":"Ne'ot HaKikar",
    "gn:country_code":"IL",
    "gn:dem":-350,
    "gn:feature_class":"P",
    "gn:feature_code":"PPL",
    "gn:name":"Ne\u2019ot HaKikar",
    "gn:population":0,
    "gn:timezone":"Asia/Jerusalem",
    "iso:country":"IL",
    "name:ces_x_preferred":[
        "Ne'ot ha-Kikar"
    ],
    "name:heb_x_preferred":[
        "Ne\u2019ot HaKikar"
    ],
    "name:heb_x_variant":[
        "\u05e0\u05d0\u05d5\u05ea \u05d4\u05db\u05db\u05e8",
        "\u05e0\u05d0\u05d5\u05ea \u05d4\u05db\u05d9\u05db\u05e8"
    ],
    "name:nno_x_preferred":[
        "Neot HaKikar"
    ],
    "name:pol_x_preferred":[
        "Ne\u2019ot ha-Kikkar"
    ],
    "name:ron_x_preferred":[
        "Neot HaKikar"
    ],
    "wof:name":"Ne'ot HaKikar",
    "wof:placetype":"locality"
},
  "geometry": {"coordinates":[35.37840999999999,30.93405],"type":"Point"}
}