{
  "type": "Feature",
  "properties": {
    "iso:country":"IL",
    "name:ces_x_preferred":[
        "Nir Am"
    ],
    "name:deu_x_preferred":[
        "Nir Am"
    ],
    "name:eng_x_preferred":[
        "Nir Am"
    ],
    "name:fra_x_preferred":[
        "Nir Am"
    ],
    "name:heb_x_preferred":[
        "\u05e0\u05d9\u05e8 \u05e2\u05dd"
    ],
    "name:heb_x_variant":[
        "Nir\u2018am",
        "\u05e0\u05d9\u05e8\u05e2\u05dd",
        "Nir\u2019am",
        "Nir \u2018Am"
    ],
    "name:jpn_x_preferred":[
        "\u30cb\u30eb\u30a2\u30e0"
    ],
    "name:nld_x_preferred":[
        "Nir Am"
    ],
    "name:nno_x_preferred":[
        "Nir Am"
    ],
    "name:pol_x_preferred":[
        "Nir Am"
    ],
    "name:swe_x_preferred":[
        "Nir\u2018am"
    ],
    "qs:gn_country":"IL",
    "qs:gn_fcode":"PPL",
    "qs:gn_pop":0,
    "qs:name":"Niram",
    "qs:name_adm0":"Israel",
    "qs:name_adm1":"Southern",
    "qs:photos":146,
    "qs:photos_1k":30,
    "qs:photos_9k":1,
    "qs:photos_9r":3,
    "qs:photos_all":146,
    "qs:photos_sr":3,
    "qs:placetype":"Town",
    "qs:pop_sr":"0",
    "qs:woe_adm0":23424852,
    "wd:wordcount":92,
    "wof:name":"Niram",
    "wof:placetype":"locality"
},
  "geometry": {"coordinates":[34.58006,31.51959],"type":"Point"}
}