{
  "type": "Feature",
  "properties": {
    "iso:country":"IL",
    "name:ces_x_preferred":[
        "Kfar ha-Nasi"
    ],
    "name:deu_x_preferred":[
        "Kfar Hanassi"
    ],
    "name:eng_x_preferred":[
        "Kfar HaNassi"
    ],
    "name:fra_x_preferred":[
        "Kfar HaNassi"
    ],
    "name:heb_x_preferred":[
        "\u05db\u05e4\u05e8 \u05d4\u05e0\u05e9\u05d9\u05d0"
    ],
    "name:nld_x_preferred":[
        "Kfar Hanassi"
    ],
    "name:nno_x_preferred":[
        "Kfar HaNassi"
    ],
    "name:nob_x_preferred":[
        "Kfar HaNassi"
    ],
    "name:nor_x_preferred":[
        "Kfar HaNassi"
    ],
    "name:pol_x_preferred":[
        "Kefar ha-Nasi"
    ],
    "name:pol_x_variant":[
        "Kfar HaNassi"
    ],
    "name:und_x_variant":[
        "Mansurah"
    ],
    "qs:gn_country":"IL",
    "qs:gn_fcode":"PPL",
    "qs:gn_pop":0,
    "qs:name":"Kefar HaNasi",
    "qs:name_adm0":"Israel",
    "qs:name_adm1":"Northern",
    "qs:photos":86,
    "qs:photos_1k":17,
    "qs:photos_9k":1,
    "qs:photos_9r":3,
    "qs:photos_all":86,
    "qs:photos_sr":3,
    "qs:placetype":"Town",
    "qs:pop_sr":"0",
    "qs:woe_adm0":23424852,
    "wd:wordcount":118,
    "wof:name":"Kefar HaNasi",
    "wof:placetype":"locality"
},
  "geometry": {"coordinates":[35.60395,32.97447],"type":"Point"}
}