{
  "type": "Feature",
  "properties": {
    "gn:admin1_code":"04",
    "gn:asciiname":"Yajur",
    "gn:country_code":"IL",
    "gn:dem":385,
    "gn:feature_class":"P",
    "gn:feature_code":"PPL",
    "gn:name":"Y\u0101jur",
    "gn:population":0,
    "gn:timezone":"Asia/Jerusalem",
    "iso:country":"IL",
    "name:und_x_variant":[
        "Y\u0101jur"
    ],
    "wof:name":"Yajur",
    "wof:placetype":"locality"
},
  "geometry": {"coordinates":[35.05,32.75],"type":"Point"}
}