{
  "type": "Feature",
  "properties": {
    "gn:admin1_code":"01",
    "gn:asciiname":"Bet Shiqma",
    "gn:country_code":"IL",
    "gn:dem":53,
    "gn:feature_class":"P",
    "gn:feature_code":"PPL",
    "gn:name":"Bet Shiqma",
    "gn:population":0,
    "gn:timezone":"Asia/Jerusalem",
    "iso:country":"IL",
    "name:ces_x_preferred":[
        "Bejt \u0160ikma"
    ],
    "name:heb_x_preferred":[
        "\u05d1\u05d9\u05ea \u05e9\u05e7\u05de\u05d4"
    ],
    "name:nno_x_preferred":[
        "Beit Shikma"
    ],
    "name:pol_x_preferred":[
        "Bet Szikma"
    ],
    "name:und_x_variant":[
        "Julis",
        "Beit Shiqmah",
        "Shiqma",
        "Beit Shiqma",
        "Bet Shiqma",
        "Bet Shikma"
    ],
    "wof:name":"Bet Shiqma",
    "wof:placetype":"locality"
},
  "geometry": {"coordinates":[34.60636,31.63589],"type":"Point"}
}