{
  "type": "Feature",
  "properties": {
    "gn:admin1_code":"01",
    "gn:asciiname":"Nir Moshe",
    "gn:country_code":"IL",
    "gn:dem":146,
    "gn:feature_class":"P",
    "gn:feature_code":"PPL",
    "gn:name":"Nir Moshe",
    "gn:population":0,
    "gn:timezone":"Asia/Jerusalem",
    "iso:country":"IL",
    "name:ces_x_preferred":[
        "Nir Mo\u0161e"
    ],
    "name:heb_x_preferred":[
        "\u05e0\u05d9\u05e8 \u05de\u05e9\u05d4"
    ],
    "name:nno_x_preferred":[
        "Nir Moshe"
    ],
    "name:pol_x_preferred":[
        "Nir Mosze"
    ],
    "name:und_x_variant":[
        "Eastern Shoval 1",
        "Shoval Mizra\u1e96i A\u1e96at"
    ],
    "wof:name":"Nir Moshe",
    "wof:placetype":"locality"
},
  "geometry": {"coordinates":[34.63204,31.47812],"type":"Point"}
}