{
  "type": "Feature",
  "properties": {
    "gn:admin1_code":"02",
    "gn:asciiname":"Kokhav Ya'ir",
    "gn:country_code":"IL",
    "gn:dem":92,
    "gn:feature_class":"P",
    "gn:feature_code":"PPL",
    "gn:name":"Kokhav Ya\u2019ir",
    "gn:population":0,
    "gn:timezone":"Asia/Jerusalem",
    "iso:country":"IL",
    "name:heb_x_preferred":[
        "Kokhav Ya\u2019ir"
    ],
    "name:heb_x_variant":[
        "\u05db\u05d5\u05db\u05d1 \u05d9\u05d0\u05d9\u05e8"
    ],
    "wof:name":"Kokhav Ya'ir",
    "wof:placetype":"locality"
},
  "geometry": {"coordinates":[35.00222,32.22623],"type":"Point"}
}