{
  "type": "Feature",
  "properties": {
    "gn:admin1_code":"03",
    "gn:asciiname":"Lotem",
    "gn:country_code":"IL",
    "gn:dem":340,
    "gn:feature_class":"P",
    "gn:feature_code":"PPL",
    "gn:name":"Lotem",
    "gn:population":0,
    "gn:timezone":"Asia/Jerusalem",
    "iso:country":"IL",
    "name:ces_x_preferred":[
        "Lotem"
    ],
    "name:heb_x_preferred":[
        "\u05dc\u05d8\u05dd"
    ],
    "name:heb_x_variant":[
        "\u05dc\u05d5\u05d8\u05dd"
    ],
    "name:nno_x_preferred":[
        "Lotem"
    ],
    "name:pol_x_preferred":[
        "Lotem"
    ],
    "wof:name":"Lotem",
    "wof:placetype":"locality"
},
  "geometry": {"coordinates":[35.35882,32.88179],"type":"Point"}
}