{
  "type": "Feature",
  "properties": {
    "gn:admin1_code":"01",
    "gn:asciiname":"Nogah",
    "gn:country_code":"IL",
    "gn:dem":108,
    "gn:feature_class":"P",
    "gn:feature_code":"PPL",
    "gn:name":"Nogah",
    "gn:population":0,
    "gn:timezone":"Asia/Jerusalem",
    "iso:country":"IL",
    "name:ces_x_preferred":[
        "Noga"
    ],
    "name:heb_x_preferred":[
        "\u05e0\u05d2\u05d4"
    ],
    "name:heb_x_variant":[
        "\u05e0\u05d5\u05d2\u05d4"
    ],
    "name:pol_x_preferred":[
        "Nogah"
    ],
    "name:und_x_variant":[
        "Noga",
        "Nogah"
    ],
    "wof:name":"Nogah",
    "wof:placetype":"locality"
},
  "geometry": {"coordinates":[34.6949,31.62485],"type":"Point"}
}