{
  "type": "Feature",
  "properties": {
    "gn:admin1_code":"01",
    "gn:asciiname":"Giv'ot Bar",
    "gn:country_code":"IL",
    "gn:dem":229,
    "gn:feature_class":"P",
    "gn:feature_code":"PPL",
    "gn:name":"Giv'ot Bar",
    "gn:population":0,
    "gn:timezone":"Asia/Jerusalem",
    "iso:country":"IL",
    "name:ces_x_preferred":[
        "Giv'ot Bar"
    ],
    "name:heb_x_preferred":[
        "\u05d2\u05d1\u05e2\u05d5\u05ea \u05d1\u05e8"
    ],
    "name:nno_x_preferred":[
        "Giv'ot Bar"
    ],
    "name:pol_x_preferred":[
        "Gewa\u2019ot Bar"
    ],
    "wof:name":"Giv'ot Bar",
    "wof:placetype":"locality"
},
  "geometry": {"coordinates":[34.75525,31.3565],"type":"Point"}
}