{
  "type": "Feature",
  "properties": {
    "gn:admin1_code":"03",
    "gn:asciiname":"Majdal Shams",
    "gn:cc2":"SY",
    "gn:country_code":"IL",
    "gn:dem":1185,
    "gn:feature_class":"P",
    "gn:feature_code":"PPL",
    "gn:name":"Majdal Shams",
    "gn:population":0,
    "gn:timezone":"Asia/Damascus",
    "iso:country":"IL",
    "name:ara_x_preferred":[
        "\u0645\u062c\u062f\u0644 \u0634\u0645\u0633"
    ],
    "name:ces_x_preferred":[
        "Mad\u017edal \u0160ams"
    ],
    "name:fas_x_preferred":[
        "\u0645\u062c\u062f\u0644 \u0634\u0645\u0633"
    ],
    "name:heb_x_preferred":[
        "\u05de\u05d2\u05d3\u05dc \u05e9\u05de\u05e1"
    ],
    "name:pol_x_preferred":[
        "Mad\u017cdal Szams"
    ],
    "name:rus_x_preferred":[
        "\u041c\u0430\u0434\u0436\u0434\u0430\u043b\u044c-\u0428\u0430\u043c\u0441"
    ],
    "name:und_x_variant":[
        "Majd el Chams",
        "Majdal-esh-Shems",
        "Majdal Shams",
        "Majdel Chams"
    ],
    "wof:name":"Majdal Shams",
    "wof:placetype":"locality"
},
  "geometry": {"coordinates":[35.76972,33.27],"type":"Point"}
}