{
  "type": "Feature",
  "properties": {
    "gn:admin1_code":"04",
    "gn:asciiname":"Kefar Hasidim Alef",
    "gn:country_code":"IL",
    "gn:dem":11,
    "gn:feature_class":"P",
    "gn:feature_code":"PPL",
    "gn:name":"Kefar H\u0331asidim Alef",
    "gn:population":0,
    "gn:timezone":"Asia/Jerusalem",
    "iso:country":"IL",
    "name:heb_x_preferred":[
        "\u05db\u05e4\u05e8 \u05d7\u05e1\u05d9\u05d3\u05d9\u05dd"
    ],
    "name:heb_x_variant":[
        "Kefar H\u0331asidim Alef",
        "\u05db\u05e4\u05e8 \u05d7\u05e1\u05d9\u05d3\u05d9\u05dd \u05d0"
    ],
    "name:und_x_variant":[
        "Kefar Hassidim",
        "Kefar H\u0331asidim"
    ],
    "wof:name":"Kefar Hasidim Alef",
    "wof:placetype":"locality"
},
  "geometry": {"coordinates":[35.09137,32.74867],"type":"Point"}
}