{
  "type": "Feature",
  "properties": {
    "gn:admin1_code":"01",
    "gn:asciiname":"Berosh",
    "gn:country_code":"IL",
    "gn:dem":130,
    "gn:feature_class":"P",
    "gn:feature_code":"PPL",
    "gn:name":"Berosh",
    "gn:population":0,
    "gn:timezone":"Asia/Jerusalem",
    "iso:country":"IL",
    "name:heb_x_preferred":[
        "\u05d1\u05e8\u05d5\u05e9"
    ],
    "name:und_x_variant":[
        "Wadi Sharia A",
        "Brosh",
        "Neta\u2019im Training Unit",
        "Berosh"
    ],
    "wof:name":"Berosh",
    "wof:placetype":"locality"
},
  "geometry": {"coordinates":[34.63395,31.37121],"type":"Point"}
}