{
  "type": "Feature",
  "properties": {
    "iso:country":"IL",
    "name:ara_x_preferred":[
        "\u062d\u0631\u0641\u064a\u0634"
    ],
    "name:arz_x_preferred":[
        "\u062d\u0631\u0641\u064a\u0634"
    ],
    "name:ceb_x_preferred":[
        "\u1e24urfeish"
    ],
    "name:ces_x_preferred":[
        "Churfej\u0161"
    ],
    "name:eng_x_preferred":[
        "Hurfeish"
    ],
    "name:fin_x_preferred":[
        "Hurfeish"
    ],
    "name:heb_x_preferred":[
        "\u05d7\u05d5\u05e8\u05e4\u05d9\u05e9"
    ],
    "name:heb_x_variant":[
        "\u1e24urfeish",
        "\u05d7\u05e8\u05e4\u05d9\u05e9"
    ],
    "name:ind_x_preferred":[
        "Hurfeish"
    ],
    "name:nld_x_preferred":[
        "Hurfeish"
    ],
    "name:nno_x_preferred":[
        "Hurfeish"
    ],
    "name:pol_x_preferred":[
        "Churfeisz"
    ],
    "name:rus_x_preferred":[
        "\u0425\u0443\u0440\u0444\u0435\u0439\u0448"
    ],
    "name:spa_x_preferred":[
        "Horfeis"
    ],
    "name:swe_x_preferred":[
        "\u1e24urfeish"
    ],
    "name:und_x_variant":[
        "Hourfeich"
    ],
    "qs:gn_country":"IL",
    "qs:gn_fcode":"PPL",
    "qs:gn_pop":5308,
    "qs:name":"Hurfeish",
    "qs:name_adm0":"Israel",
    "qs:name_adm1":"Northern",
    "qs:photos":0,
    "qs:photos_1k":0,
    "qs:photos_9k":0,
    "qs:photos_9r":0,
    "qs:photos_all":0,
    "qs:photos_sr":0,
    "qs:placetype":"Town",
    "qs:pop_sr":"5",
    "qs:woe_adm0":23424852,
    "wd:wordcount":1007,
    "wof:name":"Hurfeish",
    "wof:placetype":"locality",
    "wof:population":5308
},
  "geometry": {"coordinates":[35.34835,33.01711],"type":"Point"}
}