{
  "type": "Feature",
  "properties": {
    "gn:admin1_code":"04",
    "gn:asciiname":"Ma`bara",
    "gn:country_code":"IL",
    "gn:dem":24,
    "gn:feature_class":"P",
    "gn:feature_code":"PPL",
    "gn:name":"Ma\u2018bara",
    "gn:population":0,
    "gn:timezone":"Asia/Jerusalem",
    "iso:country":"IL",
    "name:und_x_variant":[
        "Ma\u2018abarat Tirah",
        "Ma\u2018b\u0101r\u0101h",
        "Ma\u2018bara"
    ],
    "wof:name":"Ma`bara",
    "wof:placetype":"locality"
},
  "geometry": {"coordinates":[34.96667,32.76667],"type":"Point"}
}