{
  "type": "Feature",
  "properties": {
    "gn:admin1_code":"00",
    "gn:asciiname":"Ramat Eliyyahu",
    "gn:country_code":"IL",
    "gn:dem":61,
    "gn:feature_class":"P",
    "gn:feature_code":"PPL",
    "gn:name":"Ramat Eliyyahu",
    "gn:population":0,
    "gn:timezone":"Asia/Jerusalem",
    "iso:country":"IL",
    "wof:name":"Ramat Eliyyahu",
    "wof:placetype":"neighbourhood"
},
  "geometry": {"coordinates":[34.785,31.98778],"type":"Point"}
}