{
  "type": "Feature",
  "properties": {
    "gn:admin1_code":"01",
    "gn:asciiname":"Talme Yafe",
    "gn:country_code":"IL",
    "gn:dem":81,
    "gn:feature_class":"P",
    "gn:feature_code":"PPL",
    "gn:name":"Talm\u00e9 Yafe",
    "gn:population":0,
    "gn:timezone":"Asia/Jerusalem",
    "iso:country":"IL",
    "name:ces_x_preferred":[
        "Talmej Jafe"
    ],
    "name:heb_x_preferred":[
        "Talm\u00e9 Yafe"
    ],
    "name:heb_x_variant":[
        "\u05ea\u05dc\u05de\u05d9 \u05d9\u05e4\u05d4"
    ],
    "name:nno_x_preferred":[
        "Talmei Yafeh"
    ],
    "name:pol_x_preferred":[
        "Talme Jafe"
    ],
    "name:und_x_variant":[
        "Lahat",
        "Talmei Yafeh",
        "Talmei Yafe",
        "Talme Yafeh"
    ],
    "wof:name":"Talme Yafe",
    "wof:placetype":"locality"
},
  "geometry": {"coordinates":[34.61273,31.61734],"type":"Point"}
}