{
  "type": "Feature",
  "properties": {
    "gn:admin1_code":"02",
    "gn:asciiname":"Ganne Hadar",
    "gn:country_code":"IL",
    "gn:dem":89,
    "gn:feature_class":"P",
    "gn:feature_code":"PPL",
    "gn:name":"Gann\u00e9 Hadar",
    "gn:population":0,
    "gn:timezone":"Asia/Jerusalem",
    "iso:country":"IL",
    "name:ces_x_preferred":[
        "Ganej Hadar"
    ],
    "name:heb_x_preferred":[
        "Gann\u00e9 Hadar"
    ],
    "name:heb_x_variant":[
        "\u05d2\u05e0\u05d9 \u05d4\u05d3\u05e8"
    ],
    "name:nno_x_preferred":[
        "Ganei Hadar"
    ],
    "name:pol_x_preferred":[
        "Ganne Hadar"
    ],
    "wof:name":"Ganne Hadar",
    "wof:placetype":"locality"
},
  "geometry": {"coordinates":[34.85363,31.87858],"type":"Point"}
}