{
  "type": "Feature",
  "properties": {
    "gn:admin1_code":"03",
    "gn:asciiname":"Qeren",
    "gn:country_code":"IL",
    "gn:dem":382,
    "gn:feature_class":"P",
    "gn:feature_code":"PPL",
    "gn:name":"Qeren",
    "gn:population":0,
    "gn:timezone":"Asia/Jerusalem",
    "iso:country":"IL",
    "name:heb_x_preferred":[
        "\u05e7\u05e8\u05df"
    ],
    "name:und_x_variant":[
        "Keren"
    ],
    "wof:name":"Qeren",
    "wof:placetype":"locality"
},
  "geometry": {"coordinates":[35.55622,33.09475],"type":"Point"}
}