{
  "type": "Feature",
  "properties": {
    "gn:admin1_code":"06",
    "gn:asciiname":"Tal Shahar",
    "gn:country_code":"IL",
    "gn:dem":126,
    "gn:feature_class":"P",
    "gn:feature_code":"PPL",
    "gn:name":"Tal Sha\u1e96ar",
    "gn:population":0,
    "gn:timezone":"Asia/Jerusalem",
    "iso:country":"IL",
    "name:ces_x_preferred":[
        "Tal \u0160achar"
    ],
    "name:heb_x_preferred":[
        "\u05d8\u05dc \u05e9\u05d7\u05e8"
    ],
    "name:nno_x_preferred":[
        "Tal Shahar"
    ],
    "name:pol_x_preferred":[
        "Tal Szachar"
    ],
    "name:por_x_preferred":[
        "Tal Shahar"
    ],
    "name:und_x_variant":[
        "Tal Sha\u1e96ar"
    ],
    "wof:name":"Tal Shahar",
    "wof:placetype":"locality"
},
  "geometry": {"coordinates":[34.90111,31.80469],"type":"Point"}
}