{
  "type": "Feature",
  "properties": {
    "gn:admin1_code":"03",
    "gn:asciiname":"Muqeibila",
    "gn:country_code":"IL",
    "gn:dem":97,
    "gn:feature_class":"P",
    "gn:feature_code":"PPL",
    "gn:name":"Muqeibila",
    "gn:population":0,
    "gn:timezone":"Asia/Jerusalem",
    "iso:country":"IL",
    "name:ara_x_preferred":[
        "\u0645\u0642\u064a\u0628\u0644\u0629"
    ],
    "name:ces_x_preferred":[
        "Mukejbla"
    ],
    "name:heb_x_preferred":[
        "\u05de\u05e7\u05d9\u05d1\u05dc\u05d4"
    ],
    "name:heb_x_variant":[
        "\u05de\u05d5\u05e7\u05d9\u05d9\u05d1\u05dc\u05d4"
    ],
    "name:nno_x_preferred":[
        "Muqeible"
    ],
    "name:pol_x_preferred":[
        "Mukajbila"
    ],
    "name:und_x_variant":[
        "Muqeibile",
        "Mukeibileh",
        "Mqeible",
        "Muqeibila"
    ],
    "name:urd_x_preferred":[
        "\u0645\u0642\u06cc\u0628\u0644\u06c1"
    ],
    "wof:name":"Muqeibila",
    "wof:placetype":"locality"
},
  "geometry": {"coordinates":[35.29617000000001,32.51424],"type":"Point"}
}