{
  "type": "Feature",
  "properties": {
    "iso:country":"IL",
    "name:eng_x_colloquial":[
        "Ahuzzat Shemuel",
        "Ahuzzat Shemu\u2019el"
    ],
    "name:eng_x_preferred":[
        "Ah\u0331uzzat Shemu\u2019el"
    ],
    "name:eng_x_variant":[
        "Ahutzasamuel",
        "Ahuzat Samuel",
        "Ahuzat Sir Herbert Samuel",
        "Ahuzza",
        "Ahuzzat Sir Herbert Samuel"
    ],
    "qs:gn_adm0_cc":"IL",
    "qs:gn_local":294801,
    "qs:gn_nam_loc":"Haifa, Haifa, IL",
    "qs:gn_namadm1":"04",
    "qs:local_max":13408,
    "qs:local_sum":25534,
    "qs:localhoods":8,
    "qs:name":"Ah\u0331uzzat Shemu\u2019el",
    "qs:name_adm0":"Israel",
    "qs:name_adm1":"Haifa",
    "qs:name_local":"Haifa",
    "qs:photo_max":195,
    "qs:photo_sum":1557,
    "qs:placetype":"Suburb",
    "qs:quad_count":74,
    "qs:woe_adm0":23424852,
    "qs:woe_adm1":2345794,
    "qs:woe_adm2":0,
    "qs:woe_lau":0,
    "qs:woe_local":1967449,
    "qs:woe_ver":"7.10.0",
    "wof:lang":[
        "eng"
    ],
    "wof:name":"Ah\u0331uzzat Shemu\u2019el",
    "wof:placetype":"neighbourhood"
},
  "geometry": {"coordinates":[34.979522,32.777223],"type":"Point"}
}