{
  "type": "Feature",
  "properties": {
    "gn:admin1_code":"03",
    "gn:asciiname":"Julis",
    "gn:country_code":"IL",
    "gn:dem":105,
    "gn:feature_class":"P",
    "gn:feature_code":"PPL",
    "gn:name":"J\u016blis",
    "gn:population":0,
    "gn:timezone":"Asia/Jerusalem",
    "iso:country":"IL",
    "name:ara_x_preferred":[
        "\u062c\u0648\u0644\u0633"
    ],
    "name:ces_x_preferred":[
        "D\u017eulis"
    ],
    "name:deu_x_preferred":[
        "Dschulis"
    ],
    "name:heb_x_preferred":[
        "J\u016blis"
    ],
    "name:heb_x_variant":[
        "\u05d2\u2019\u05d5\u05dc\u05e1",
        "\u05d2'\u05d5\u05dc\u05d9\u05e1"
    ],
    "name:jpn_x_preferred":[
        "\u30b8\u30e5\u30ea\u30b9"
    ],
    "name:nno_x_preferred":[
        "Julis"
    ],
    "name:pol_x_preferred":[
        "Julis"
    ],
    "name:rus_x_preferred":[
        "\u0414\u0436\u0443\u043b\u0438\u0441"
    ],
    "name:und_x_variant":[
        "\u011eulis"
    ],
    "wof:name":"Julis",
    "wof:placetype":"locality"
},
  "geometry": {"coordinates":[35.18278,32.94267],"type":"Point"}
}