{
  "type": "Feature",
  "properties": {
    "gn:admin1_code":"03",
    "gn:asciiname":"Julis",
    "gn:country_code":"IL",
    "gn:dem":105,
    "gn:feature_class":"P",
    "gn:feature_code":"PPL",
    "gn:name":"J\u016blis",
    "gn:population":0,
    "gn:timezone":"Asia/Jerusalem",
    "iso:country":"IL",
    "name:heb_x_preferred":[
        "J\u016blis"
    ],
    "name:heb_x_variant":[
        "\u05d2\u2019\u05d5\u05dc\u05e1"
    ],
    "name:und_x_variant":[
        "J\u016blis",
        "\u011eulis"
    ],
    "wof:name":"Julis",
    "wof:placetype":"locality"
},
  "geometry": {"coordinates":[35.18278,32.94267],"type":"Point"}
}