{
  "type": "Feature",
  "properties": {
    "gn:admin1_code":"03",
    "gn:asciiname":"Sde Ilan",
    "gn:cc2":"IL",
    "gn:country_code":"IL",
    "gn:dem":186,
    "gn:feature_class":"P",
    "gn:feature_code":"PPL",
    "gn:name":"Sde Ilan",
    "gn:population":0,
    "gn:timezone":"Asia/Jerusalem",
    "iso:country":"IL",
    "name:ceb_x_preferred":[
        "Sde Ilan"
    ],
    "name:ces_x_preferred":[
        "Sde Ilan"
    ],
    "name:heb_x_preferred":[
        "\u05e9\u05d3\u05d4 \u05d0\u05d9\u05dc\u05df"
    ],
    "name:nno_x_preferred":[
        "Sde Ilan"
    ],
    "name:pol_x_preferred":[
        "Sede Ilan"
    ],
    "name:swe_x_preferred":[
        "Sde Ilan"
    ],
    "name:und_x_variant":[
        "Mitspe Hagalil",
        "Sedeh Ilan",
        "Mitspeh Hagalil",
        "Sede Ilan"
    ],
    "wof:name":"Sde Ilan",
    "wof:placetype":"locality"
},
  "geometry": {"coordinates":[35.42222,32.74861],"type":"Point"}
}