{
  "type": "Feature",
  "properties": {
    "iso:country":"IL",
    "name:ces_x_preferred":[
        "E\u0161el ha-Nasi"
    ],
    "name:cze_x_preferred":[
        "E\u0161el ha-Nasi"
    ],
    "name:dut_x_preferred":[
        "Eshel HaNasi"
    ],
    "name:eng_x_preferred":[
        "Eshel HaNasi"
    ],
    "name:heb_x_preferred":[
        "\u05d0\u05e9\u05dc \u05d4\u05e0\u05e9\u05d9\u05d0"
    ],
    "name:nno_x_preferred":[
        "Eshel HaNasi"
    ],
    "name:pol_x_preferred":[
        "Eszel HaNasi"
    ],
    "qs:gn_country":"IL",
    "qs:gn_fcode":"PPL",
    "qs:gn_pop":0,
    "qs:name":"Eshel HaNasi",
    "qs:name_adm0":"Israel",
    "qs:name_adm1":"Southern",
    "qs:photos":23,
    "qs:photos_1k":5,
    "qs:photos_9k":1,
    "qs:photos_9r":1,
    "qs:photos_all":23,
    "qs:photos_sr":1,
    "qs:placetype":"Town",
    "qs:pop_sr":"0",
    "qs:woe_adm0":23424852,
    "wd:wordcount":133,
    "wof:name":"Eshel HaNasi",
    "wof:placetype":"locality"
},
  "geometry": {"coordinates":[34.69744,31.32567],"type":"Point"}
}