{
  "type": "Feature",
  "properties": {
    "gn:admin1_code":"01",
    "gn:asciiname":"Shahar",
    "gn:country_code":"IL",
    "gn:dem":107,
    "gn:feature_class":"P",
    "gn:feature_code":"PPL",
    "gn:name":"Sha\u1e96ar",
    "gn:population":0,
    "gn:timezone":"Asia/Jerusalem",
    "iso:country":"IL",
    "name:ces_x_preferred":[
        "\u0160achar"
    ],
    "name:heb_x_preferred":[
        "Sha\u1e96ar"
    ],
    "name:heb_x_variant":[
        "\u05e9\u05d7\u05e8"
    ],
    "name:pol_x_preferred":[
        "Szachar"
    ],
    "wof:name":"Shahar",
    "wof:placetype":"locality"
},
  "geometry": {"coordinates":[34.72416,31.61923],"type":"Point"}
}