{
  "type": "Feature",
  "properties": {
    "iso:country":"IL",
    "name:als_x_preferred":[
        "Caesarea"
    ],
    "name:ara_x_preferred":[
        "\u0642\u064a\u0633\u0627\u0631\u064a\u0629"
    ],
    "name:bel_x_preferred":[
        "\u041a\u0435\u0441\u0430\u0440\u044b\u044f"
    ],
    "name:cat_x_preferred":[
        "Cesarea"
    ],
    "name:ceb_x_preferred":[
        "Qesarya"
    ],
    "name:ces_x_preferred":[
        "Caesarea"
    ],
    "name:dan_x_preferred":[
        "Caesarea"
    ],
    "name:deu_x_preferred":[
        "Caesarea"
    ],
    "name:eng_x_preferred":[
        "Caesarea"
    ],
    "name:epo_x_preferred":[
        "Cezareo"
    ],
    "name:fas_x_preferred":[
        "\u0642\u06cc\u0635\u0631\u06cc\u0647"
    ],
    "name:fin_x_preferred":[
        "Caesarea"
    ],
    "name:fra_x_preferred":[
        "C\u00e9sar\u00e9e"
    ],
    "name:gsw_x_preferred":[
        "Caesarea"
    ],
    "name:hbs_x_preferred":[
        "Cezareja"
    ],
    "name:heb_x_preferred":[
        "\u05e7\u05d9\u05e1\u05e8\u05d9\u05d4"
    ],
    "name:ind_x_preferred":[
        "Kaisarea"
    ],
    "name:ita_x_preferred":[
        "Caesarea"
    ],
    "name:jpn_x_preferred":[
        "\u30ab\u30a4\u30b6\u30ea\u30a2"
    ],
    "name:lad_x_preferred":[
        "Kesariya"
    ],
    "name:nld_x_preferred":[
        "Caesarea"
    ],
    "name:nno_x_preferred":[
        "Caesarea"
    ],
    "name:oci_x_preferred":[
        "Cesar\u00e8a"
    ],
    "name:pol_x_preferred":[
        "Cezarea"
    ],
    "name:por_x_preferred":[
        "Cesareia"
    ],
    "name:ron_x_preferred":[
        "Caesarea"
    ],
    "name:rus_x_preferred":[
        "\u041a\u0435\u0441\u0430\u0440\u0438\u044f"
    ],
    "name:spa_x_preferred":[
        "Cesarea"
    ],
    "name:srp_x_preferred":[
        "\u0426\u0435\u0437\u0430\u0440\u0435\u0458\u0430"
    ],
    "name:swe_x_preferred":[
        "Qesarya"
    ],
    "name:tur_x_preferred":[
        "Kayserya"
    ],
    "name:ukr_x_preferred":[
        "\u041a\u0435\u0441\u0430\u0440\u0456\u044f"
    ],
    "name:unk_x_variant":[
        "Kaysaria"
    ],
    "name:urd_x_preferred":[
        "\u0642\u06cc\u0635\u0631\u06cc\u06c1"
    ],
    "name:vie_x_preferred":[
        "Caesarea"
    ],
    "name:zho_x_preferred":[
        "\u51ef\u6492\u5229\u4e9a"
    ],
    "qs:gn_country":"IL",
    "qs:gn_fcode":"PPL",
    "qs:gn_pop":4500,
    "qs:name":"Caesarea",
    "qs:name_adm0":"Israel",
    "qs:name_adm1":"Haifa",
    "qs:photos":3784,
    "qs:photos_1k":767,
    "qs:photos_9k":17,
    "qs:photos_9r":12,
    "qs:photos_all":3784,
    "qs:photos_sr":21,
    "qs:placetype":"Town",
    "qs:pop_sr":"4",
    "qs:woe_adm0":23424852,
    "wd:wordcount":3527,
    "wof:name":"Caesarea",
    "wof:placetype":"locality",
    "wof:population":4500
},
  "geometry": {"coordinates":[34.90459,32.51888],"type":"Point"}
}