{
  "type": "Feature",
  "properties": {
    "gn:admin1_code":"03",
    "gn:asciiname":"Kisra",
    "gn:country_code":"IL",
    "gn:dem":714,
    "gn:feature_class":"P",
    "gn:feature_code":"PPL",
    "gn:name":"Kisr\u0101",
    "gn:population":0,
    "gn:timezone":"Asia/Jerusalem",
    "iso:country":"IL",
    "name:ast_x_preferred":[
        "Kisra"
    ],
    "name:fra_x_preferred":[
        "Kisra"
    ],
    "name:heb_x_preferred":[
        "Kisr\u0101"
    ],
    "name:heb_x_variant":[
        "\u05db\u05e1\u05e8\u05d0"
    ],
    "name:spa_x_preferred":[
        "Kisra"
    ],
    "name:und_x_variant":[
        "Qisrah",
        "Kisrah"
    ],
    "wof:name":"Kisra",
    "wof:placetype":"locality"
},
  "geometry": {"coordinates":[35.3029,32.96239],"type":"Point"}
}