{
  "type": "Feature",
  "properties": {
    "iso:country":"IL",
    "name:cze_x_preferred":[
        "Kfar Dani'el"
    ],
    "name:dut_x_preferred":[
        "Kfar Daniel"
    ],
    "name:eng_x_preferred":[
        "Kfar Daniel"
    ],
    "name:fre_x_preferred":[
        "Kfar Daniel"
    ],
    "name:heb_x_preferred":[
        "\u05db\u05e4\u05e8 \u05d3\u05e0\u05d9\u05d0\u05dc"
    ],
    "name:nno_x_preferred":[
        "Kfar Daniel"
    ],
    "name:pol_x_preferred":[
        "Kfar Daniel"
    ],
    "name:rus_x_preferred":[
        "\u041a\u0444\u0430\u0440-\u0414\u0430\u043d\u0438\u044d\u043b\u044c"
    ],
    "name:unk_x_variant":[
        "D\u0101niy\u0101l"
    ],
    "qs:gn_country":"IL",
    "qs:gn_fcode":"PPL",
    "qs:gn_pop":0,
    "qs:name":"Kefar Daniyyel",
    "qs:name_adm0":"Israel",
    "qs:name_adm1":"Central",
    "qs:photos":60,
    "qs:photos_1k":12,
    "qs:photos_9k":1,
    "qs:photos_9r":2,
    "qs:photos_all":60,
    "qs:photos_sr":2,
    "qs:placetype":"Town",
    "qs:pop_sr":"0",
    "qs:woe_adm0":23424852,
    "wof:name":"Kefar Daniyyel",
    "wof:placetype":"locality"
},
  "geometry": {"coordinates":[34.93165,31.93424],"type":"Point"}
}