{
  "type": "Feature",
  "properties": {
    "iso:country":"IL",
    "name:ces_x_preferred":[
        "Ma'agan Micha'el"
    ],
    "name:deu_x_preferred":[
        "Ma\u2019agan Micha\u2019el"
    ],
    "name:eng_x_preferred":[
        "Ma'agan Michael"
    ],
    "name:heb_x_preferred":[
        "\u05de\u05e2\u05d2\u05df \u05de\u05d9\u05db\u05d0\u05dc"
    ],
    "name:heb_x_variant":[
        "Ma\u2018agan Mikha\u2019el"
    ],
    "name:nld_x_preferred":[
        "Ma'agan Michael"
    ],
    "name:nno_x_preferred":[
        "Ma'agan Michael"
    ],
    "name:nob_x_preferred":[
        "Ma'agan Michael"
    ],
    "name:nor_x_preferred":[
        "Ma'agan Michael"
    ],
    "name:pol_x_preferred":[
        "Ma\u2019agan Micha\u2019el"
    ],
    "name:rus_x_preferred":[
        "\u041c\u0430\u0430\u0433\u0430\u043d-\u041c\u0438\u0445\u0430\u044d\u043b\u044c"
    ],
    "name:tur_x_preferred":[
        "Ma'agan Michael"
    ],
    "name:unk_x_variant":[
        "Hatsofim Alef"
    ],
    "qs:gn_country":"IL",
    "qs:gn_fcode":"PPL",
    "qs:gn_pop":0,
    "qs:name":"Maagan Mikha'el",
    "qs:name_adm0":"Israel",
    "qs:name_adm1":"Haifa",
    "qs:photos":449,
    "qs:photos_1k":91,
    "qs:photos_9k":2,
    "qs:photos_9r":5,
    "qs:photos_all":449,
    "qs:photos_sr":6,
    "qs:placetype":"Town",
    "qs:pop_sr":"0",
    "qs:woe_adm0":23424852,
    "wd:wordcount":1326,
    "wof:name":"Maagan Mikha'el",
    "wof:placetype":"locality"
},
  "geometry": {"coordinates":[34.91638,32.55549],"type":"Point"}
}