{
  "type": "Feature",
  "properties": {
    "iso:country":"IL",
    "name:amh_x_preferred":[
        "\u121b\u12d3\u130b\u1295 \u121a\u12bb\u12a4\u120d"
    ],
    "name:ara_x_preferred":[
        "\u0645\u064e\u0639\u064e\u0686\u064e\u0646 \u0645\u0650\u064a\u062e\u064e\u0627\u0626\u0650\u064a\u0644"
    ],
    "name:ces_x_preferred":[
        "Ma'agan Micha'el"
    ],
    "name:deu_x_preferred":[
        "Ma\u2019agan Micha\u2019el"
    ],
    "name:eng_x_preferred":[
        "Ma'agan Michael"
    ],
    "name:fas_x_preferred":[
        "\u0645\u0627\u06af\u0627\u0646 \u0645\u06cc\u0634\u06cc\u0644"
    ],
    "name:fra_x_preferred":[
        "Ma'agan Michael"
    ],
    "name:heb_x_preferred":[
        "\u05de\u05e2\u05d2\u05df \u05de\u05d9\u05db\u05d0\u05dc"
    ],
    "name:heb_x_variant":[
        "Ma\u2018agan Mikha\u2019el"
    ],
    "name:jpn_x_preferred":[
        "\u30de\u30fc\u30ac\u30f3\u30df\u30ab\u30a8\u30eb"
    ],
    "name:kor_x_preferred":[
        "\ub9c8\uc544\uac04 \ubbf8\uce74\uc5d8"
    ],
    "name:nld_x_preferred":[
        "Ma'agan Michael"
    ],
    "name:nno_x_preferred":[
        "Ma'agan Michael"
    ],
    "name:nob_x_preferred":[
        "Ma'agan Michael"
    ],
    "name:nor_x_preferred":[
        "Ma'agan Michael"
    ],
    "name:pol_x_preferred":[
        "Ma\u2019agan Micha\u2019el"
    ],
    "name:pol_x_variant":[
        "Maagan Michael"
    ],
    "name:ron_x_preferred":[
        "Maagan Mihael"
    ],
    "name:rus_x_preferred":[
        "\u041c\u0430\u0430\u0433\u0430\u043d-\u041c\u0438\u0445\u0430\u044d\u043b\u044c"
    ],
    "name:tur_x_preferred":[
        "Ma'agan Michael"
    ],
    "name:und_x_variant":[
        "Hatsofim Alef"
    ],
    "qs:gn_country":"IL",
    "qs:gn_fcode":"PPL",
    "qs:gn_pop":0,
    "qs:name":"Maagan Mikha'el",
    "qs:name_adm0":"Israel",
    "qs:name_adm1":"Haifa",
    "qs:photos":449,
    "qs:photos_1k":91,
    "qs:photos_9k":2,
    "qs:photos_9r":5,
    "qs:photos_all":449,
    "qs:photos_sr":6,
    "qs:placetype":"Town",
    "qs:pop_sr":"0",
    "qs:woe_adm0":23424852,
    "wd:wordcount":1326,
    "wof:name":"Maagan Mikha'el",
    "wof:placetype":"locality"
},
  "geometry": {"coordinates":[34.91638,32.55549],"type":"Point"}
}