{
  "type": "Feature",
  "properties": {
    "gn:country":"IL",
    "gn:fcode":"PPL",
    "gn:population":2509,
    "iso:country":"IL",
    "name:ara_x_preferred":[
        "\u0643\u0641\u0627\u0631 \u0623\u0648\u0631\u0627\u0646\u064a\u0645"
    ],
    "name:ceb_x_preferred":[
        "Kfar NaOranim"
    ],
    "name:ces_x_preferred":[
        "Kfar ha-Oranim"
    ],
    "name:eng_x_preferred":[
        "Kfar HaOranim"
    ],
    "name:fra_x_preferred":[
        "Kfar HaOranim"
    ],
    "name:heb_x_colloquial":[
        "\u05db\u05e4\u05e8 \u05d4\u05d0\u05d5\u05e8\u05e0\u05d9\u05dd"
    ],
    "name:heb_x_historical":[
        "\u05db\u05e4\u05e8 \u05d4\u05d0\u05d5\u05e8\u05e0\u05d9\u05dd"
    ],
    "name:heb_x_preferred":[
        "\u05db\u05e4\u05e8 \u05d4\u05d0\u05d5\u05e8\u05e0\u05d9\u05dd"
    ],
    "name:nld_x_preferred":[
        "Kfar HaOranim"
    ],
    "name:nno_x_preferred":[
        "Kfar HaOranim"
    ],
    "name:pol_x_preferred":[
        "Kefar HaOranim"
    ],
    "name:rus_x_preferred":[
        "\u041a\u0444\u0430\u0440-\u0445\u0430-\u041e\u0440\u0430\u043d\u0438\u043c"
    ],
    "name:swe_x_preferred":[
        "Kfar NaOranim"
    ],
    "qs:name":"Kfar NaOranim",
    "qs:photos_9r":0,
    "qs:photos_sr":0,
    "qs:pop_sr":"4",
    "wof:name":"Kfar NaOranim",
    "wof:placetype":"locality",
    "wof:population":2509
},
  "geometry": {"coordinates":[35.03669,31.91982],"type":"Point"}
}