{
  "type": "Feature",
  "properties": {
    "gn:admin1_code":"02",
    "gn:asciiname":"Bet Rabban",
    "gn:country_code":"IL",
    "gn:dem":62,
    "gn:feature_class":"P",
    "gn:feature_code":"PPL",
    "gn:name":"Bet Rabban",
    "gn:population":0,
    "gn:timezone":"Asia/Jerusalem",
    "iso:country":"IL",
    "name:heb_x_preferred":[
        "\u05d1\u05d9\u05ea \u05e8\u05d1\u05df"
    ],
    "name:und_x_variant":[
        "Beit-Raban",
        "Bet Rabban"
    ],
    "wof:name":"Bet Rabban",
    "wof:placetype":"locality"
},
  "geometry": {"coordinates":[34.72937,31.81677],"type":"Point"}
}