{
  "type": "Feature",
  "properties": {
    "iso:country":"IL",
    "name:ces_x_preferred":[
        "Kfar ha-No'ar ha-Dati"
    ],
    "name:eng_x_preferred":[
        "Kfar HaNoar HaDati"
    ],
    "name:heb_x_preferred":[
        "\u05db\u05e4\u05e8 \u05d4\u05e0\u05d5\u05e2\u05e8 \u05d4\u05d3\u05ea\u05d9"
    ],
    "name:heb_x_variant":[
        "Kefar HaNo\u2018ar HaDati",
        "\u05db\u05e4\u05e8 \u05d4\u05e0\u05e2\u05e8 \u05d4\u05d3\u05ea\u05d9"
    ],
    "name:nld_x_preferred":[
        "Kfar HaNoar HaDati"
    ],
    "name:nno_x_preferred":[
        "Kfar HaNoar HaDati"
    ],
    "qs:gn_country":"IL",
    "qs:gn_fcode":"PPL",
    "qs:gn_pop":0,
    "qs:name":"Kefar HaNoar HaDati",
    "qs:name_adm0":"Israel",
    "qs:name_adm1":"Haifa",
    "qs:photos":497,
    "qs:photos_1k":101,
    "qs:photos_9k":2,
    "qs:photos_9r":5,
    "qs:photos_all":497,
    "qs:photos_sr":7,
    "qs:placetype":"Town",
    "qs:pop_sr":"0",
    "qs:woe_adm0":23424852,
    "wd:wordcount":91,
    "wof:name":"Kefar HaNoar HaDati",
    "wof:placetype":"locality"
},
  "geometry": {"coordinates":[35.09683,32.7433],"type":"Point"}
}