{
  "type": "Feature",
  "properties": {
    "gn:admin1_code":"03",
    "gn:asciiname":"Mizpe Netofa",
    "gn:country_code":"IL",
    "gn:dem":404,
    "gn:feature_class":"P",
    "gn:feature_code":"PPL",
    "gn:name":"Mi\u1e95p\u00e9 Netofa",
    "gn:population":0,
    "gn:timezone":"Asia/Jerusalem",
    "iso:country":"IL",
    "name:ces_x_preferred":[
        "Micpe Netofa"
    ],
    "name:heb_x_preferred":[
        "Mi\u1e95p\u00e9 Netofa"
    ],
    "name:heb_x_variant":[
        "\u05de\u05e6\u05e4\u05d4 \u05e0\u05d8\u05d5\u05e4\u05d4",
        "Mitsp\u00e9 Netofa"
    ],
    "name:nno_x_preferred":[
        "Mitzpe Netofa"
    ],
    "name:pol_x_preferred":[
        "Micpe Netofa"
    ],
    "wof:name":"Mizpe Netofa",
    "wof:placetype":"locality"
},
  "geometry": {"coordinates":[35.38290999999999,32.80287],"type":"Point"}
}