{
  "type": "Feature",
  "properties": {
    "iso:country":"IL",
    "name:ara_x_preferred":[
        "\u0643\u0641\u0627\u0631 \u0628\u0644\u0648\u0645"
    ],
    "name:arz_x_preferred":[
        "\u0643\u0641\u0627\u0631 \u0628\u0644\u0648\u0645"
    ],
    "name:cat_x_preferred":[
        "Kfar Blum"
    ],
    "name:ceb_x_preferred":[
        "Kefar Blum"
    ],
    "name:ces_x_preferred":[
        "Kfar Blum"
    ],
    "name:deu_x_preferred":[
        "Kfar Blum"
    ],
    "name:eng_x_preferred":[
        "Kfar Blum"
    ],
    "name:fas_x_preferred":[
        "\u06a9\u0641\u0631 \u0628\u0644\u0648\u0645"
    ],
    "name:fin_x_preferred":[
        "Kfar Blum"
    ],
    "name:fra_x_preferred":[
        "Kfar Blum"
    ],
    "name:heb_x_preferred":[
        "\u05db\u05e4\u05e8 \u05d1\u05dc\u05d5\u05dd"
    ],
    "name:nld_x_preferred":[
        "Kfar Bloem"
    ],
    "name:nld_x_variant":[
        "Kfar Blum"
    ],
    "name:nno_x_preferred":[
        "Kfar Blum"
    ],
    "name:pol_x_preferred":[
        "Kefar Blum"
    ],
    "name:pol_x_variant":[
        "Kfar Blum"
    ],
    "name:rus_x_preferred":[
        "\u041a\u0444\u0430\u0440-\u0411\u043b\u044e\u043c"
    ],
    "name:swe_x_preferred":[
        "Kefar Blum"
    ],
    "qs:gn_country":"IL",
    "qs:gn_fcode":"PPL",
    "qs:gn_pop":0,
    "qs:name":"Kefar Blum",
    "qs:name_adm0":"Israel",
    "qs:name_adm1":"Northern",
    "qs:photos":143,
    "qs:photos_1k":29,
    "qs:photos_9k":1,
    "qs:photos_9r":3,
    "qs:photos_all":143,
    "qs:photos_sr":3,
    "qs:placetype":"Town",
    "qs:pop_sr":"0",
    "qs:woe_adm0":23424852,
    "wd:wordcount":443,
    "wof:name":"Kefar Blum",
    "wof:placetype":"locality"
},
  "geometry": {"coordinates":[35.60982,33.17172],"type":"Point"}
}