{
  "type": "Feature",
  "properties": {
    "gn:admin1_code":"01",
    "gn:asciiname":"Yesha`",
    "gn:country_code":"IL",
    "gn:dem":121,
    "gn:feature_class":"P",
    "gn:feature_code":"PPL",
    "gn:name":"Yesha\u2018",
    "gn:population":0,
    "gn:timezone":"Asia/Jerusalem",
    "iso:country":"IL",
    "name:heb_x_preferred":[
        "Yesha\u2018"
    ],
    "name:heb_x_variant":[
        "\u05d9\u05e9\u05e2"
    ],
    "name:und_x_variant":[
        "Yesha"
    ],
    "wof:name":"Yesha`",
    "wof:placetype":"locality"
},
  "geometry": {"coordinates":[34.40276,31.24729],"type":"Point"}
}