{
  "type": "Feature",
  "properties": {
    "iso:country":"IL",
    "name:ces_x_preferred":[
        "Re'im"
    ],
    "name:cze_x_preferred":[
        "Re'im"
    ],
    "name:eng_x_preferred":[
        "Re'im"
    ],
    "name:fra_x_preferred":[
        "R\u00e9\u00efm"
    ],
    "name:fre_x_preferred":[
        "R\u00e9\u00efm"
    ],
    "name:heb_x_preferred":[
        "\u05e8\u05e2\u05d9\u05dd"
    ],
    "name:heb_x_variant":[
        "Re\u2018im",
        "Re\u2019im"
    ],
    "name:nno_x_preferred":[
        "Re'im"
    ],
    "name:pol_x_preferred":[
        "Re'im"
    ],
    "name:swe_x_preferred":[
        "Re\u2018im"
    ],
    "name:unk_x_variant":[
        "Beit Qamah"
    ],
    "qs:gn_country":"IL",
    "qs:gn_fcode":"PPL",
    "qs:gn_pop":0,
    "qs:name":"Reim",
    "qs:name_adm0":"Israel",
    "qs:name_adm1":"Southern",
    "qs:photos":30,
    "qs:photos_1k":6,
    "qs:photos_9k":1,
    "qs:photos_9r":2,
    "qs:photos_all":30,
    "qs:photos_sr":2,
    "qs:placetype":"Town",
    "qs:pop_sr":"0",
    "qs:woe_adm0":23424852,
    "wd:wordcount":753,
    "wof:name":"Reim",
    "wof:placetype":"locality"
},
  "geometry": {"coordinates":[34.45943,31.3853],"type":"Point"}
}