{
  "type": "Feature",
  "properties": {
    "iso:country":"IL",
    "name:ara_x_preferred":[
        "\u0639\u064a\u0646 \u0623\u064a\u0627\u0644\u0627"
    ],
    "name:ces_x_preferred":[
        "Ejn Ajala"
    ],
    "name:eng_x_preferred":[
        "Ein Ayala"
    ],
    "name:heb_x_preferred":[
        "\u05e2\u05d9\u05df \u05d0\u05d9\u05dc\u05d4"
    ],
    "name:nno_x_preferred":[
        "Ein Ayala"
    ],
    "name:pol_x_preferred":[
        "En Ajjala"
    ],
    "name:pol_x_variant":[
        "Ein Ajala"
    ],
    "name:und_x_variant":[
        "Ain Ayala"
    ],
    "qs:gn_country":"IL",
    "qs:gn_fcode":"PPL",
    "qs:gn_pop":0,
    "qs:name":"En Ayyala",
    "qs:name_adm0":"Israel",
    "qs:name_adm1":"Haifa",
    "qs:photos":225,
    "qs:photos_1k":46,
    "qs:photos_9k":1,
    "qs:photos_9r":4,
    "qs:photos_all":225,
    "qs:photos_sr":4,
    "qs:placetype":"Town",
    "qs:pop_sr":"0",
    "qs:woe_adm0":23424852,
    "wd:wordcount":224,
    "wof:name":"En Ayyala",
    "wof:placetype":"locality"
},
  "geometry": {"coordinates":[34.94483,32.62899],"type":"Point"}
}