{
  "type": "Feature",
  "properties": {
    "gn:country":"IL",
    "gn:fcode":"PPL",
    "gn:pop":1100,
    "iso:country":"IL",
    "qs:name":"Midreshet Ben-Gurion",
    "qs:photos_9r":0,
    "qs:photos_sr":0,
    "qs:pop_sr":"3",
    "wd:wordcount":522,
    "wof:name":"Midreshet Ben-Gurion",
    "wof:placetype":"locality",
    "wof:population":1100
},
  "geometry": {"coordinates":[34.7834,30.85154],"type":"Point"}
}