{
  "type": "Feature",
  "properties": {
    "gn:country":"IL",
    "iso:country":"IL",
    "name:ces_x_preferred":[
        "Batej Ungarin"
    ],
    "name:heb_x_preferred":[
        "\u05d1\u05ea\u05d9 \u05d0\u05d5\u05e0\u05d2\u05e8\u05d9\u05df"
    ],
    "name:ind_x_preferred":[
        "Batei Ungarin"
    ],
    "name:pol_x_preferred":[
        "Batte Ungarin"
    ],
    "name:yid_x_preferred":[
        "\u05d0\u05d5\u05e0\u05d2\u05d0\u05e8\u05d9\u05e9\u05e2 \u05d4\u05d9\u05d9\u05d6\u05e2\u05e8"
    ],
    "name:zho_x_preferred":[
        "\u5308\u7259\u5229\u4e4b\u5bb6"
    ],
    "qs_pg:aaroncc":"IL",
    "qs_pg:gn_country":"IL",
    "qs_pg:name":"Batei Ungarin",
    "qs_pg:name_adm0":"Israel",
    "qs_pg:name_adm1":"Jerusalem",
    "qs_pg:photos":154,
    "qs_pg:photos_1k":31,
    "qs_pg:photos_9k":1,
    "qs_pg:photos_9r":4,
    "qs_pg:photos_all":154,
    "qs_pg:photos_sr":4,
    "qs_pg:pop_sr":0,
    "qs_pg:qs_pg_placetype":"neighbourhood",
    "qs_pg:qs_pg_placetype_gp":"Suburb",
    "qs_pg:woe_adm0":23424852,
    "woe:adm0_id":23424852,
    "woe:name_adm0":"Israel",
    "woe:name_adm1":"Jerusalem",
    "woe:placetype":"Suburb",
    "wof:name":"Batei Ungarin",
    "wof:placetype":"neighbourhood"
},
  "geometry": {"coordinates":[35.226974,31.788667],"type":"Point"}
}