{
  "type": "Feature",
  "properties": {
    "iso:country":"IL",
    "name:ara_x_preferred":[
        "\u0639\u0645\u0642\u0627"
    ],
    "name:ces_x_preferred":[
        "Amka"
    ],
    "name:cze_x_preferred":[
        "Amka"
    ],
    "name:dan_x_preferred":[
        "Amqa"
    ],
    "name:eng_x_preferred":[
        "Amka"
    ],
    "name:heb_x_preferred":[
        "\u05e2\u05de\u05e7\u05d4"
    ],
    "name:heb_x_variant":[
        "\u2018Amqa"
    ],
    "name:ind_x_preferred":[
        "Amqa"
    ],
    "name:nno_x_preferred":[
        "Amka"
    ],
    "name:pol_x_preferred":[
        "Amka"
    ],
    "name:swe_x_preferred":[
        "Amqa"
    ],
    "name:unk_x_variant":[
        "\u2018Amqah"
    ],
    "qs:gn_country":"IL",
    "qs:gn_fcode":"PPL",
    "qs:gn_pop":0,
    "qs:name":"Amqa",
    "qs:name_adm0":"Israel",
    "qs:name_adm1":"Northern",
    "qs:photos":0,
    "qs:photos_1k":0,
    "qs:photos_9k":0,
    "qs:photos_9r":0,
    "qs:photos_all":0,
    "qs:photos_sr":0,
    "qs:placetype":"Town",
    "qs:pop_sr":"0",
    "qs:woe_adm0":23424852,
    "wd:wordcount":1848,
    "wof:name":"Amqa",
    "wof:placetype":"locality"
},
  "geometry": {"coordinates":[35.16332,32.97987],"type":"Point"}
}