{
  "type": "Feature",
  "properties": {
    "iso:country":"IL",
    "name:ces_x_preferred":[
        "Nir Banim"
    ],
    "name:eng_x_preferred":[
        "Nir Banim"
    ],
    "name:heb_x_preferred":[
        "\u05e0\u05d9\u05e8 \u05d1\u05e0\u05d9\u05dd"
    ],
    "name:heb_x_variant":[
        "\u05d1\u05e0\u05d9 \u05d4\u05de\u05d5\u05e9\u05d1\u05d9\u05dd",
        "\u05e6\u05d5\u05e8 \u05de\u05e2\u05d5\u05df"
    ],
    "name:nld_x_preferred":[
        "Nir Banim"
    ],
    "name:nno_x_preferred":[
        "Nir Banim"
    ],
    "name:pol_x_preferred":[
        "Nir Banim"
    ],
    "name:unk_x_variant":[
        "Bene HaMoshavim"
    ],
    "qs:gn_country":"IL",
    "qs:gn_fcode":"PPL",
    "qs:gn_pop":0,
    "qs:name":"Nir Banim",
    "qs:name_adm0":"Israel",
    "qs:name_adm1":"Southern",
    "qs:photos":0,
    "qs:photos_1k":0,
    "qs:photos_9k":1,
    "qs:photos_9r":1,
    "qs:photos_all":12,
    "qs:photos_sr":0,
    "qs:placetype":"Town",
    "qs:pop_sr":"0",
    "qs:woe_adm0":23424852,
    "wd:wordcount":140,
    "wof:name":"Nir Banim",
    "wof:placetype":"locality"
},
  "geometry": {"coordinates":[34.75482,31.67178],"type":"Point"}
}