{
  "type": "Feature",
  "properties": {
    "iso:country":"IL",
    "qs:gn_pop":0,
    "qs:name":"Terabin",
    "qs:name_adm0":"Israel",
    "qs:name_adm1":"Southern",
    "qs:photos":99,
    "qs:photos_1k":20,
    "qs:photos_9k":1,
    "qs:photos_9r":3,
    "qs:photos_all":99,
    "qs:photos_sr":3,
    "qs:placetype":"Town",
    "qs:pop_sr":"0",
    "qs:woe_adm0":23424852,
    "wof:name":"Terabin",
    "wof:placetype":"locality"
},
  "geometry": {"coordinates":[34.825286,31.139072],"type":"Point"}
}