{
  "type": "Feature",
  "properties": {
    "iso:country":"IL",
    "name:ceb_x_preferred":[
        "\u1e94ur Hadassa"
    ],
    "name:ces_x_preferred":[
        "Cur Hadasa"
    ],
    "name:eng_x_preferred":[
        "Tzur Hadassah"
    ],
    "name:heb_x_preferred":[
        "\u05e6\u05d5\u05e8 \u05d4\u05d3\u05e1\u05d4"
    ],
    "name:heb_x_variant":[
        "\u1e94ur Hadassa"
    ],
    "name:nno_x_preferred":[
        "Tzur Hadassah"
    ],
    "name:pol_x_preferred":[
        "Cur Hadassa"
    ],
    "name:pol_x_variant":[
        "Cur Hadasa"
    ],
    "name:swe_x_preferred":[
        "\u1e94ur Hadassa"
    ],
    "name:unk_x_variant":[
        "Tsur Hadassa"
    ],
    "qs:gn_country":"IL",
    "qs:gn_fcode":"PPL",
    "qs:gn_pop":4700,
    "qs:name":"Zur Hadassa",
    "qs:name_adm0":"Israel",
    "qs:name_adm1":"Jerusalem",
    "qs:photos":0,
    "qs:photos_1k":0,
    "qs:photos_9k":1,
    "qs:photos_9r":4,
    "qs:photos_all":185,
    "qs:photos_sr":0,
    "qs:placetype":"Town",
    "qs:pop_sr":"4",
    "qs:woe_adm0":23424852,
    "wd:wordcount":234,
    "wof:name":"Zur Hadassa",
    "wof:placetype":"locality",
    "wof:population":4700
},
  "geometry": {"coordinates":[35.09549,31.71794],"type":"Point"}
}