{
  "type": "Feature",
  "properties": {
    "iso:country":"IL",
    "name:ces_x_preferred":[
        "Sde Eli'ezer"
    ],
    "name:eng_x_preferred":[
        "Sde Eliezer"
    ],
    "name:heb_x_preferred":[
        "\u05e9\u05d3\u05d4 \u05d0\u05dc\u05d9\u05e2\u05d6\u05e8"
    ],
    "name:nno_x_preferred":[
        "Sde Eliezer"
    ],
    "name:pol_x_preferred":[
        "Sede Eli\u2019ezer"
    ],
    "name:pol_x_variant":[
        "Sde Eliezer"
    ],
    "qs:gn_country":"IL",
    "qs:gn_fcode":"PPL",
    "qs:gn_pop":0,
    "qs:name":"Sede Eliezer",
    "qs:name_adm0":"Israel",
    "qs:name_adm1":"Northern",
    "qs:photos":7,
    "qs:photos_1k":1,
    "qs:photos_9k":1,
    "qs:photos_9r":1,
    "qs:photos_all":7,
    "qs:photos_sr":1,
    "qs:placetype":"Town",
    "qs:pop_sr":"0",
    "qs:woe_adm0":23424852,
    "wd:wordcount":112,
    "wof:name":"Sede Eliezer",
    "wof:placetype":"locality"
},
  "geometry": {"coordinates":[35.56389,33.04528],"type":"Point"}
}