{
  "type": "Feature",
  "properties": {
    "gn:admin1_code":"06",
    "gn:asciiname":"Qiryat `Anavim",
    "gn:country_code":"IL",
    "gn:dem":669,
    "gn:feature_class":"P",
    "gn:feature_code":"PPL",
    "gn:name":"Qiryat \u2018Anavim",
    "gn:population":0,
    "gn:timezone":"Asia/Jerusalem",
    "iso:country":"IL",
    "name:ceb_x_preferred":[
        "Qiryat \u2018Anavim"
    ],
    "name:ces_x_preferred":[
        "Kirjat Anavim"
    ],
    "name:fra_x_preferred":[
        "Kiryat-Anavim"
    ],
    "name:heb_x_preferred":[
        "\u05e7\u05e8\u05d9\u05ea \u05e2\u05e0\u05d1\u05d9\u05dd"
    ],
    "name:heb_x_variant":[
        "\u05e7\u05e8\u05d9\u05d9\u05ea \u05e2\u05e0\u05d1\u05d9\u05dd"
    ],
    "name:nno_x_preferred":[
        "Kiryat Anavim"
    ],
    "name:pol_x_preferred":[
        "Kirjat Anawim"
    ],
    "name:swe_x_preferred":[
        "Qiryat \u2018Anavim"
    ],
    "name:und_x_variant":[
        "Dilb",
        "Qiryath \u2018An\u0101v\u012bm",
        "Kiria"
    ],
    "wof:name":"Qiryat `Anavim",
    "wof:placetype":"locality"
},
  "geometry": {"coordinates":[35.12035,31.81082],"type":"Point"}
}