{
  "type": "Feature",
  "properties": {
    "gn:admin1_code":"03",
    "gn:asciiname":"Segev",
    "gn:country_code":"IL",
    "gn:dem":364,
    "gn:feature_class":"P",
    "gn:feature_code":"PPL",
    "gn:name":"Segev",
    "gn:population":0,
    "gn:timezone":"Asia/Jerusalem",
    "iso:country":"IL",
    "name:ces_x_preferred":[
        "Acmon"
    ],
    "name:heb_x_preferred":[
        "\u05e9\u05d2\u05d1"
    ],
    "name:heb_x_variant":[
        "\u05e2\u05e6\u05de\u05d5\u05df-\u05e9\u05d2\u05d1"
    ],
    "name:nno_x_preferred":[
        "Atzmon"
    ],
    "name:pol_x_preferred":[
        "Segew"
    ],
    "wof:name":"Segev",
    "wof:placetype":"locality"
},
  "geometry": {"coordinates":[35.25189,32.86602],"type":"Point"}
}