{
  "type": "Feature",
  "properties": {
    "gn:admin1_code":"03",
    "gn:asciiname":"Manshiyet Zabda",
    "gn:country_code":"IL",
    "gn:dem":116,
    "gn:feature_class":"P",
    "gn:feature_code":"PPL",
    "gn:name":"Mansh\u012byet Zabda",
    "gn:population":0,
    "gn:timezone":"Asia/Jerusalem",
    "iso:country":"IL",
    "name:heb_x_preferred":[
        "Mansh\u012byet Zabda"
    ],
    "name:heb_x_variant":[
        "\u05de\u05e0\u05e9\u05d9\u05ea \u05d6\u05d1\u05d3\u05d4"
    ],
    "name:und_x_variant":[
        "Manshiyya Zibda"
    ],
    "wof:name":"Manshiyet Zabda",
    "wof:placetype":"locality"
},
  "geometry": {"coordinates":[35.19354000000001,32.70638],"type":"Point"}
}