{
  "type": "Feature",
  "properties": {
    "gn:admin1_code":"01",
    "gn:asciiname":"Yoshivya",
    "gn:country_code":"IL",
    "gn:dem":140,
    "gn:feature_class":"P",
    "gn:feature_code":"PPL",
    "gn:name":"Yoshivya",
    "gn:population":0,
    "gn:timezone":"Asia/Jerusalem",
    "iso:country":"IL",
    "name:ces_x_preferred":[
        "Jo\u0161ivja"
    ],
    "name:heb_x_preferred":[
        "\u05d9\u05d5\u05e9\u05d9\u05d1\u05d9\u05d4"
    ],
    "name:nno_x_preferred":[
        "Yoshivia"
    ],
    "name:pol_x_preferred":[
        "Josziwja"
    ],
    "name:und_x_variant":[
        "Muharakah Alef",
        "Yoshivyah",
        "Yoshivya"
    ],
    "wof:name":"Yoshivya",
    "wof:placetype":"locality"
},
  "geometry": {"coordinates":[34.60949,31.44397],"type":"Point"}
}