{
  "type": "Feature",
  "properties": {
    "iso:country":"IL",
    "name:ces_x_preferred":[
        "Dor"
    ],
    "name:eng_x_preferred":[
        "Dor"
    ],
    "name:fra_x_preferred":[
        "Dor"
    ],
    "name:heb_x_preferred":[
        "\u05d3\u05d5\u05e8"
    ],
    "name:nno_x_preferred":[
        "Dor i Hof HaCarmel"
    ],
    "name:pol_x_preferred":[
        "Dor"
    ],
    "name:unk_x_variant":[
        "Tant\u016bra"
    ],
    "qs:gn_country":"IL",
    "qs:gn_fcode":"PPL",
    "qs:gn_pop":0,
    "qs:name":"Dor",
    "qs:name_adm0":"Israel",
    "qs:name_adm1":"Haifa",
    "qs:photos":397,
    "qs:photos_1k":80,
    "qs:photos_9k":2,
    "qs:photos_9r":5,
    "qs:photos_all":397,
    "qs:photos_sr":6,
    "qs:placetype":"Town",
    "qs:pop_sr":"0",
    "qs:woe_adm0":23424852,
    "wof:name":"Dor",
    "wof:placetype":"locality"
},
  "geometry": {"coordinates":[34.9233,32.60751],"type":"Point"}
}