{
  "type": "Feature",
  "properties": {
    "iso:country":"IL",
    "name:ara_x_preferred":[
        "\u0628\u0627\u0631 \u062c\u064a\u0648\u0631\u0627"
    ],
    "name:arz_x_preferred":[
        "\u0628\u0627\u0631 \u062c\u064a\u0648\u0631\u0627"
    ],
    "name:ces_x_preferred":[
        "Bar Giora"
    ],
    "name:eng_x_preferred":[
        "Bar Giora"
    ],
    "name:heb_x_preferred":[
        "\u05d1\u05e8 \u05d2\u05d9\u05d5\u05e8\u05d0"
    ],
    "name:heb_x_variant":[
        "\u05d1\u05e8 \u05d2\u05d9\u05d5\u05e8\u05d4"
    ],
    "name:nno_x_preferred":[
        "Bar Giora"
    ],
    "name:pol_x_preferred":[
        "Bar Gijjora"
    ],
    "name:pol_x_variant":[
        "Bar Gijora"
    ],
    "name:rus_x_preferred":[
        "\u0411\u0430\u0440 \u0413\u0438\u043e\u0440\u0430"
    ],
    "name:urd_x_preferred":[
        "\u0628\u0631 \u06af\u06cc\u0648\u0631\u0627\u0621"
    ],
    "qs:gn_country":"IL",
    "qs:gn_fcode":"PPL",
    "qs:gn_pop":0,
    "qs:name":"Bar Giyyora",
    "qs:name_adm0":"Israel",
    "qs:name_adm1":"Jerusalem",
    "qs:photos":22,
    "qs:photos_1k":4,
    "qs:photos_9k":1,
    "qs:photos_9r":1,
    "qs:photos_all":22,
    "qs:photos_sr":1,
    "qs:placetype":"Town",
    "qs:pop_sr":"0",
    "qs:woe_adm0":23424852,
    "wd:wordcount":151,
    "wof:name":"Bar Giyyora",
    "wof:placetype":"locality"
},
  "geometry": {"coordinates":[35.07296,31.72973],"type":"Point"}
}