{
  "type": "Feature",
  "properties": {
    "gn:admin1_code":"03",
    "gn:asciiname":"Zafon Ka`abiyya",
    "gn:country_code":"IL",
    "gn:dem":184,
    "gn:feature_class":"P",
    "gn:feature_code":"PPL",
    "gn:name":"\u1e94afon Ka\u2018abiyya",
    "gn:population":0,
    "gn:timezone":"Asia/Jerusalem",
    "iso:country":"IL",
    "name:heb_x_preferred":[
        "\u1e94afon Ka\u2018abiyya"
    ],
    "name:heb_x_variant":[
        "\u05e6\u05e4\u05d5\u05df \u05db\u05e2\u05d1\u05d9\u05d9\u05d4",
        "Tsafon Ka\u2018abiyya",
        "Ka\u2018abiyya",
        "\u05db\u05e2\u05d1\u05d9\u05d4"
    ],
    "wof:name":"Zafon Ka`abiyya",
    "wof:placetype":"locality"
},
  "geometry": {"coordinates":[35.18279,32.75844],"type":"Point"}
}