{
  "type": "Feature",
  "properties": {
    "gn:country":"IL",
    "iso:country":"IL",
    "name:ces_x_preferred":[
        "Snir"
    ],
    "name:eng_x_preferred":[
        "Snir"
    ],
    "name:heb_x_preferred":[
        "\u05e9\u05e0\u05d9\u05e8"
    ],
    "name:nld_x_preferred":[
        "Snir"
    ],
    "name:nno_x_preferred":[
        "Snir"
    ],
    "name:pol_x_preferred":[
        "Snir"
    ],
    "qs_pg:aaroncc":"IL",
    "qs_pg:gn_country":"IL",
    "qs_pg:name":"Snir",
    "qs_pg:name_adm0":"Israel",
    "qs_pg:name_adm1":"Northern",
    "qs_pg:photos":781,
    "qs_pg:photos_1k":158,
    "qs_pg:photos_9k":3,
    "qs_pg:photos_9r":6,
    "qs_pg:photos_all":781,
    "qs_pg:photos_sr":9,
    "qs_pg:pop_sr":0,
    "qs_pg:qs_pg_placetype":"locality",
    "qs_pg:qs_pg_placetype_gp":"Town",
    "qs_pg:woe_adm0":23424852,
    "woe:adm0_id":23424852,
    "woe:name_adm0":"Israel",
    "woe:name_adm1":"Northern",
    "woe:placetype":"Town",
    "wof:name":"Snir",
    "wof:placetype":"locality"
},
  "geometry": {"coordinates":[35.693833,33.243167],"type":"Point"}
}