{
  "type": "Feature",
  "properties": {
    "iso:country":"IL",
    "name:cze_x_preferred":[
        "Cor'a"
    ],
    "name:eng_x_preferred":[
        "Tzora"
    ],
    "name:heb_x_preferred":[
        "\u05e6\u05e8\u05e2\u05d4"
    ],
    "name:jpn_x_preferred":[
        "\u30c4\u30a1\u30eb\u30a2\u30fc"
    ],
    "name:nno_x_preferred":[
        "Tzora"
    ],
    "name:pol_x_preferred":[
        "Cor'a"
    ],
    "name:por_x_preferred":[
        "Zor\u00e1"
    ],
    "name:unk_x_variant":[
        "Sar\u2018a"
    ],
    "qs:gn_country":"IL",
    "qs:gn_fcode":"PPL",
    "qs:gn_pop":0,
    "qs:name":"Zora",
    "qs:name_adm0":"Israel",
    "qs:name_adm1":"Jerusalem",
    "qs:photos":226,
    "qs:photos_1k":46,
    "qs:photos_9k":1,
    "qs:photos_9r":4,
    "qs:photos_all":226,
    "qs:photos_sr":4,
    "qs:placetype":"Town",
    "qs:pop_sr":"0",
    "qs:woe_adm0":23424852,
    "wd:wordcount":113,
    "wof:name":"Zora",
    "wof:placetype":"locality"
},
  "geometry": {"coordinates":[34.96906,31.76242],"type":"Point"}
}