{
  "type": "Feature",
  "properties": {
    "iso:country":"IL",
    "name:ara_x_preferred":[
        "\u0623\u0648\u0631 \u0639\u0642\u064a\u0641\u0627"
    ],
    "name:arz_x_preferred":[
        "\u0627\u0648\u0631 \u0639\u0642\u064a\u0641\u0627"
    ],
    "name:ast_x_preferred":[
        "Or Akiva"
    ],
    "name:bel_x_preferred":[
        "\u041e\u0440-\u0410\u043a\u0456\u0432\u0430"
    ],
    "name:cat_x_preferred":[
        "Or Aqiva"
    ],
    "name:ceb_x_preferred":[
        "Or \u2018Aqiva"
    ],
    "name:ces_x_preferred":[
        "Or Akiva"
    ],
    "name:dan_x_preferred":[
        "Or Akiva"
    ],
    "name:deu_x_preferred":[
        "Or Akiwa"
    ],
    "name:eng_x_preferred":[
        "Or Akiva"
    ],
    "name:fas_x_preferred":[
        "\u0627\u0648\u0631 \u0639\u0642\u06cc\u0641\u0627"
    ],
    "name:fra_x_preferred":[
        "Or Aqiva"
    ],
    "name:heb_x_preferred":[
        "\u05d0\u05d5\u05e8 \u05e2\u05e7\u05d9\u05d1\u05d0"
    ],
    "name:heb_x_variant":[
        "Or \u2018Aqiva"
    ],
    "name:hye_x_preferred":[
        "\u0555\u057c \u0531\u056f\u056b\u057e\u0561"
    ],
    "name:ind_x_preferred":[
        "Or Akiva"
    ],
    "name:ita_x_preferred":[
        "Or Akiva"
    ],
    "name:nld_x_preferred":[
        "Or Akiva"
    ],
    "name:nno_x_preferred":[
        "Or Akiva"
    ],
    "name:nob_x_preferred":[
        "Or Akiva"
    ],
    "name:nor_x_preferred":[
        "Or Akiva"
    ],
    "name:pol_x_preferred":[
        "Or Akiwa"
    ],
    "name:pol_x_variant":[
        "Or Aqiva"
    ],
    "name:por_x_preferred":[
        "Or Aqiva"
    ],
    "name:ron_x_preferred":[
        "Or Akiva"
    ],
    "name:rus_x_preferred":[
        "\u041e\u0440-\u0410\u043a\u0438\u0432\u0430"
    ],
    "name:sco_x_preferred":[
        "Or Akiva"
    ],
    "name:spa_x_preferred":[
        "Or Akiva"
    ],
    "name:swa_x_preferred":[
        "Or Akiva"
    ],
    "name:swe_x_preferred":[
        "Or \u2018Aqiva"
    ],
    "name:tgl_x_preferred":[
        "Or Akiva"
    ],
    "name:und_x_variant":[
        "Or \u2018Aq\u012bv\u0101h"
    ],
    "name:urd_x_preferred":[
        "\u0627\u0648\u0631 \u0639\u06a9\u06cc\u0648\u0627"
    ],
    "name:vie_x_preferred":[
        "Or Akiva"
    ],
    "name:yid_x_preferred":[
        "\u05d0\u05d5\u05e8 \u05e2\u05e7\u05d9\u05d1\u05d0"
    ],
    "name:zho_x_preferred":[
        "\u5967\u723e\u963f\u9f4a\u74e6"
    ],
    "qs:gn_country":"IL",
    "qs:gn_fcode":"PPL",
    "qs:gn_pop":0,
    "qs:name":"Or Akiva",
    "qs:name_adm0":"Israel",
    "qs:name_adm1":"Haifa",
    "qs:photos":1973,
    "qs:photos_1k":400,
    "qs:photos_9k":9,
    "qs:photos_9r":9,
    "qs:photos_all":1973,
    "qs:photos_sr":15,
    "qs:placetype":"Town",
    "qs:pop_sr":"0",
    "qs:woe_adm0":23424852,
    "wd:wordcount":476,
    "wof:name":"Or Akiva",
    "wof:placetype":"locality"
},
  "geometry": {"coordinates":[34.92087,32.5064],"type":"Point"}
}