{
  "type": "Feature",
  "properties": {
    "gn:admin1_code":"02",
    "gn:asciiname":"HaMa`pil",
    "gn:country_code":"IL",
    "gn:dem":41,
    "gn:feature_class":"P",
    "gn:feature_code":"PPL",
    "gn:name":"HaMa\u2018pil",
    "gn:population":0,
    "gn:timezone":"Asia/Jerusalem",
    "iso:country":"IL",
    "name:ces_x_preferred":[
        "Ha-Ma'apil"
    ],
    "name:heb_x_preferred":[
        "HaMa\u2018pil"
    ],
    "name:heb_x_variant":[
        "\u05d4\u05de\u05e2\u05e4\u05d9\u05dc",
        "HaMa\u2019pil"
    ],
    "name:nno_x_preferred":[
        "HaMa'apil"
    ],
    "name:pol_x_preferred":[
        "Ha-Mapil"
    ],
    "name:und_x_variant":[
        "Hama\u2018apil"
    ],
    "wof:name":"HaMa`pil",
    "wof:placetype":"locality"
},
  "geometry": {"coordinates":[34.98337,32.37802],"type":"Point"}
}