{
  "type": "Feature",
  "properties": {
    "gn:admin1_code":"02",
    "gn:asciiname":"Giv`at Koah",
    "gn:country_code":"IL",
    "gn:dem":71,
    "gn:feature_class":"P",
    "gn:feature_code":"PPL",
    "gn:name":"Giv\u2018at Koa\u1e96",
    "gn:population":0,
    "gn:timezone":"Asia/Jerusalem",
    "iso:country":"IL",
    "name:ces_x_preferred":[
        "Giv'at Koach"
    ],
    "name:heb_x_preferred":[
        "Giv\u2018at Koa\u1e96"
    ],
    "name:heb_x_variant":[
        "\u05d2\u05d1\u05e2\u05ea \u05db\u05d7",
        "\u05d2\u05d1\u05e2\u05ea \u05db\"\u05d7"
    ],
    "name:nno_x_preferred":[
        "Giv'at Ko'ah"
    ],
    "name:pol_x_preferred":[
        "Giwat Koach"
    ],
    "name:rus_x_preferred":[
        "\u0413\u0438\u0432\u0430\u0442-\u041a\u043e\u0430\u0445"
    ],
    "wof:name":"Giv`at Koah",
    "wof:placetype":"locality"
},
  "geometry": {"coordinates":[34.93657,32.03117],"type":"Point"}
}