{
  "type": "Feature",
  "properties": {
    "gn:admin1_code":"06",
    "gn:asciiname":"Kfar Adumim",
    "gn:country_code":"IL",
    "gn:dem":344,
    "gn:feature_class":"P",
    "gn:feature_code":"PPL",
    "gn:name":"Kfar Adumim",
    "gn:population":0,
    "gn:timezone":"Asia/Jerusalem",
    "iso:country":"IL",
    "wof:name":"Kfar Adumim",
    "wof:placetype":"locality"
},
  "geometry": {"coordinates":[35.33684,31.8262],"type":"Point"}
}