{
  "type": "Feature",
  "properties": {
    "gn:admin1_code":"06",
    "gn:asciiname":"Kfar Adumim",
    "gn:country_code":"IL",
    "gn:dem":344,
    "gn:feature_class":"P",
    "gn:feature_code":"PPL",
    "gn:name":"Kfar Adumim",
    "gn:population":0,
    "gn:timezone":"Asia/Jerusalem",
    "iso:country":"IL",
    "name:ara_x_preferred":[
        "\u0643\u0641\u0627\u0631 \u0623\u062f\u0648\u0645\u064a\u0645"
    ],
    "name:ces_x_preferred":[
        "Kfar Adumim"
    ],
    "name:deu_x_preferred":[
        "Kfar Adumim"
    ],
    "name:heb_x_preferred":[
        "\u05db\u05e4\u05e8 \u05d0\u05d3\u05d5\u05de\u05d9\u05dd"
    ],
    "name:nno_x_preferred":[
        "Kfar Adumim"
    ],
    "name:pol_x_preferred":[
        "Kefar Adummim"
    ],
    "name:rus_x_preferred":[
        "\u041a\u0444\u0430\u0440-\u0410\u0434\u0443\u043c\u0438\u043c"
    ],
    "wof:name":"Kfar Adumim",
    "wof:placetype":"locality"
},
  "geometry": {"coordinates":[35.33684,31.8262],"type":"Point"}
}