{
  "type": "Feature",
  "properties": {
    "iso:country":"IL",
    "name:ara_x_preferred":[
        "\u062f\u0627\u0646"
    ],
    "name:ces_x_preferred":[
        "Dan"
    ],
    "name:deu_x_preferred":[
        "Dan"
    ],
    "name:eng_x_preferred":[
        "Dan"
    ],
    "name:fra_x_preferred":[
        "Dan"
    ],
    "name:heb_x_preferred":[
        "\u05d3\u05df"
    ],
    "name:nld_x_preferred":[
        "Dan"
    ],
    "name:nno_x_preferred":[
        "Dan i Israel"
    ],
    "name:nob_x_preferred":[
        "Dan i Israel"
    ],
    "name:nor_x_preferred":[
        "Dan i Israel"
    ],
    "name:pol_x_preferred":[
        "Dan"
    ],
    "name:rus_x_preferred":[
        "\u0414\u044d\u043d"
    ],
    "name:unk_x_variant":[
        "Tell el Qady"
    ],
    "qs:gn_country":"IL",
    "qs:gn_fcode":"PPL",
    "qs:gn_pop":0,
    "qs:name":"Dan",
    "qs:name_adm0":"Israel",
    "qs:name_adm1":"Northern",
    "qs:photos":225,
    "qs:photos_1k":46,
    "qs:photos_9k":1,
    "qs:photos_9r":4,
    "qs:photos_all":225,
    "qs:photos_sr":4,
    "qs:placetype":"Town",
    "qs:pop_sr":"0",
    "qs:woe_adm0":23424852,
    "wd:wordcount":314,
    "wof:name":"Dan",
    "wof:placetype":"locality"
},
  "geometry": {"coordinates":[35.65335,33.23979],"type":"Point"}
}