{
  "type": "Feature",
  "properties": {
    "iso:country":"IL",
    "name:arg_x_preferred":[
        "Gat\u00f3n de Campos"
    ],
    "name:cat_x_preferred":[
        "Gat\u00f3n de Campos"
    ],
    "name:ceb_x_preferred":[
        "Gat\u00f3n de Campos"
    ],
    "name:ces_x_preferred":[
        "Ga'aton"
    ],
    "name:eng_x_preferred":[
        "Ga'aton"
    ],
    "name:eus_x_preferred":[
        "Gat\u00f3n de Campos"
    ],
    "name:fas_x_preferred":[
        "\u06af\u0627\u062a\u0646 \u062f \u06a9\u0627\u0645\u067e\u0633"
    ],
    "name:fra_x_preferred":[
        "Gat\u00f3n de Campos"
    ],
    "name:heb_x_preferred":[
        "Ga\u2018ton"
    ],
    "name:heb_x_variant":[
        "\u05d2\u05e2\u05ea\u05d5\u05df",
        "Ga\u2019ton"
    ],
    "name:hun_x_preferred":[
        "Gat\u00f3n de Campos"
    ],
    "name:hye_x_preferred":[
        "\u0533\u0561\u057f\u0578\u0576 \u0564\u0565 \u053f\u0561\u0574\u057a\u0578\u057d"
    ],
    "name:ina_x_preferred":[
        "Gat\u00f3n de Campos"
    ],
    "name:nno_x_preferred":[
        "Ga'aton"
    ],
    "name:pol_x_preferred":[
        "Ga'aton"
    ],
    "name:spa_x_preferred":[
        "Gat\u00f3n de Campos"
    ],
    "name:und_x_variant":[
        "Ga\u2018aton"
    ],
    "qs:gn_country":"IL",
    "qs:gn_fcode":"PPL",
    "qs:gn_pop":0,
    "qs:name":"Gaton",
    "qs:name_adm0":"Israel",
    "qs:name_adm1":"Northern",
    "qs:photos":1,
    "qs:photos_1k":1,
    "qs:photos_9k":1,
    "qs:photos_9r":1,
    "qs:photos_all":1,
    "qs:photos_sr":1,
    "qs:placetype":"Town",
    "qs:pop_sr":"0",
    "qs:woe_adm0":23424852,
    "wof:name":"Gaton",
    "wof:placetype":"locality"
},
  "geometry": {"coordinates":[35.21477,33.00628],"type":"Point"}
}