{
  "type": "Feature",
  "properties": {
    "iso:country":"IL",
    "name:ces_x_preferred":[
        "Chogla"
    ],
    "name:cze_x_preferred":[
        "Chogla"
    ],
    "name:eng_x_preferred":[
        "Hogla"
    ],
    "name:heb_x_preferred":[
        "\u05d7\u05d2\u05dc\u05d4"
    ],
    "name:heb_x_variant":[
        "H\u0331ogla"
    ],
    "name:nno_x_preferred":[
        "Hogla i Israel"
    ],
    "name:pol_x_preferred":[
        "Hogla"
    ],
    "name:unk_x_variant":[
        "Hoglah"
    ],
    "qs:gn_country":"IL",
    "qs:gn_fcode":"PPL",
    "qs:gn_pop":0,
    "qs:name":"Hogla",
    "qs:name_adm0":"Israel",
    "qs:name_adm1":"Central",
    "qs:photos":2145,
    "qs:photos_1k":435,
    "qs:photos_9k":10,
    "qs:photos_9r":9,
    "qs:photos_all":2145,
    "qs:photos_sr":16,
    "qs:placetype":"Town",
    "qs:pop_sr":"0",
    "qs:woe_adm0":23424852,
    "wd:wordcount":94,
    "wof:name":"Hogla",
    "wof:placetype":"locality"
},
  "geometry": {"coordinates":[34.92759,32.38767],"type":"Point"}
}