{
  "type": "Feature",
  "properties": {
    "gn:admin1_code":"02",
    "gn:asciiname":"Avihayil",
    "gn:country_code":"IL",
    "gn:dem":47,
    "gn:feature_class":"P",
    "gn:feature_code":"PPL",
    "gn:name":"Avi\u1e96ayil",
    "gn:population":0,
    "gn:timezone":"Asia/Jerusalem",
    "iso:country":"IL",
    "name:heb_x_preferred":[
        "Avi\u1e96ayil"
    ],
    "name:heb_x_variant":[
        "\u05d0\u05d1\u05d9\u05d7\u05d9\u05dc"
    ],
    "name:und_x_variant":[
        "\u2018Ein Ha\u2018oved",
        "Avi\u1e96ayil"
    ],
    "wof:name":"Avihayil",
    "wof:placetype":"locality"
},
  "geometry": {"coordinates":[34.87119000000001,32.3504],"type":"Point"}
}