{
  "type": "Feature",
  "properties": {
    "iso:country":"IL",
    "name:ces_x_preferred":[
        "Luzit"
    ],
    "name:eng_x_preferred":[
        "Luzit"
    ],
    "name:heb_x_preferred":[
        "\u05dc\u05d5\u05d6\u05d9\u05ea"
    ],
    "name:nno_x_preferred":[
        "Luzit"
    ],
    "name:pol_x_preferred":[
        "Luzit"
    ],
    "name:unk_x_variant":[
        "Deir Dubban"
    ],
    "qs:gn_country":"IL",
    "qs:gn_fcode":"PPL",
    "qs:gn_pop":0,
    "qs:name":"Luzit",
    "qs:name_adm0":"Israel",
    "qs:name_adm1":"Jerusalem",
    "qs:photos":34,
    "qs:photos_1k":7,
    "qs:photos_9k":1,
    "qs:photos_9r":2,
    "qs:photos_all":34,
    "qs:photos_sr":2,
    "qs:placetype":"Town",
    "qs:pop_sr":"0",
    "qs:woe_adm0":23424852,
    "wd:wordcount":91,
    "wof:name":"Luzit",
    "wof:placetype":"locality"
},
  "geometry": {"coordinates":[34.88649,31.68715],"type":"Point"}
}