{
  "type": "Feature",
  "properties": {
    "gn:country":"IL",
    "gn:fcode":"PPLX",
    "gn:population":0,
    "iso:country":"IL",
    "name:eng_x_colloquial":[
        "Havazzelet",
        "Havazelet"
    ],
    "name:eng_x_preferred":[
        "H\u0331ava\u1e95\u1e95elet"
    ],
    "name:eng_x_variant":[
        "Havatselet",
        "H\u0331ava\u1e95elet"
    ],
    "name:heb_x_preferred":[
        "H\u0331avatselet"
    ],
    "name:heb_x_variant":[
        "\u05d7\u05d1\u05e6\u05dc\u05ea"
    ],
    "qs:gn_adm0_cc":"IL",
    "qs:gn_fcode":"PPLX",
    "qs:gn_local":293725,
    "qs:gn_nam_loc":"Rehovot, Central, IL",
    "qs:gn_namadm1":"02",
    "qs:gn_name":"H\u0331ava\u1e95\u1e95elet",
    "qs:local_max":1403,
    "qs:local_sum":1403,
    "qs:localhoods":1,
    "qs:name":"H\u0331ava\u1e95\u1e95elet",
    "qs:name_adm0":"Israel",
    "qs:name_adm1":"Central",
    "qs:name_local":"Rehovot",
    "qs:photo_max":443,
    "qs:photo_sum":1403,
    "qs:placetype":"Suburb",
    "qs:quad_count":69,
    "qs:woe_adm0":23424852,
    "qs:woe_adm1":2345792,
    "qs:woe_adm2":0,
    "qs:woe_lau":0,
    "qs:woe_local":1968207,
    "qs:woe_ver":"7.10.0",
    "qs_pg:aaroncc":"IL",
    "qs_pg:gn_country":"IL",
    "qs_pg:gn_fcode":"PPLX",
    "qs_pg:gn_pop":0,
    "qs_pg:name":"H\u0331ava\u1e95\u1e95elet",
    "qs_pg:name_adm0":"Israel",
    "qs_pg:name_adm1":"Central",
    "qs_pg:photos":1294,
    "qs_pg:photos_1k":262,
    "qs_pg:photos_9k":6,
    "qs_pg:photos_9r":7,
    "qs_pg:photos_all":1294,
    "qs_pg:photos_sr":12,
    "qs_pg:pop_sr":0,
    "qs_pg:qs_pg_placetype":"neighbourhood",
    "qs_pg:qs_pg_placetype_gp":"Suburb",
    "qs_pg:woe_adm0":23424852,
    "wof:lang":[
        "eng"
    ],
    "wof:name":"H\u0331ava\u1e95\u1e95elet",
    "wof:placetype":"neighbourhood"
},
  "geometry": {"coordinates":[34.808921,31.889789],"type":"Point"}
}