{
  "type": "Feature",
  "properties": {
    "gn:admin1_code":"01",
    "gn:asciiname":"Yahel",
    "gn:country_code":"IL",
    "gn:dem":197,
    "gn:feature_class":"P",
    "gn:feature_code":"PPL",
    "gn:name":"Yahel",
    "gn:population":0,
    "gn:timezone":"Asia/Jerusalem",
    "iso:country":"IL",
    "name:ces_x_preferred":[
        "Jahel"
    ],
    "name:deu_x_preferred":[
        "Yahel"
    ],
    "name:heb_x_preferred":[
        "\u05d9\u05d4\u05dc"
    ],
    "name:nno_x_preferred":[
        "Yahel"
    ],
    "name:pol_x_preferred":[
        "Jahel"
    ],
    "wof:name":"Yahel",
    "wof:placetype":"locality"
},
  "geometry": {"coordinates":[35.12817,30.08364000000001],"type":"Point"}
}