{
  "type": "Feature",
  "properties": {
    "iso:country":"IL",
    "name:ces_x_preferred":[
        "Avtaljon"
    ],
    "name:eng_x_preferred":[
        "Avtalion"
    ],
    "name:fra_x_preferred":[
        "Abtalion"
    ],
    "name:heb_x_preferred":[
        "\u05d0\u05d1\u05d8\u05dc\u05d9\u05d5\u05df"
    ],
    "name:nno_x_preferred":[
        "Avtalion"
    ],
    "name:pol_x_preferred":[
        "Avtalion"
    ],
    "name:yid_x_preferred":[
        "\u05d0\u05d1\u05d8\u05dc\u05d9\u05d5\u05df"
    ],
    "qs:gn_country":"IL",
    "qs:gn_fcode":"PPL",
    "qs:gn_pop":0,
    "qs:name":"Avtalyon",
    "qs:name_adm0":"Israel",
    "qs:name_adm1":"Northern",
    "qs:photos":0,
    "qs:photos_1k":0,
    "qs:photos_9k":1,
    "qs:photos_9r":1,
    "qs:photos_all":1,
    "qs:photos_sr":0,
    "qs:placetype":"Town",
    "qs:pop_sr":"0",
    "qs:woe_adm0":23424852,
    "wd:wordcount":941,
    "wof:name":"Avtalyon",
    "wof:placetype":"locality"
},
  "geometry": {"coordinates":[35.34932,32.83619],"type":"Point"}
}