{
  "type": "Feature",
  "properties": {
    "gn:admin1_code":"01",
    "gn:asciiname":"Mabbu`im",
    "gn:country_code":"IL",
    "gn:dem":178,
    "gn:feature_class":"P",
    "gn:feature_code":"PPL",
    "gn:name":"Mabbu\u2018im",
    "gn:population":0,
    "gn:timezone":"Asia/Jerusalem",
    "iso:country":"IL",
    "name:ces_x_preferred":[
        "Mabu'im"
    ],
    "name:heb_x_preferred":[
        "\u05de\u05d1\u05d5\u05e2\u05d9\u05dd"
    ],
    "name:nno_x_preferred":[
        "Mabu'im"
    ],
    "name:pol_x_preferred":[
        "Mabbu\u2019im"
    ],
    "name:und_x_variant":[
        "Mabuim",
        "Mabbu\u2018im"
    ],
    "wof:name":"Mabbu`im",
    "wof:placetype":"locality"
},
  "geometry": {"coordinates":[34.65477,31.44965],"type":"Point"}
}