{
  "type": "Feature",
  "properties": {
    "iso:country":"IL",
    "name:ces_x_preferred":[
        "Bejt Josef"
    ],
    "name:deu_x_preferred":[
        "Bejit Josef"
    ],
    "name:eng_x_preferred":[
        "Beit Yosef"
    ],
    "name:heb_x_preferred":[
        "\u05d1\u05d9\u05ea \u05d9\u05d5\u05e1\u05e3"
    ],
    "name:nld_x_preferred":[
        "Beit Yosef"
    ],
    "name:nno_x_preferred":[
        "Beit Yosef i Israel"
    ],
    "name:pol_x_preferred":[
        "Beit Josef"
    ],
    "name:unk_x_variant":[
        "Beit Yosef"
    ],
    "qs:gn_country":"IL",
    "qs:gn_fcode":"PPL",
    "qs:gn_pop":0,
    "qs:name":"Bet Yosef",
    "qs:name_adm0":"Israel",
    "qs:name_adm1":"Northern",
    "qs:photos":0,
    "qs:photos_1k":0,
    "qs:photos_9k":1,
    "qs:photos_9r":1,
    "qs:photos_all":1,
    "qs:photos_sr":0,
    "qs:placetype":"Town",
    "qs:pop_sr":"0",
    "qs:woe_adm0":23424852,
    "wd:wordcount":24,
    "wof:name":"Bet Yosef",
    "wof:placetype":"locality"
},
  "geometry": {"coordinates":[35.5516,32.5585],"type":"Point"}
}