{
  "type": "Feature",
  "properties": {
    "gn:admin1_code":"02",
    "gn:asciiname":"Ramot HaShavim",
    "gn:country_code":"IL",
    "gn:dem":49,
    "gn:feature_class":"P",
    "gn:feature_code":"PPL",
    "gn:name":"Ramot HaShavim",
    "gn:population":0,
    "gn:timezone":"Asia/Jerusalem",
    "iso:country":"IL",
    "name:heb_x_preferred":[
        "\u05e8\u05de\u05d5\u05ea \u05d4\u05e9\u05d1\u05d9\u05dd"
    ],
    "wof:name":"Ramot HaShavim",
    "wof:placetype":"locality"
},
  "geometry": {"coordinates":[34.88761,32.16372],"type":"Point"}
}