{
  "type": "Feature",
  "properties": {
    "gn:admin1_code":"01",
    "gn:asciiname":"Kerem Shalom",
    "gn:country_code":"IL",
    "gn:dem":90,
    "gn:feature_class":"P",
    "gn:feature_code":"PPL",
    "gn:name":"Kerem Shalom",
    "gn:population":0,
    "gn:timezone":"Asia/Jerusalem",
    "iso:country":"IL",
    "name:heb_x_preferred":[
        "\u05db\u05e8\u05dd \u05e9\u05dc\u05d5\u05dd"
    ],
    "wof:name":"Kerem Shalom",
    "wof:placetype":"locality"
},
  "geometry": {"coordinates":[34.28459,31.22777],"type":"Point"}
}