{
  "type": "Feature",
  "properties": {
    "gn:admin1_code":"01",
    "gn:asciiname":"Kerem Shalom",
    "gn:country_code":"IL",
    "gn:dem":90,
    "gn:feature_class":"P",
    "gn:feature_code":"PPL",
    "gn:name":"Kerem Shalom",
    "gn:population":0,
    "gn:timezone":"Asia/Jerusalem",
    "iso:country":"IL",
    "name:ara_x_preferred":[
        "\u0643\u0631\u0645 \u0623\u0628\u0648 \u0633\u0627\u0644\u0645"
    ],
    "name:cat_x_preferred":[
        "K\u00e9rem Xalom"
    ],
    "name:ces_x_preferred":[
        "Kerem \u0160alom"
    ],
    "name:deu_x_preferred":[
        "Kerem Schalom"
    ],
    "name:fra_x_preferred":[
        "Kerem Shalom"
    ],
    "name:heb_x_preferred":[
        "\u05db\u05e8\u05dd \u05e9\u05dc\u05d5\u05dd"
    ],
    "name:ita_x_preferred":[
        "Kerem Shalom"
    ],
    "name:nno_x_preferred":[
        "Kerem Shalom"
    ],
    "name:pol_x_preferred":[
        "Kerem Szalom"
    ],
    "name:por_x_preferred":[
        "Kerem Shalom"
    ],
    "name:rus_x_preferred":[
        "\u041a\u0435\u0440\u0435\u043c-\u0428\u0430\u043b\u043e\u043c"
    ],
    "name:spa_x_preferred":[
        "Kerem Shalom"
    ],
    "name:zho_x_preferred":[
        "\u51ef\u91cc\u59c6\u6c99\u6d1b\u59c6"
    ],
    "wof:name":"Kerem Shalom",
    "wof:placetype":"locality"
},
  "geometry": {"coordinates":[34.28459,31.22777],"type":"Point"}
}