{
  "type": "Feature",
  "properties": {
    "gn:admin1_code":"02",
    "gn:asciiname":"Ge'ulle Teman",
    "gn:country_code":"IL",
    "gn:dem":12,
    "gn:feature_class":"P",
    "gn:feature_code":"PPL",
    "gn:name":"Ge\u2019ulle Teman",
    "gn:population":0,
    "gn:timezone":"Asia/Jerusalem",
    "iso:country":"IL",
    "name:heb_x_preferred":[
        "Ge\u2019ulle Teman"
    ],
    "name:heb_x_variant":[
        "\u05d2\u05d0\u05dc\u05d9 \u05ea\u05d9\u05de\u05df"
    ],
    "wof:name":"Ge'ulle Teman",
    "wof:placetype":"locality"
},
  "geometry": {"coordinates":[34.90215,32.39256],"type":"Point"}
}