{
  "type": "Feature",
  "properties": {
    "iso:country":"IL",
    "name:ces_x_preferred":[
        "Bejt El'azari"
    ],
    "name:cze_x_preferred":[
        "Bejt El'azari"
    ],
    "name:eng_x_preferred":[
        "Beit Elazari"
    ],
    "name:heb_x_preferred":[
        "\u05d1\u05d9\u05ea \u05d0\u05dc\u05e2\u05d6\u05e8\u05d9"
    ],
    "name:heb_x_variant":[
        "Bet El\u2018azari",
        "Bet El\u2019azari"
    ],
    "name:nno_x_preferred":[
        "Beit Elazari"
    ],
    "name:pol_x_preferred":[
        "Beit Elazari"
    ],
    "name:unk_x_variant":[
        "Beit El\u2018azari"
    ],
    "qs:gn_country":"IL",
    "qs:gn_fcode":"PPL",
    "qs:gn_pop":0,
    "qs:name":"Bet Elazari",
    "qs:name_adm0":"Israel",
    "qs:name_adm1":"Central",
    "qs:photos":0,
    "qs:photos_1k":0,
    "qs:photos_9k":0,
    "qs:photos_9r":0,
    "qs:photos_all":0,
    "qs:photos_sr":0,
    "qs:placetype":"Town",
    "qs:pop_sr":"0",
    "qs:woe_adm0":23424852,
    "wd:wordcount":178,
    "wof:name":"Bet Elazari",
    "wof:placetype":"locality"
},
  "geometry": {"coordinates":[34.80368,31.84429],"type":"Point"}
}