{
  "type": "Feature",
  "properties": {
    "gn:country":"IL",
    "gn:fcode":"PPL",
    "gn:pop":10108,
    "iso:country":"IL",
    "name:bul_x_preferred":[
        "\u0410\u0437\u043e\u0440"
    ],
    "name:cat_x_preferred":[
        "Azor"
    ],
    "name:ceb_x_preferred":[
        "Azor"
    ],
    "name:ces_x_preferred":[
        "Azor"
    ],
    "name:eng_x_preferred":[
        "Yazir"
    ],
    "name:eng_x_variant":[
        "Azur",
        "Yazor",
        "Y\u0101z\u016br",
        "Azor"
    ],
    "name:est_x_preferred":[
        "Azor"
    ],
    "name:fra_x_preferred":[
        "Azor"
    ],
    "name:heb_x_preferred":[
        "\u05d0\u05d6\u05d5\u05e8"
    ],
    "name:hun_x_preferred":[
        "Azor"
    ],
    "name:ita_x_preferred":[
        "Azor"
    ],
    "name:kat_x_preferred":[
        "\u10d0\u10d6\u10dd\u10e0\u10d8"
    ],
    "name:nld_x_preferred":[
        "Azor"
    ],
    "name:nno_x_preferred":[
        "Azor"
    ],
    "name:pol_x_preferred":[
        "Azor"
    ],
    "name:por_x_preferred":[
        "Azor"
    ],
    "name:rus_x_preferred":[
        "\u0410\u0437\u043e\u0440"
    ],
    "name:sco_x_preferred":[
        "Azor"
    ],
    "name:spa_x_preferred":[
        "Azor"
    ],
    "name:swe_x_preferred":[
        "Azor"
    ],
    "name:ukr_x_preferred":[
        "\u0410\u0437\u043e\u0440"
    ],
    "name:wol_x_preferred":[
        "Asor"
    ],
    "qs:name":"Azor",
    "qs:photos_9r":0,
    "qs:photos_sr":0,
    "qs:pop_sr":"6",
    "wd:wordcount":247,
    "wof:name":"Azor",
    "wof:placetype":"locality",
    "wof:population":10108
},
  "geometry": {"coordinates":[34.80623,32.02456],"type":"Point"}
}