{
  "type": "Feature",
  "properties": {
    "iso:country":"IL",
    "qs:gn_pop":0,
    "qs:name":"Shkhunat Pat",
    "qs:name_adm0":"Israel",
    "qs:name_adm1":"Jerusalem",
    "qs:photos":45,
    "qs:photos_1k":9,
    "qs:photos_9k":1,
    "qs:photos_9r":2,
    "qs:photos_all":45,
    "qs:photos_sr":2,
    "qs:placetype":"Suburb",
    "qs:pop_sr":"0",
    "qs:woe_adm0":23424852,
    "wof:name":"Shkhunat Pat",
    "wof:placetype":"neighbourhood"
},
  "geometry": {"coordinates":[35.207233,31.74872],"type":"Point"}
}