{
  "type": "Feature",
  "properties": {
    "gn:admin1_code":"03",
    "gn:asciiname":"Sawa`id",
    "gn:country_code":"IL",
    "gn:dem":550,
    "gn:feature_class":"P",
    "gn:feature_code":"PPL",
    "gn:name":"Sawa\u2018id",
    "gn:population":0,
    "gn:timezone":"Asia/Jerusalem",
    "iso:country":"IL",
    "name:heb_x_preferred":[
        "Sawa\u2018id"
    ],
    "name:heb_x_variant":[
        "\u05e1\u05d5\u05e2\u05d3"
    ],
    "name:und_x_variant":[
        "Saw\u0101\u2018id"
    ],
    "wof:name":"Sawa`id",
    "wof:placetype":"locality"
},
  "geometry": {"coordinates":[35.33553,32.90823],"type":"Point"}
}