{
  "type": "Feature",
  "properties": {
    "iso:country":"IL",
    "name:ceb_x_preferred":[
        "Yanuv"
    ],
    "name:ces_x_preferred":[
        "Januv"
    ],
    "name:eng_x_preferred":[
        "Yanuv"
    ],
    "name:heb_x_preferred":[
        "\u05d9\u05e0\u05d5\u05d1"
    ],
    "name:nno_x_preferred":[
        "Yanuv"
    ],
    "name:pol_x_preferred":[
        "Januw"
    ],
    "name:pol_x_variant":[
        "Yanuv"
    ],
    "name:swe_x_preferred":[
        "Yanuv"
    ],
    "name:und_x_variant":[
        "Fardis Nabulsi"
    ],
    "qs:gn_country":"IL",
    "qs:gn_fcode":"PPL",
    "qs:gn_pop":0,
    "qs:name":"Yanuv",
    "qs:name_adm0":"Israel",
    "qs:name_adm1":"Central",
    "qs:photos":0,
    "qs:photos_1k":0,
    "qs:photos_9k":0,
    "qs:photos_9r":0,
    "qs:photos_all":0,
    "qs:photos_sr":0,
    "qs:placetype":"Town",
    "qs:pop_sr":"0",
    "qs:woe_adm0":23424852,
    "wd:wordcount":235,
    "wof:name":"Yanuv",
    "wof:placetype":"locality"
},
  "geometry": {"coordinates":[34.9503,32.30627],"type":"Point"}
}