{
  "type": "Feature",
  "properties": {
    "gn:admin1_code":"03",
    "gn:asciiname":"Rummana",
    "gn:country_code":"IL",
    "gn:dem":183,
    "gn:feature_class":"P",
    "gn:feature_code":"PPL",
    "gn:name":"Rumm\u0101na",
    "gn:population":0,
    "gn:timezone":"Asia/Jerusalem",
    "iso:country":"IL",
    "name:ces_x_preferred":[
        "Rum\u00e1na"
    ],
    "name:fas_x_preferred":[
        "\u0631\u0645\u0627\u0646\u0647"
    ],
    "name:heb_x_preferred":[
        "\u05e8\u05de\u05e0\u05d4"
    ],
    "name:heb_x_variant":[
        "\u05e8\u05de\u05d5\u05df",
        "\u05e8\u05d5\u05de\u05d0\u05e0\u05d4"
    ],
    "name:nld_x_preferred":[
        "Roumana"
    ],
    "name:pol_x_preferred":[
        "Rummana"
    ],
    "name:rus_x_preferred":[
        "\u0420\u0443\u043c\u0430\u043d\u0430"
    ],
    "name:und_x_variant":[
        "Rumanah",
        "Rumm\u0101ne",
        "Rimmon",
        "Rumm\u0101na"
    ],
    "wof:name":"Rummana",
    "wof:placetype":"locality"
},
  "geometry": {"coordinates":[35.31091,32.78783],"type":"Point"}
}