{
  "type": "Feature",
  "properties": {
    "iso:country":"IL",
    "name:ces_x_preferred":[
        "Zichron Josef"
    ],
    "name:slk_x_preferred":[
        "Zichron Josef"
    ],
    "qs:gn_pop":0,
    "qs:name":"Zikhron Yosef",
    "qs:name_adm0":"Israel",
    "qs:name_adm1":"Jerusalem",
    "qs:photos":256,
    "qs:photos_1k":52,
    "qs:photos_9k":1,
    "qs:photos_9r":4,
    "qs:photos_all":256,
    "qs:photos_sr":5,
    "qs:placetype":"Suburb",
    "qs:pop_sr":"0",
    "qs:woe_adm0":23424852,
    "wd:wordcount":159,
    "wof:name":"Zikhron Yosef",
    "wof:placetype":"neighbourhood"
},
  "geometry": {"coordinates":[35.208263,31.7848],"type":"Point"}
}