{
  "type": "Feature",
  "properties": {
    "iso:country":"IL",
    "name:ces_x_preferred":[
        "Bustan ha-Galil"
    ],
    "name:cze_x_preferred":[
        "Bustan ha-Galil"
    ],
    "name:eng_x_preferred":[
        "Bustan HaGalil"
    ],
    "name:heb_x_preferred":[
        "\u05d1\u05d5\u05e1\u05ea\u05df \u05d4\u05d2\u05dc\u05d9\u05dc"
    ],
    "name:heb_x_variant":[
        "\u05d1\u05e1\u05ea\u05df \u05d4\u05d2\u05dc\u05d9\u05dc"
    ],
    "name:nno_x_preferred":[
        "Bustan HaGalil"
    ],
    "name:pol_x_preferred":[
        "Bustan HaGalil"
    ],
    "name:swe_x_preferred":[
        "Bustan HaGalil"
    ],
    "name:unk_x_variant":[
        "Bustan"
    ],
    "qs:gn_country":"IL",
    "qs:gn_fcode":"PPL",
    "qs:gn_pop":0,
    "qs:name":"Bustan HaGalil",
    "qs:name_adm0":"Israel",
    "qs:name_adm1":"Northern",
    "qs:photos":4549,
    "qs:photos_1k":922,
    "qs:photos_9k":20,
    "qs:photos_9r":13,
    "qs:photos_all":4549,
    "qs:photos_sr":23,
    "qs:placetype":"Town",
    "qs:pop_sr":"0",
    "qs:woe_adm0":23424852,
    "wd:wordcount":185,
    "wof:name":"Bustan HaGalil",
    "wof:placetype":"locality"
},
  "geometry": {"coordinates":[35.08076,32.95385],"type":"Point"}
}