{
  "type": "Feature",
  "properties": {
    "gn:admin1_code":"02",
    "gn:asciiname":"Hibbat Ziyyon",
    "gn:country_code":"IL",
    "gn:dem":38,
    "gn:feature_class":"P",
    "gn:feature_code":"PPL",
    "gn:name":"H\u0331ibbat \u1e94iyyon",
    "gn:population":0,
    "gn:timezone":"Asia/Jerusalem",
    "iso:country":"IL",
    "name:ces_x_preferred":[
        "Chibat Cijon"
    ],
    "name:deu_x_preferred":[
        "Chibbat Zion"
    ],
    "name:heb_x_preferred":[
        "H\u0331ibbat \u1e94iyyon"
    ],
    "name:heb_x_variant":[
        "\u05d7\u05d1\u05ea \u05e6\u05d9\u05d5\u05df",
        "\u05d7\u05d9\u05d1\u05ea \u05e6\u05d9\u05d5\u05df"
    ],
    "name:nno_x_preferred":[
        "Hibat Tzion"
    ],
    "name:pol_x_preferred":[
        "Chibbat Cijjon"
    ],
    "name:und_x_variant":[
        "\u1e24ibat Zion",
        "Hibat Tsiyon",
        "\u1e24ibbat Zion",
        "\u1e24ibat Tsion"
    ],
    "wof:name":"Hibbat Ziyyon",
    "wof:placetype":"locality"
},
  "geometry": {"coordinates":[34.91249000000001,32.39731],"type":"Point"}
}