{
  "type": "Feature",
  "properties": {
    "gn:admin1_code":"02",
    "gn:asciiname":"Elyashiv",
    "gn:country_code":"IL",
    "gn:dem":26,
    "gn:feature_class":"P",
    "gn:feature_code":"PPL",
    "gn:name":"Elyashiv",
    "gn:population":0,
    "gn:timezone":"Asia/Jerusalem",
    "iso:country":"IL",
    "name:ces_x_preferred":[
        "Elja\u0161iv"
    ],
    "name:heb_x_preferred":[
        "\u05d0\u05dc\u05d9\u05e9\u05d9\u05d1"
    ],
    "name:nno_x_preferred":[
        "Eliashiv"
    ],
    "name:pol_x_preferred":[
        "Eljasziw"
    ],
    "wof:name":"Elyashiv",
    "wof:placetype":"locality"
},
  "geometry": {"coordinates":[34.90883,32.38108],"type":"Point"}
}