{
  "type": "Feature",
  "properties": {
    "iso:country":"IL",
    "name:ces_x_preferred":[
        "Becet"
    ],
    "name:eng_x_preferred":[
        "Betzet"
    ],
    "name:heb_x_preferred":[
        "\u05d1\u05e6\u05ea"
    ],
    "name:heb_x_variant":[
        "Be\u1e95et"
    ],
    "name:nno_x_preferred":[
        "Betzet"
    ],
    "name:pol_x_preferred":[
        "Betzet"
    ],
    "name:pol_x_variant":[
        "Becet"
    ],
    "name:und_x_variant":[
        "Al Bassa"
    ],
    "qs:gn_country":"IL",
    "qs:gn_fcode":"PPL",
    "qs:gn_pop":0,
    "qs:name":"Bezet",
    "qs:name_adm0":"Israel",
    "qs:name_adm1":"Northern",
    "qs:photos":42,
    "qs:photos_1k":9,
    "qs:photos_9k":1,
    "qs:photos_9r":2,
    "qs:photos_all":42,
    "qs:photos_sr":2,
    "qs:placetype":"Town",
    "qs:pop_sr":"0",
    "qs:woe_adm0":23424852,
    "wd:wordcount":271,
    "wof:name":"Bezet",
    "wof:placetype":"locality"
},
  "geometry": {"coordinates":[35.13587,33.06847],"type":"Point"}
}