{
  "type": "Feature",
  "properties": {
    "gn:admin1_code":"04",
    "gn:asciiname":"`Ar`ara",
    "gn:country_code":"IL",
    "gn:dem":163,
    "gn:feature_class":"P",
    "gn:feature_code":"PPL",
    "gn:name":"\u2018Ar\u2018ara",
    "gn:population":0,
    "gn:timezone":"Asia/Jerusalem",
    "iso:country":"IL",
    "name:ara_x_preferred":[
        "\u0639\u0631\u0639\u0631\u0629"
    ],
    "name:cat_x_preferred":[
        "Arara"
    ],
    "name:ces_x_preferred":[
        "Ar'ara"
    ],
    "name:fra_x_preferred":[
        "Ar'ara"
    ],
    "name:heb_x_preferred":[
        "\u2018Ar\u2018ara"
    ],
    "name:heb_x_variant":[
        "\u05e2\u05e8\u05e2\u05e8\u05d4",
        "Ar\u2019ara"
    ],
    "name:nno_x_preferred":[
        "Ar'ara"
    ],
    "name:pol_x_preferred":[
        "Arara"
    ],
    "name:rus_x_preferred":[
        "\u0410\u0440\u0430\u0440\u0430"
    ],
    "name:sco_x_preferred":[
        "Ar'ara"
    ],
    "name:spa_x_preferred":[
        "Ar'ara"
    ],
    "name:und_x_variant":[
        "\u2018Ar\u2018arah",
        "\u2018Ar\u2018ara"
    ],
    "wof:name":"`Ar`ara",
    "wof:placetype":"locality"
},
  "geometry": {"coordinates":[35.09411,32.49553],"type":"Point"}
}