{
  "type": "Feature",
  "properties": {
    "iso:country":"IL",
    "name:ces_x_preferred":[
        "Ja'ara"
    ],
    "name:eng_x_preferred":[
        "Ya'ara"
    ],
    "name:fra_x_preferred":[
        "Ya'ara"
    ],
    "name:heb_x_preferred":[
        "Ya\u2018ara"
    ],
    "name:heb_x_variant":[
        "\u05d9\u05e2\u05e8\u05d4",
        "Ya\u2019rah"
    ],
    "name:nno_x_preferred":[
        "Ya'ara"
    ],
    "name:pol_x_preferred":[
        "Ja'ara"
    ],
    "name:und_x_variant":[
        "Ya\u2018arah"
    ],
    "qs:gn_country":"IL",
    "qs:gn_fcode":"PPL",
    "qs:gn_pop":0,
    "qs:name":"Yaara",
    "qs:name_adm0":"Israel",
    "qs:name_adm1":"Northern",
    "qs:photos":93,
    "qs:photos_1k":19,
    "qs:photos_9k":1,
    "qs:photos_9r":3,
    "qs:photos_all":93,
    "qs:photos_sr":3,
    "qs:placetype":"Town",
    "qs:pop_sr":"0",
    "qs:woe_adm0":23424852,
    "wof:name":"Yaara",
    "wof:placetype":"locality"
},
  "geometry": {"coordinates":[35.18704,33.06755],"type":"Point"}
}