{
  "type": "Feature",
  "properties": {
    "gn:admin1_code":"01",
    "gn:asciiname":"Metar",
    "gn:country_code":"IL",
    "gn:dem":421,
    "gn:feature_class":"P",
    "gn:feature_code":"PPL",
    "gn:name":"Metar",
    "gn:population":0,
    "gn:timezone":"Asia/Jerusalem",
    "iso:country":"IL",
    "name:heb_x_preferred":[
        "\u05de\u05d9\u05ea\u05e8"
    ],
    "wof:name":"Metar",
    "wof:placetype":"locality"
},
  "geometry": {"coordinates":[34.93945,31.3264],"type":"Point"}
}